Workbook
Name JR_PAGE_ANCHOR_0_1: #REF!

Sheet 办事处汇总
A1: 西北大区服务收入统计7.28-8.9
A2: 办事处 | B2: 清洗保养 | C2: 延保服务 | D2: 止回阀 | E2: 装饰罩 | F2: 清洁耗材 | G2: 水/气路金属软管 | H2: 其他产品线专用 | I2: 排烟出风管 | J2: 其他水路辅材 | K2: 其他气路辅材 | L2: 橱柜类辅材 | M2: 水气路通用辅材 | N2: 燃气管快速接头 | O2: 工具 | P2: 合计 | Q2: 7月任务 | R2: 服务收入完成进度 | S2: 120% 每天完成 | T2: 三大爆品合计 | U2: 三大爆品任务 | V2: 三大爆品 完成率
A3: 包头办事处 | B3: =SUMIFS(CSM服务项目!Y:Y,CSM服务项目!Q:Q,$B$2,CSM服务项目!B:B,A3) -> 1453 | C3: =SUMIFS(CSM服务项目!Y:Y,CSM服务项目!Q:Q,$C$2,CSM服务项目!B:B,A3) -> 343.5 | D3: =SUMIFS(CSM配件!AB:AB,CSM配件!R:R,$D$2,CSM配件!C:C,A3) -> 3760 | E3: =SUMIFS(CSM配件!AB:AB,CSM配件!R:R,$E$2,CSM配件!C:C,A3) -> 0 | F3: =SUMIFS(CSM配件!AB:AB,CSM配件!R:R,$F$2,CSM配件!C:C,A3)+SUMIFS(WMS网点买断配件明细!I:I,WMS网点买断配件明细!K:K,$F$2,WMS网点买断配件明细!B:B,A3) -> 2528 | G3: =SUMIFS(CSM配件!AB:AB,CSM配件!R:R,$G$2,CSM配件!C:C,A3)+SUMIFS(WMS网点买断配件明细!I:I,WMS网点买断配件明细!K:K,$G$2,WMS网点买断配件明细!B:B,A3) -> 408.21 | H3: =SUMIFS(CSM配件!AB:AB,CSM配件!R:R,$H$2,CSM配件!C:C,A3)+SUMIFS(WMS网点买断配件明细!I:I,WMS网点买断配件明细!K:K,$H$2,WMS网点买断配件明细!B:B,A3) -> 4249 | I3: =SUMIFS(CSM配件!AB:AB,CSM配件!R:R,$I$2,CSM配件!C:C,A3)+SUMIFS(WMS网点买断配件明细!I:I,WMS网点买断配件明细!K:K,$I$2,WMS网点买断配件明细!B:B,A3) -> 372 | J3: =SUMIFS(CSM配件!AB:AB,CSM配件!R:R,$J$2,CSM配件!C:C,A3)+SUMIFS(WMS网点买断配件明细!I:I,WMS网点买断配件明细!K:K,$J$2,WMS网点买断配件明细!B:B,A3) -> 196 | K3: =SUMIFS(CSM配件!AB:AB,CSM配件!R:R,$K$2,CSM配件!C:C,A3)+SUMIFS(WMS网点买断配件明细!I:I,WMS网点买断配件明细!K:K,$K$2,WMS网点买断配件明细!B:B,A3) -> 0 | L3: =SUMIFS(CSM配件!AB:AB,CSM配件!R:R,$L$2,CSM配件!C:C,A3)+SUMIFS(WMS网点买断配件明细!I:I,WMS网点买断配件明细!K:K,$L$2,WMS网点买断配件明细!B:B,A3) -> 155 | M3: =SUMIFS(CSM配件!AB:AB,CSM配件!R:R,$M$2,CSM配件!C:C,A3)+SUMIFS(WMS网点买断配件明细!I:I,WMS网点买断配件明细!K:K,$M$2,WMS网点买断配件明细!B:B,A3) -> 0 | N3: =SUMIFS(CSM配件!AB:AB,CSM配件!R:R,$N$2,CSM配件!C:C,A3)+SUMIFS(WMS网点买断配件明细!I:I,WMS网点买断配件明细!K:K,$N$2,WMS网点买断配件明细!B:B,A3) -> 44.4 | O3: =SUMIFS(CSM配件!AB:AB,CSM配件!R:R,$O$2,CSM配件!C:C,A3)+SUMIFS(WMS网点买断配件明细!I:I,WMS网点买断配件明细!K:K,$O$2,WMS网点买断配件明细!B:B,A3) -> 0 | P3: =SUM(B3:O3) -> 13509.11 | Q3: 35100 | R3: =P3/Q3 -> 0.38487493 | S3: =(Q3*1.2-P3)/19 -> 1505.8363 | T3: =B3+C3+F3 -> 4324.5 | U3: 12600 | V3: =T3/U3 -> 0.34321429
A4: 呼和浩特办事处 | B4: =SUMIFS(CSM服务项目!Y:Y,CSM服务项目!Q:Q,$B$2,CSM服务项目!B:B,A4) -> 2344 | C4: =SUMIFS(CSM服务项目!Y:Y,CSM服务项目!Q:Q,$C$2,CSM服务项目!B:B,A4) -> 0 | D4: =SUMIFS(CSM配件!AB:AB,CSM配件!R:R,$D$2,CSM配件!C:C,A4) -> 2880 | E4: =SUMIFS(CSM配件!AB:AB,CSM配件!R:R,$E$2,CSM配件!C:C,A4) -> 1127 | F4: =SUMIFS(CSM配件!AB:AB,CSM配件!R:R,$F$2,CSM配件!C:C,A4)+SUMIFS(WMS网点买断配件明细!I:I,WMS网点买断配件明细!K:K,$F$2,WMS网点买断配件明细!B:B,A4) -> 465 | G4: =SUMIFS(CSM配件!AB:AB,CSM配件!R:R,$G$2,CSM配件!C:C,A4)+SUMIFS(WMS网点买断配件明细!I:I,WMS网点买断配件明细!K:K,$G$2,WMS网点买断配件明细!B:B,A4) -> 662.97 | H4: =SUMIFS(CSM配件!AB:AB,CSM配件!R:R,$H$2,CSM配件!C:C,A4)+SUMIFS(WMS网点买断配件明细!I:I,WMS网点买断配件明细!K:K,$H$2,WMS网点买断配件明细!B:B,A4) -> 3732.5 | I4: =SUMIFS(CSM配件!AB:AB,CSM配件!R:R,$I$2,CSM配件!C:C,A4)+SUMIFS(WMS网点买断配件明细!I:I,WMS网点买断配件明细!K:K,$I$2,WMS网点买断配件明细!B:B,A4) -> 860.5 | J4: =SUMIFS(CSM配件!AB:AB,CSM配件!R:R,$J$2,CSM配件!C:C,A4)+SUMIFS(WMS网点买断配件明细!I:I,WMS网点买断配件明细!K:K,$J$2,WMS网点买断配件明细!B:B,A4) -> 1588 | K4: =SUMIFS(CSM配件!AB:AB,CSM配件!R:R,$K$2,CSM配件!C:C,A4)+SUMIFS(WMS网点买断配件明细!I:I,WMS网点买断配件明细!K:K,$K$2,WMS网点买断配件明细!B:B,A4) -> 0 | L4: =SUMIFS(CSM配件!AB:AB,CSM配件!R:R,$L$2,CSM配件!C:C,A4)+SUMIFS(WMS网点买断配件明细!I:I,WMS网点买断配件明细!K:K,$L$2,WMS网点买断配件明细!B:B,A4) -> 52.5 | M4: =SUMIFS(CSM配件!AB:AB,CSM配件!R:R,$M$2,CSM配件!C:C,A4)+SUMIFS(WMS网点买断配件明细!I:I,WMS网点买断配件明细!K:K,$M$2,WMS网点买断配件明细!B:B,A4) -> 0 | N4: =SUMIFS(CSM配件!AB:AB,CSM配件!R:R,$N$2,CSM配件!C:C,A4)+SUMIFS(WMS网点买断配件明细!I:I,WMS网点买断配件明细!K:K,$N$2,WMS网点买断配件明细!B:B,A4) -> 0 | O4: =SUMIFS(CSM配件!AB:AB,CSM配件!R:R,$O$2,CSM配件!C:C,A4)+SUMIFS(WMS网点买断配件明细!I:I,WMS网点买断配件明细!K:K,$O$2,WMS网点买断配件明细!B:B,A4) -> 0 | P4: =SUM(B4:O4) -> 13712.47 | Q4: 32400 | R4: =P4/Q4 -> 0.42322438 | S4: =(Q4*1.2-P4)/19 -> 1324.6068 | T4: =B4+C4+F4 -> 2809 | U4: 11700 | V4: =T4/U4 -> 0.24008547
A5: 兰州办事处 | B5: =SUMIFS(CSM服务项目!Y:Y,CSM服务项目!Q:Q,$B$2,CSM服务项目!B:B,A5) -> 4112 | C5: =SUMIFS(CSM服务项目!Y:Y,CSM服务项目!Q:Q,$C$2,CSM服务项目!B:B,A5) -> 4442.6 | D5: =SUMIFS(CSM配件!AB:AB,CSM配件!R:R,$D$2,CSM配件!C:C,A5) -> 8600 | E5: =SUMIFS(CSM配件!AB:AB,CSM配件!R:R,$E$2,CSM配件!C:C,A5) -> 1405.6 | F5: =SUMIFS(CSM配件!AB:AB,CSM配件!R:R,$F$2,CSM配件!C:C,A5)+SUMIFS(WMS网点买断配件明细!I:I,WMS网点买断配件明细!K:K,$F$2,WMS网点买断配件明细!B:B,A5) -> 675 | G5: =SUMIFS(CSM配件!AB:AB,CSM配件!R:R,$G$2,CSM配件!C:C,A5)+SUMIFS(WMS网点买断配件明细!I:I,WMS网点买断配件明细!K:K,$G$2,WMS网点买断配件明细!B:B,A5) -> 7430.7 | H5: =SUMIFS(CSM配件!AB:AB,CSM配件!R:R,$H$2,CSM配件!C:C,A5)+SUMIFS(WMS网点买断配件明细!I:I,WMS网点买断配件明细!K:K,$H$2,WMS网点买断配件明细!B:B,A5) -> 3608 | I5: =SUMIFS(CSM配件!AB:AB,CSM配件!R:R,$I$2,CSM配件!C:C,A5)+SUMIFS(WMS网点买断配件明细!I:I,WMS网点买断配件明细!K:K,$I$2,WMS网点买断配件明细!B:B,A5) -> 1184 | J5: =SUMIFS(CSM配件!AB:AB,CSM配件!R:R,$J$2,CSM配件!C:C,A5)+SUMIFS(WMS网点买断配件明细!I:I,WMS网点买断配件明细!K:K,$J$2,WMS网点买断配件明细!B:B,A5) -> 84 | K5: =SUMIFS(CSM配件!AB:AB,CSM配件!R:R,$K$2,CSM配件!C:C,A5)+SUMIFS(WMS网点买断配件明细!I:I,WMS网点买断配件明细!K:K,$K$2,WMS网点买断配件明细!B:B,A5) -> 0 | L5: =SUMIFS(CSM配件!AB:AB,CSM配件!R:R,$L$2,CSM配件!C:C,A5)+SUMIFS(WMS网点买断配件明细!I:I,WMS网点买断配件明细!K:K,$L$2,WMS网点买断配件明细!B:B,A5) -> 112 | M5: =SUMIFS(CSM配件!AB:AB,CSM配件!R:R,$M$2,CSM配件!C:C,A5)+SUMIFS(WMS网点买断配件明细!I:I,WMS网点买断配件明细!K:K,$M$2,WMS网点买断配件明细!B:B,A5) -> 0 | N5: =SUMIFS(CSM配件!AB:AB,CSM配件!R:R,$N$2,CSM配件!C:C,A5)+SUMIFS(WMS网点买断配件明细!I:I,WMS网点买断配件明细!K:K,$N$2,WMS网点买断配件明细!B:B,A5) -> 1004 | O5: =SUMIFS(CSM配件!AB:AB,CSM配件!R:R,$O$2,CSM配件!C:C,A5)+SUMIFS(WMS网点买断配件明细!I:I,WMS网点买断配件明细!K:K,$O$2,WMS网点买断配件明细!B:B,A5) -> 0 | P5: =SUM(B5:O5) -> 32657.9 | Q5: 83700 | R5: =P5/Q5 -> 0.39017802 | S5: =(Q5*1.2-P5)/19 -> 3567.4789 | T5: =B5+C5+F5 -> 9229.6 | U5: 23400 | V5: =T5/U5 -> 0.39442735
A6: 宁夏办事处 | B6: =SUMIFS(CSM服务项目!Y:Y,CSM服务项目!Q:Q,$B$2,CSM服务项目!B:B,A6) -> 7187 | C6: =SUMIFS(CSM服务项目!Y:Y,CSM服务项目!Q:Q,$C$2,CSM服务项目!B:B,A6) -> 7509.7 | D6: =SUMIFS(CSM配件!AB:AB,CSM配件!R:R,$D$2,CSM配件!C:C,A6) -> 14800 | E6: =SUMIFS(CSM配件!AB:AB,CSM配件!R:R,$E$2,CSM配件!C:C,A6) -> 441 | F6: =SUMIFS(CSM配件!AB:AB,CSM配件!R:R,$F$2,CSM配件!C:C,A6)+SUMIFS(WMS网点买断配件明细!I:I,WMS网点买断配件明细!K:K,$F$2,WMS网点买断配件明细!B:B,A6) -> 6065 | G6: =SUMIFS(CSM配件!AB:AB,CSM配件!R:R,$G$2,CSM配件!C:C,A6)+SUMIFS(WMS网点买断配件明细!I:I,WMS网点买断配件明细!K:K,$G$2,WMS网点买断配件明细!B:B,A6) -> 2577.22 | H6: =SUMIFS(CSM配件!AB:AB,CSM配件!R:R,$H$2,CSM配件!C:C,A6)+SUMIFS(WMS网点买断配件明细!I:I,WMS网点买断配件明细!K:K,$H$2,WMS网点买断配件明细!B:B,A6) -> 4460.4 | I6: =SUMIFS(CSM配件!AB:AB,CSM配件!R:R,$I$2,CSM配件!C:C,A6)+SUMIFS(WMS网点买断配件明细!I:I,WMS网点买断配件明细!K:K,$I$2,WMS网点买断配件明细!B:B,A6) -> 2090.5 | J6: =SUMIFS(CSM配件!AB:AB,CSM配件!R:R,$J$2,CSM配件!C:C,A6)+SUMIFS(WMS网点买断配件明细!I:I,WMS网点买断配件明细!K:K,$J$2,WMS网点买断配件明细!B:B,A6) -> 1539 | K6: =SUMIFS(CSM配件!AB:AB,CSM配件!R:R,$K$2,CSM配件!C:C,A6)+SUMIFS(WMS网点买断配件明细!I:I,WMS网点买断配件明细!K:K,$K$2,WMS网点买断配件明细!B:B,A6) -> 0 | L6: =SUMIFS(CSM配件!AB:AB,CSM配件!R:R,$L$2,CSM配件!C:C,A6)+SUMIFS(WMS网点买断配件明细!I:I,WMS网点买断配件明细!K:K,$L$2,WMS网点买断配件明细!B:B,A6) -> 94.5 | M6: =SUMIFS(CSM配件!AB:AB,CSM配件!R:R,$M$2,CSM配件!C:C,A6)+SUMIFS(WMS网点买断配件明细!I:I,WMS网点买断配件明细!K:K,$M$2,WMS网点买断配件明细!B:B,A6) -> 0 | N6: =SUMIFS(CSM配件!AB:AB,CSM配件!R:R,$N$2,CSM配件!C:C,A6)+SUMIFS(WMS网点买断配件明细!I:I,WMS网点买断配件明细!K:K,$N$2,WMS网点买断配件明细!B:B,A6) -> 133.2 | O6: =SUMIFS(CSM配件!AB:AB,CSM配件!R:R,$O$2,CSM配件!C:C,A6)+SUMIFS(WMS网点买断配件明细!I:I,WMS网点买断配件明细!K:K,$O$2,WMS网点买断配件明细!B:B,A6) -> 0 | P6: =SUM(B6:O6) -> 46897.52 | Q6: 111600 | R6: =P6/Q6 -> 0.42022867 | S6: =(Q6*1.2-P6)/19 -> 4580.1305 | T6: =B6+C6+F6 -> 20761.7 | U6: 35100 | V6: =T6/U6 -> 0.59150142
A7: 西宁办事处 | B7: =SUMIFS(CSM服务项目!Y:Y,CSM服务项目!Q:Q,$B$2,CSM服务项目!B:B,A7) -> 150 | C7: =SUMIFS(CSM服务项目!Y:Y,CSM服务项目!Q:Q,$C$2,CSM服务项目!B:B,A7) -> 2633.5 | D7: =SUMIFS(CSM配件!AB:AB,CSM配件!R:R,$D$2,CSM配件!C:C,A7) -> 900 | E7: =SUMIFS(CSM配件!AB:AB,CSM配件!R:R,$E$2,CSM配件!C:C,A7) -> 0 | F7: =SUMIFS(CSM配件!AB:AB,CSM配件!R:R,$F$2,CSM配件!C:C,A7)+SUMIFS(WMS网点买断配件明细!I:I,WMS网点买断配件明细!K:K,$F$2,WMS网点买断配件明细!B:B,A7) -> 132 | G7: =SUMIFS(CSM配件!AB:AB,CSM配件!R:R,$G$2,CSM配件!C:C,A7)+SUMIFS(WMS网点买断配件明细!I:I,WMS网点买断配件明细!K:K,$G$2,WMS网点买断配件明细!B:B,A7) -> 0 | H7: =SUMIFS(CSM配件!AB:AB,CSM配件!R:R,$H$2,CSM配件!C:C,A7)+SUMIFS(WMS网点买断配件明细!I:I,WMS网点买断配件明细!K:K,$H$2,WMS网点买断配件明细!B:B,A7) -> 1126.5 | I7: =SUMIFS(CSM配件!AB:AB,CSM配件!R:R,$I$2,CSM配件!C:C,A7)+SUMIFS(WMS网点买断配件明细!I:I,WMS网点买断配件明细!K:K,$I$2,WMS网点买断配件明细!B:B,A7) -> 591.5 | J7: =SUMIFS(CSM配件!AB:AB,CSM配件!R:R,$J$2,CSM配件!C:C,A7)+SUMIFS(WMS网点买断配件明细!I:I,WMS网点买断配件明细!K:K,$J$2,WMS网点买断配件明细!B:B,A7) -> 0 | K7: =SUMIFS(CSM配件!AB:AB,CSM配件!R:R,$K$2,CSM配件!C:C,A7)+SUMIFS(WMS网点买断配件明细!I:I,WMS网点买断配件明细!K:K,$K$2,WMS网点买断配件明细!B:B,A7) -> 0 | L7: =SUMIFS(CSM配件!AB:AB,CSM配件!R:R,$L$2,CSM配件!C:C,A7)+SUMIFS(WMS网点买断配件明细!I:I,WMS网点买断配件明细!K:K,$L$2,WMS网点买断配件明细!B:B,A7) -> 0 | M7: =SUMIFS(CSM配件!AB:AB,CSM配件!R:R,$M$2,CSM配件!C:C,A7)+SUMIFS(WMS网点买断配件明细!I:I,WMS网点买断配件明细!K:K,$M$2,WMS网点买断配件明细!B:B,A7) -> 0 | N7: =SUMIFS(CSM配件!AB:AB,CSM配件!R:R,$N$2,CSM配件!C:C,A7)+SUMIFS(WMS网点买断配件明细!I:I,WMS网点买断配件明细!K:K,$N$2,WMS网点买断配件明细!B:B,A7) -> 0 | O7: =SUMIFS(CSM配件!AB:AB,CSM配件!R:R,$O$2,CSM配件!C:C,A7)+SUMIFS(WMS网点买断配件明细!I:I,WMS网点买断配件明细!K:K,$O$2,WMS网点买断配件明细!B:B,A7) -> 0 | P7: =SUM(B7:O7) -> 5533.5 | Q7: 14400 | R7: =P7/Q7 -> 0.38427083 | S7: =(Q7*1.2-P7)/19 -> 618.23684 | T7: =B7+C7+F7 -> 2915.5 | U7: 4500 | V7: =T7/U7 -> 0.64788889
A8: 新疆办事处 | B8: =SUMIFS(CSM服务项目!Y:Y,CSM服务项目!Q:Q,$B$2,CSM服务项目!B:B,A8) -> 19558 | C8: =SUMIFS(CSM服务项目!Y:Y,CSM服务项目!Q:Q,$C$2,CSM服务项目!B:B,A8) -> 7236.4 | D8: =SUMIFS(CSM配件!AB:AB,CSM配件!R:R,$D$2,CSM配件!C:C,A8) -> 22500 | E8: =SUMIFS(CSM配件!AB:AB,CSM配件!R:R,$E$2,CSM配件!C:C,A8) -> 411.6 | F8: =SUMIFS(CSM配件!AB:AB,CSM配件!R:R,$F$2,CSM配件!C:C,A8)+SUMIFS(WMS网点买断配件明细!I:I,WMS网点买断配件明细!K:K,$F$2,WMS网点买断配件明细!B:B,A8) -> 3875 | G8: =SUMIFS(CSM配件!AB:AB,CSM配件!R:R,$G$2,CSM配件!C:C,A8)+SUMIFS(WMS网点买断配件明细!I:I,WMS网点买断配件明细!K:K,$G$2,WMS网点买断配件明细!B:B,A8) -> 7755.99 | H8: =SUMIFS(CSM配件!AB:AB,CSM配件!R:R,$H$2,CSM配件!C:C,A8)+SUMIFS(WMS网点买断配件明细!I:I,WMS网点买断配件明细!K:K,$H$2,WMS网点买断配件明细!B:B,A8) -> 8555 | I8: =SUMIFS(CSM配件!AB:AB,CSM配件!R:R,$I$2,CSM配件!C:C,A8)+SUMIFS(WMS网点买断配件明细!I:I,WMS网点买断配件明细!K:K,$I$2,WMS网点买断配件明细!B:B,A8) -> 5281 | J8: =SUMIFS(CSM配件!AB:AB,CSM配件!R:R,$J$2,CSM配件!C:C,A8)+SUMIFS(WMS网点买断配件明细!I:I,WMS网点买断配件明细!K:K,$J$2,WMS网点买断配件明细!B:B,A8) -> 1750 | K8: =SUMIFS(CSM配件!AB:AB,CSM配件!R:R,$K$2,CSM配件!C:C,A8)+SUMIFS(WMS网点买断配件明细!I:I,WMS网点买断配件明细!K:K,$K$2,WMS网点买断配件明细!B:B,A8) -> 0 | L8: =SUMIFS(CSM配件!AB:AB,CSM配件!R:R,$L$2,CSM配件!C:C,A8)+SUMIFS(WMS网点买断配件明细!I:I,WMS网点买断配件明细!K:K,$L$2,WMS网点买断配件明细!B:B,A8) -> 224 | M8: =SUMIFS(CSM配件!AB:AB,CSM配件!R:R,$M$2,CSM配件!C:C,A8)+SUMIFS(WMS网点买断配件明细!I:I,WMS网点买断配件明细!K:K,$M$2,WMS网点买断配件明细!B:B,A8) -> 0 | N8: =SUMIFS(CSM配件!AB:AB,CSM配件!R:R,$N$2,CSM配件!C:C,A8)+SUMIFS(WMS网点买断配件明细!I:I,WMS网点买断配件明细!K:K,$N$2,WMS网点买断配件明细!B:B,A8) -> 2461 | O8: =SUMIFS(CSM配件!AB:AB,CSM配件!R:R,$O$2,CSM配件!C:C,A8)+SUMIFS(WMS网点买断配件明细!I:I,WMS网点买断配件明细!K:K,$O$2,WMS网点买断配件明细!B:B,A8) -> 0 | P8: =SUM(B8:O8) -> 79607.99 | Q8: 168300 | R8: =P8/Q8 -> 0.47301242 | S8: =(Q8*1.2-P8)/19 -> 6439.5795 | T8: =B8+C8+F8 -> 30669.4 | U8: 48600 | V8: =T8/U8 -> 0.63105761
A9: 西北大区部 | B9: =SUM(B3:B8) -> 34804 | C9: =SUM(C3:C8) -> 22165.7 | D9: =SUM(D3:D8) -> 53440 | E9: =SUM(E3:E8) -> 3385.2 | F9: =SUM(F3:F8) -> 13740 | G9: =SUM(G3:G8) -> 18835.09 | H9: =SUM(H3:H8) -> 25731.4 | I9: =SUM(I3:I8) -> 10379.5 | ... Q9: =SUM(Q3:Q8) -> 445500 | R9: =P9/Q9 -> 0.43079347 | S9: =(Q9*1.2-P9)/19 -> 18035.869 | T9: =SUM(T3:T8) -> 70709.7 | U9: =SUM(U3:U8) -> 135900 | V9: =T9/U9 -> 0.52030684

Sheet 服务产品+三大爆品
A1: 服务产品完成情况 | J1: 三大爆品完成情况
A2: 办事处 | B2: 1-7月 完成 | C2: 8月份 达成 | D2: 8月份 目标 | E2: 8月 完成率 | F2: 累计达成 | G2: 全年目标 | H2: 距离120%差值 | I2: 年度完 成进度 | J2: 1-7月 完成 | K2: 8月份 达成 | L2: 8月份 目标 | M2: 8月 完成率 | N2: 累计达成 | O2: 全年目标 | P2: 年度完 成进度
A3: 包头办事处 | B3: =19.564417+3.235077 -> 22.799494 | C3: 0 | D3: 3.51 | E3: =C3/D3 -> 0 | F3: =B3+C3 -> 22.799494 | G3: 39 | H3: =G3*1.2-F3 -> 24.000506 | I3: =F3/G3 -> 0.58460241 | J3: =8.1701+0.9251 -> 9.0952 | K3: 0 | L3: 1.26 | M3: =K3/L3 -> 0 | N3: =J3+K3 -> 9.0952 | O3: 14 | P3: =N3/O3 -> 0.64965714
A4: 呼和浩特办事处 | B4: =18.522305+3.704106 -> 22.226411 | C4: 0 | D4: 3.24 | E4: =C4/D4 -> 0 | F4: =B4+C4 -> 22.226411 | G4: 36 | H4: =G4*1.2-F4 -> 20.973589 | I4: =F4/G4 -> 0.61740031 | J4: =6.52498+0.71624 -> 7.24122 | K4: 0 | L4: 1.17 | M4: =K4/L4 -> 0 | N4: =J4+K4 -> 7.24122 | O4: 13 | P4: =N4/O4 -> 0.55701692
A5: 兰州办事处 | B5: =39.291882+6.801145 -> 46.093027 | C5: 0 | D5: 8.37 | E5: =C5/D5 -> 0 | F5: =B5+C5 -> 46.093027 | G5: 93 | H5: =G5*1.2-F5 -> 65.506973 | I5: =F5/G5 -> 0.49562395 | J5: =12.9608+1.66925 -> 14.63005 | K5: 0 | L5: 2.34 | M5: =K5/L5 -> 0 | N5: =J5+K5 -> 14.63005 | O5: 26 | P5: =N5/O5 -> 0.56269423
A6: 宁夏办事处 | B6: =64.731382+10.771978 -> 75.50336 | C6: 0 | D6: 11.16 | E6: =C6/D6 -> 0 | F6: =B6+C6 -> 75.50336 | G6: 124 | H6: =G6*1.2-F6 -> 73.29664 | I6: =F6/G6 -> 0.60889806 | J6: =27.88965+4.74917 -> 32.63882 | K6: 0 | L6: 3.51 | M6: =K6/L6 -> 0 | N6: =J6+K6 -> 32.63882 | O6: 39 | P6: =N6/O6 -> 0.83689282
A7: 西宁办事处 | B7: =6.551844+1.596426 -> 8.14827 | C7: 0 | D7: 1.44 | E7: =C7/D7 -> 0 | F7: =B7+C7 -> 8.14827 | G7: 16 | H7: =G7*1.2-F7 -> 11.05173 | I7: =F7/G7 -> 0.50926688 | J7: =1.90205+0.49436 -> 2.39641 | K7: 0 | L7: 0.45 | M7: =K7/L7 -> 0 | N7: =J7+K7 -> 2.39641 | O7: 5 | P7: =N7/O7 -> 0.479282
A8: 新疆办事处 | B8: =84.612167+17.218253 -> 101.83042 | C8: 0 | D8: 16.83 | E8: =C8/D8 -> 0 | F8: =B8+C8 -> 101.83042 | G8: 187 | H8: =G8*1.2-F8 -> 122.56958 | I8: =F8/G8 -> 0.5445477 | J8: =27.58084+5.16552 -> 32.74636 | K8: 0 | L8: 4.86 | M8: =K8/L8 -> 0 | N8: =J8+K8 -> 32.74636 | O8: 54 | P8: =N8/O8 -> 0.60641407
A9: 小计 | B9: =SUM(B3:B8) -> 276.60098 | C9: =SUM(C3:C8) -> 0 | D9: =SUM(D3:D8) -> 44.55 | E9: =C9/D9 -> 0 | F9: =SUM(F3:F8) -> 276.60098 | G9: =SUM(G3:G8) -> 495 | H9: =G9*1.2-F9 -> 317.39902 | I9: =F9/G9 -> 0.55878986 | J9: =SUM(J3:J8) -> 98.74806 | K9: =SUM(K3:K8) -> 0 | L9: =SUM(L3:L8) -> 13.59 | M9: =K9/L9 -> 0 | N9: =SUM(N3:N8) -> 98.74806 | O9: =SUM(O3:O8) -> 151 | P9: =N9/O9 -> 0.65396066

Sheet 服务产品3+1
A1: 服务产品3+1
A2: 办事处 | B2: 清洗保养 | F2: 延保服务 | J2: 清洁耗材 | N2: 止回阀
B3: 46235 | C3: 45870 | D3: 差值 | E3: 同比 | F3: 46235 | G3: 45870 | H3: 差值 | I3: 同比 | J3: 46235 | K3: 45870 | L3: 差值 | M3: 同比 | N3: 46235 | O3: 46235 | P3: 差值 | Q3: 同比
A4: 包头办事处 | B4: =SUMIFS(CSM服务项目!Y:Y,CSM服务项目!Q:Q,$B$2,CSM服务项目!B:B,A4) -> 1453 | C4: 3572 | D4: =B4-C4 -> -2119 | E4: =B4/C4-1 -> -0.59322508 | F4: =SUMIFS(CSM服务项目!Y:Y,CSM服务项目!Q:Q,$F$2,CSM服务项目!B:B,A4) -> 343.5 | G4: 855.3 | H4: =F4-G4 -> -511.8 | I4: =F4/G4-1 -> -0.59838653 | J4: =SUMIFS(CSM配件!AB:AB,CSM配件!R:R,$J$2,CSM配件!C:C,A4)+SUMIFS(WMS网点买断配件明细!I:I,WMS网点买断配件明细!K:K,$J$2,WMS网点买断配件明细!B:B,A4) -> 2528 | K4: 3580 | L4: =J4-K4 -> -1052 | M4: =J4/K4-1 -> -0.29385475 | N4: =SUMIFS(CSM配件!AB:AB,CSM配件!R:R,$N$2,CSM配件!C:C,A4) -> 3760 | O4: 9460 | P4: =N4-O4 -> -5700 | Q4: =N4/O4-1 -> -0.602537
A5: 呼和浩特办事处 | B5: =SUMIFS(CSM服务项目!Y:Y,CSM服务项目!Q:Q,$B$2,CSM服务项目!B:B,A5) -> 2344 | C5: 6440 | D5: =B5-C5 -> -4096 | E5: =B5/C5-1 -> -0.63602484 | F5: =SUMIFS(CSM服务项目!Y:Y,CSM服务项目!Q:Q,$F$2,CSM服务项目!B:B,A5) -> 0 | G5: 389.3 | H5: =F5-G5 -> -389.3 | I5: =F5/G5-1 -> -1 | J5: =SUMIFS(CSM配件!AB:AB,CSM配件!R:R,$J$2,CSM配件!C:C,A5)+SUMIFS(WMS网点买断配件明细!I:I,WMS网点买断配件明细!K:K,$J$2,WMS网点买断配件明细!B:B,A5) -> 465 | K5: 1550 | L5: =J5-K5 -> -1085 | M5: =J5/K5-1 -> -0.7 | N5: =SUMIFS(CSM配件!AB:AB,CSM配件!R:R,$N$2,CSM配件!C:C,A5) -> 2880 | O5: 3740 | P5: =N5-O5 -> -860 | Q5: =N5/O5-1 -> -0.22994652
A6: 兰州办事处 | B6: =SUMIFS(CSM服务项目!Y:Y,CSM服务项目!Q:Q,$B$2,CSM服务项目!B:B,A6) -> 4112 | C6: 11413 | D6: =B6-C6 -> -7301 | E6: =B6/C6-1 -> -0.6397091 | F6: =SUMIFS(CSM服务项目!Y:Y,CSM服务项目!Q:Q,$F$2,CSM服务项目!B:B,A6) -> 4442.6 | G6: 2061 | H6: =F6-G6 -> 2381.6 | I6: =F6/G6-1 -> 1.1555556 | J6: =SUMIFS(CSM配件!AB:AB,CSM配件!R:R,$J$2,CSM配件!C:C,A6)+SUMIFS(WMS网点买断配件明细!I:I,WMS网点买断配件明细!K:K,$J$2,WMS网点买断配件明细!B:B,A6) -> 675 | K6: 886 | L6: =J6-K6 -> -211 | M6: =J6/K6-1 -> -0.23814898 | N6: =SUMIFS(CSM配件!AB:AB,CSM配件!R:R,$N$2,CSM配件!C:C,A6) -> 8600 | O6: 26500 | P6: =N6-O6 -> -17900 | Q6: =N6/O6-1 -> -0.6754717
A7: 宁夏办事处 | B7: =SUMIFS(CSM服务项目!Y:Y,CSM服务项目!Q:Q,$B$2,CSM服务项目!B:B,A7) -> 7187 | C7: 15243 | D7: =B7-C7 -> -8056 | E7: =B7/C7-1 -> -0.52850489 | F7: =SUMIFS(CSM服务项目!Y:Y,CSM服务项目!Q:Q,$F$2,CSM服务项目!B:B,A7) -> 7509.7 | G7: 1885.8 | H7: =F7-G7 -> 5623.9 | I7: =F7/G7-1 -> 2.9822357 | J7: =SUMIFS(CSM配件!AB:AB,CSM配件!R:R,$J$2,CSM配件!C:C,A7)+SUMIFS(WMS网点买断配件明细!I:I,WMS网点买断配件明细!K:K,$J$2,WMS网点买断配件明细!B:B,A7) -> 6065 | K7: 8850 | L7: =J7-K7 -> -2785 | M7: =J7/K7-1 -> -0.31468927 | N7: =SUMIFS(CSM配件!AB:AB,CSM配件!R:R,$N$2,CSM配件!C:C,A7) -> 14800 | O7: 37400 | P7: =N7-O7 -> -22600 | Q7: =N7/O7-1 -> -0.60427807
A8: 西宁办事处 | B8: =SUMIFS(CSM服务项目!Y:Y,CSM服务项目!Q:Q,$B$2,CSM服务项目!B:B,A8) -> 150 | C8: 150 | D8: =B8-C8 -> 0 | E8: =B8/C8-1 -> 0 | F8: =SUMIFS(CSM服务项目!Y:Y,CSM服务项目!Q:Q,$F$2,CSM服务项目!B:B,A8) -> 2633.5 | G8: 0 | H8: =F8-G8 -> 2633.5 | I8: =F8/G8-1 -> #DIV/0! | J8: =SUMIFS(CSM配件!AB:AB,CSM配件!R:R,$J$2,CSM配件!C:C,A8)+SUMIFS(WMS网点买断配件明细!I:I,WMS网点买断配件明细!K:K,$J$2,WMS网点买断配件明细!B:B,A8) -> 132 | K8: 936 | L8: =J8-K8 -> -804 | M8: =J8/K8-1 -> -0.85897436 | N8: =SUMIFS(CSM配件!AB:AB,CSM配件!R:R,$N$2,CSM配件!C:C,A8) -> 900 | O8: 5560 | P8: =N8-O8 -> -4660 | Q8: =N8/O8-1 -> -0.8381295
A9: 新疆办事处 | B9: =SUMIFS(CSM服务项目!Y:Y,CSM服务项目!Q:Q,$B$2,CSM服务项目!B:B,A9) -> 19558 | C9: 38500 | D9: =B9-C9 -> -18942 | E9: =B9/C9-1 -> -0.492 | F9: =SUMIFS(CSM服务项目!Y:Y,CSM服务项目!Q:Q,$F$2,CSM服务项目!B:B,A9) -> 7236.4 | G9: 1374 | H9: =F9-G9 -> 5862.4 | I9: =F9/G9-1 -> 4.2666667 | J9: =SUMIFS(CSM配件!AB:AB,CSM配件!R:R,$J$2,CSM配件!C:C,A9)+SUMIFS(WMS网点买断配件明细!I:I,WMS网点买断配件明细!K:K,$J$2,WMS网点买断配件明细!B:B,A9) -> 3875 | K9: 3619 | L9: =J9-K9 -> 256 | M9: =J9/K9-1 -> 0.070737773 | N9: =SUMIFS(CSM配件!AB:AB,CSM配件!R:R,$N$2,CSM配件!C:C,A9) -> 22500 | O9: 47280 | P9: =N9-O9 -> -24780 | Q9: =N9/O9-1 -> -0.52411168
A10: 小计 | B10: =SUM(B4:B9) -> 34804 | C10: =SUM(C4:C9) -> 75318 | D10: =B10-C10 -> -40514 | E10: =B10/C10-1 -> -0.53790595 | F10: =SUM(F4:F9) -> 22165.7 | G10: =SUM(G4:G9) -> 6565.4 | H10: =F10-G10 -> 15600.3 | I10: =F10/G10-1 -> 2.3761385 | J10: =SUM(J4:J9) -> 13740 | K10: =SUM(K4:K9) -> 19421 | L10: =J10-K10 -> -5681 | M10: =J10/K10-1 -> -0.29251841 | N10: =SUM(N4:N9) -> 53440 | O10: =SUM(O4:O9) -> 129940 | P10: =N10-O10 -> -76500 | Q10: =N10/O10-1 -> -0.58873326

Sheet 网点数据
A1: 西北大区服务网点收入统计
A2: 办事处 | B2: 服务网点 | C2: 清洗保养 | D2: 延保服务 | E2: 止回阀 | F2: 装饰罩 | G2: 清洁耗材 | H2: 水/气路金属软管 | I2: 其他产品线专用 | J2: 排烟出风管 | K2: 其他水路辅材 | L2: 其他气路辅材 | M2: 橱柜类辅材 | N2: 水气路通用辅材 | O2: 燃气管快速接头 | P2: 工具 | Q2: 合计 | R2: 三大爆品合计 | S2: 任务 | T2: 完成进度
A3: 包头办事处 | B3: 包头服务中心零售网点 | C3: =SUMIFS(CSM服务项目!Y:Y,CSM服务项目!Q:Q,$C$2,CSM服务项目!D:D,B3) -> 928 | D3: =SUMIFS(CSM服务项目!Y:Y,CSM服务项目!Q:Q,$D$2,CSM服务项目!D:D,B3) -> 0 | E3: =SUMIFS(CSM配件!AB:AB,CSM配件!R:R,$E$2,CSM配件!D:D,B3) -> 360 | F3: =SUMIFS(CSM配件!AB:AB,CSM配件!R:R,$F$2,CSM配件!D:D,B3) -> 0 | G3: =SUMIFS(CSM配件!AB:AB,CSM配件!R:R,$G$2,CSM配件!D:D,B3)+SUMIFS(WMS网点买断配件明细!I:I,WMS网点买断配件明细!K:K,$G$2,WMS网点买断配件明细!D:D,B3) -> 273 | H3: =SUMIFS(CSM配件!AB:AB,CSM配件!R:R,$H$2,CSM配件!D:D,B3)+SUMIFS(WMS网点买断配件明细!I:I,WMS网点买断配件明细!K:K,$H$2,WMS网点买断配件明细!D:D,B3) -> 0 | I3: =SUMIFS(CSM配件!AB:AB,CSM配件!R:R,$I$2,CSM配件!D:D,B3)+SUMIFS(WMS网点买断配件明细!I:I,WMS网点买断配件明细!K:K,$I$2,WMS网点买断配件明细!D:D,B3) -> 1120 | J3: =SUMIFS(CSM配件!AB:AB,CSM配件!R:R,$J$2,CSM配件!D:D,B3)+SUMIFS(WMS网点买断配件明细!I:I,WMS网点买断配件明细!K:K,$J$2,WMS网点买断配件明细!D:D,B3) -> 50 | K3: =SUMIFS(CSM配件!AB:AB,CSM配件!R:R,$K$2,CSM配件!D:D,B3)+SUMIFS(WMS网点买断配件明细!I:I,WMS网点买断配件明细!K:K,$K$2,WMS网点买断配件明细!D:D,B3) -> 0 | L3: =SUMIFS(CSM配件!AB:AB,CSM配件!R:R,$L$2,CSM配件!D:D,B3)+SUMIFS(WMS网点买断配件明细!I:I,WMS网点买断配件明细!K:K,$L$2,WMS网点买断配件明细!D:D,B3) -> 0 | M3: =SUMIFS(CSM配件!AB:AB,CSM配件!R:R,$M$2,CSM配件!D:D,B3)+SUMIFS(WMS网点买断配件明细!I:I,WMS网点买断配件明细!K:K,$M$2,WMS网点买断配件明细!D:D,B3) -> 50 | N3: =SUMIFS(CSM配件!AB:AB,CSM配件!R:R,$N$2,CSM配件!D:D,B3)+SUMIFS(WMS网点买断配件明细!I:I,WMS网点买断配件明细!K:K,$N$2,WMS网点买断配件明细!D:D,B3) -> 0 | O3: =SUMIFS(CSM配件!AB:AB,CSM配件!R:R,$O$2,CSM配件!D:D,B3)+SUMIFS(WMS网点买断配件明细!I:I,WMS网点买断配件明细!K:K,$O$2,WMS网点买断配件明细!D:D,B3) -> 0 | P3: =SUMIFS(CSM配件!AB:AB,CSM配件!R:R,$P$2,CSM配件!D:D,B3)+SUMIFS(WMS网点买断配件明细!I:I,WMS网点买断配件明细!K:K,$P$2,WMS网点买断配件明细!D:D,B3) -> 0 | Q3: =SUM(C3:P3) -> 2781 | R3: =C3+D3+G3 -> 1201
A4: 包头办事处 | B4: 东胜区赵全笑家电维修服务部 | C4: =SUMIFS(CSM服务项目!Y:Y,CSM服务项目!Q:Q,$C$2,CSM服务项目!D:D,B4) -> 0 | D4: =SUMIFS(CSM服务项目!Y:Y,CSM服务项目!Q:Q,$D$2,CSM服务项目!D:D,B4) -> 0 | E4: =SUMIFS(CSM配件!AB:AB,CSM配件!R:R,$E$2,CSM配件!D:D,B4) -> 1100 | F4: =SUMIFS(CSM配件!AB:AB,CSM配件!R:R,$F$2,CSM配件!D:D,B4) -> 0 | G4: =SUMIFS(CSM配件!AB:AB,CSM配件!R:R,$G$2,CSM配件!D:D,B4)+SUMIFS(WMS网点买断配件明细!I:I,WMS网点买断配件明细!K:K,$G$2,WMS网点买断配件明细!D:D,B4) -> 1220 | H4: =SUMIFS(CSM配件!AB:AB,CSM配件!R:R,$H$2,CSM配件!D:D,B4)+SUMIFS(WMS网点买断配件明细!I:I,WMS网点买断配件明细!K:K,$H$2,WMS网点买断配件明细!D:D,B4) -> 0 | I4: =SUMIFS(CSM配件!AB:AB,CSM配件!R:R,$I$2,CSM配件!D:D,B4)+SUMIFS(WMS网点买断配件明细!I:I,WMS网点买断配件明细!K:K,$I$2,WMS网点买断配件明细!D:D,B4) -> 840 | J4: =SUMIFS(CSM配件!AB:AB,CSM配件!R:R,$J$2,CSM配件!D:D,B4)+SUMIFS(WMS网点买断配件明细!I:I,WMS网点买断配件明细!K:K,$J$2,WMS网点买断配件明细!D:D,B4) -> 52.5 | K4: =SUMIFS(CSM配件!AB:AB,CSM配件!R:R,$K$2,CSM配件!D:D,B4)+SUMIFS(WMS网点买断配件明细!I:I,WMS网点买断配件明细!K:K,$K$2,WMS网点买断配件明细!D:D,B4) -> 196 | L4: =SUMIFS(CSM配件!AB:AB,CSM配件!R:R,$L$2,CSM配件!D:D,B4)+SUMIFS(WMS网点买断配件明细!I:I,WMS网点买断配件明细!K:K,$L$2,WMS网点买断配件明细!D:D,B4) -> 0 | M4: =SUMIFS(CSM配件!AB:AB,CSM配件!R:R,$M$2,CSM配件!D:D,B4)+SUMIFS(WMS网点买断配件明细!I:I,WMS网点买断配件明细!K:K,$M$2,WMS网点买断配件明细!D:D,B4) -> 17.5 | N4: =SUMIFS(CSM配件!AB:AB,CSM配件!R:R,$N$2,CSM配件!D:D,B4)+SUMIFS(WMS网点买断配件明细!I:I,WMS网点买断配件明细!K:K,$N$2,WMS网点买断配件明细!D:D,B4) -> 0 | O4: =SUMIFS(CSM配件!AB:AB,CSM配件!R:R,$O$2,CSM配件!D:D,B4)+SUMIFS(WMS网点买断配件明细!I:I,WMS网点买断配件明细!K:K,$O$2,WMS网点买断配件明细!D:D,B4) -> 0 | P4: =SUMIFS(CSM配件!AB:AB,CSM配件!R:R,$P$2,CSM配件!D:D,B4)+SUMIFS(WMS网点买断配件明细!I:I,WMS网点买断配件明细!K:K,$P$2,WMS网点买断配件明细!D:D,B4) -> 0 | Q4: =SUM(C4:P4) -> 3426 | R4: =C4+D4+G4 -> 1220
A5: 包头办事处 | B5: 海勃湾区福心圆家电维修服务部（个体工商户） | C5: =SUMIFS(CSM服务项目!Y:Y,CSM服务项目!Q:Q,$C$2,CSM服务项目!D:D,B5) -> 0 | D5: =SUMIFS(CSM服务项目!Y:Y,CSM服务项目!Q:Q,$D$2,CSM服务项目!D:D,B5) -> 0 | E5: =SUMIFS(CSM配件!AB:AB,CSM配件!R:R,$E$2,CSM配件!D:D,B5) -> 500 | F5: =SUMIFS(CSM配件!AB:AB,CSM配件!R:R,$F$2,CSM配件!D:D,B5) -> 0 | G5: =SUMIFS(CSM配件!AB:AB,CSM配件!R:R,$G$2,CSM配件!D:D,B5)+SUMIFS(WMS网点买断配件明细!I:I,WMS网点买断配件明细!K:K,$G$2,WMS网点买断配件明细!D:D,B5) -> 95 | H5: =SUMIFS(CSM配件!AB:AB,CSM配件!R:R,$H$2,CSM配件!D:D,B5)+SUMIFS(WMS网点买断配件明细!I:I,WMS网点买断配件明细!K:K,$H$2,WMS网点买断配件明细!D:D,B5) -> 0 | I5: =SUMIFS(CSM配件!AB:AB,CSM配件!R:R,$I$2,CSM配件!D:D,B5)+SUMIFS(WMS网点买断配件明细!I:I,WMS网点买断配件明细!K:K,$I$2,WMS网点买断配件明细!D:D,B5) -> 322 | J5: =SUMIFS(CSM配件!AB:AB,CSM配件!R:R,$J$2,CSM配件!D:D,B5)+SUMIFS(WMS网点买断配件明细!I:I,WMS网点买断配件明细!K:K,$J$2,WMS网点买断配件明细!D:D,B5) -> 0 | K5: =SUMIFS(CSM配件!AB:AB,CSM配件!R:R,$K$2,CSM配件!D:D,B5)+SUMIFS(WMS网点买断配件明细!I:I,WMS网点买断配件明细!K:K,$K$2,WMS网点买断配件明细!D:D,B5) -> 0 | L5: =SUMIFS(CSM配件!AB:AB,CSM配件!R:R,$L$2,CSM配件!D:D,B5)+SUMIFS(WMS网点买断配件明细!I:I,WMS网点买断配件明细!K:K,$L$2,WMS网点买断配件明细!D:D,B5) -> 0 | M5: =SUMIFS(CSM配件!AB:AB,CSM配件!R:R,$M$2,CSM配件!D:D,B5)+SUMIFS(WMS网点买断配件明细!I:I,WMS网点买断配件明细!K:K,$M$2,WMS网点买断配件明细!D:D,B5) -> 0 | N5: =SUMIFS(CSM配件!AB:AB,CSM配件!R:R,$N$2,CSM配件!D:D,B5)+SUMIFS(WMS网点买断配件明细!I:I,WMS网点买断配件明细!K:K,$N$2,WMS网点买断配件明细!D:D,B5) -> 0 | O5: =SUMIFS(CSM配件!AB:AB,CSM配件!R:R,$O$2,CSM配件!D:D,B5)+SUMIFS(WMS网点买断配件明细!I:I,WMS网点买断配件明细!K:K,$O$2,WMS网点买断配件明细!D:D,B5) -> 0 | P5: =SUMIFS(CSM配件!AB:AB,CSM配件!R:R,$P$2,CSM配件!D:D,B5)+SUMIFS(WMS网点买断配件明细!I:I,WMS网点买断配件明细!K:K,$P$2,WMS网点买断配件明细!D:D,B5) -> 0 | Q5: =SUM(C5:P5) -> 917 | R5: =C5+D5+G5 -> 95
A6: 包头办事处 | B6: 杭锦后旗李杰家电卫浴维修服务中心 | C6: =SUMIFS(CSM服务项目!Y:Y,CSM服务项目!Q:Q,$C$2,CSM服务项目!D:D,B6) -> 0 | D6: =SUMIFS(CSM服务项目!Y:Y,CSM服务项目!Q:Q,$D$2,CSM服务项目!D:D,B6) -> 0 | E6: =SUMIFS(CSM配件!AB:AB,CSM配件!R:R,$E$2,CSM配件!D:D,B6) -> 0 | F6: =SUMIFS(CSM配件!AB:AB,CSM配件!R:R,$F$2,CSM配件!D:D,B6) -> 0 | G6: =SUMIFS(CSM配件!AB:AB,CSM配件!R:R,$G$2,CSM配件!D:D,B6)+SUMIFS(WMS网点买断配件明细!I:I,WMS网点买断配件明细!K:K,$G$2,WMS网点买断配件明细!D:D,B6) -> 0 | H6: =SUMIFS(CSM配件!AB:AB,CSM配件!R:R,$H$2,CSM配件!D:D,B6)+SUMIFS(WMS网点买断配件明细!I:I,WMS网点买断配件明细!K:K,$H$2,WMS网点买断配件明细!D:D,B6) -> 0 | I6: =SUMIFS(CSM配件!AB:AB,CSM配件!R:R,$I$2,CSM配件!D:D,B6)+SUMIFS(WMS网点买断配件明细!I:I,WMS网点买断配件明细!K:K,$I$2,WMS网点买断配件明细!D:D,B6) -> 70 | J6: =SUMIFS(CSM配件!AB:AB,CSM配件!R:R,$J$2,CSM配件!D:D,B6)+SUMIFS(WMS网点买断配件明细!I:I,WMS网点买断配件明细!K:K,$J$2,WMS网点买断配件明细!D:D,B6) -> 0 | K6: =SUMIFS(CSM配件!AB:AB,CSM配件!R:R,$K$2,CSM配件!D:D,B6)+SUMIFS(WMS网点买断配件明细!I:I,WMS网点买断配件明细!K:K,$K$2,WMS网点买断配件明细!D:D,B6) -> 0 | L6: =SUMIFS(CSM配件!AB:AB,CSM配件!R:R,$L$2,CSM配件!D:D,B6)+SUMIFS(WMS网点买断配件明细!I:I,WMS网点买断配件明细!K:K,$L$2,WMS网点买断配件明细!D:D,B6) -> 0 | M6: =SUMIFS(CSM配件!AB:AB,CSM配件!R:R,$M$2,CSM配件!D:D,B6)+SUMIFS(WMS网点买断配件明细!I:I,WMS网点买断配件明细!K:K,$M$2,WMS网点买断配件明细!D:D,B6) -> 0 | N6: =SUMIFS(CSM配件!AB:AB,CSM配件!R:R,$N$2,CSM配件!D:D,B6)+SUMIFS(WMS网点买断配件明细!I:I,WMS网点买断配件明细!K:K,$N$2,WMS网点买断配件明细!D:D,B6) -> 0 | O6: =SUMIFS(CSM配件!AB:AB,CSM配件!R:R,$O$2,CSM配件!D:D,B6)+SUMIFS(WMS网点买断配件明细!I:I,WMS网点买断配件明细!K:K,$O$2,WMS网点买断配件明细!D:D,B6) -> 0 | P6: =SUMIFS(CSM配件!AB:AB,CSM配件!R:R,$P$2,CSM配件!D:D,B6)+SUMIFS(WMS网点买断配件明细!I:I,WMS网点买断配件明细!K:K,$P$2,WMS网点买断配件明细!D:D,B6) -> 0 | Q6: =SUM(C6:P6) -> 70 | R6: =C6+D6+G6 -> 0
A7: 包头办事处 | B7: 康巴什区中福家电维修服务部 | C7: =SUMIFS(CSM服务项目!Y:Y,CSM服务项目!Q:Q,$C$2,CSM服务项目!D:D,B7) -> 0 | D7: =SUMIFS(CSM服务项目!Y:Y,CSM服务项目!Q:Q,$D$2,CSM服务项目!D:D,B7) -> 0 | E7: =SUMIFS(CSM配件!AB:AB,CSM配件!R:R,$E$2,CSM配件!D:D,B7) -> 1100 | F7: =SUMIFS(CSM配件!AB:AB,CSM配件!R:R,$F$2,CSM配件!D:D,B7) -> 0 | G7: =SUMIFS(CSM配件!AB:AB,CSM配件!R:R,$G$2,CSM配件!D:D,B7)+SUMIFS(WMS网点买断配件明细!I:I,WMS网点买断配件明细!K:K,$G$2,WMS网点买断配件明细!D:D,B7) -> 228 | H7: =SUMIFS(CSM配件!AB:AB,CSM配件!R:R,$H$2,CSM配件!D:D,B7)+SUMIFS(WMS网点买断配件明细!I:I,WMS网点买断配件明细!K:K,$H$2,WMS网点买断配件明细!D:D,B7) -> 0 | I7: =SUMIFS(CSM配件!AB:AB,CSM配件!R:R,$I$2,CSM配件!D:D,B7)+SUMIFS(WMS网点买断配件明细!I:I,WMS网点买断配件明细!K:K,$I$2,WMS网点买断配件明细!D:D,B7) -> 567 | J7: =SUMIFS(CSM配件!AB:AB,CSM配件!R:R,$J$2,CSM配件!D:D,B7)+SUMIFS(WMS网点买断配件明细!I:I,WMS网点买断配件明细!K:K,$J$2,WMS网点买断配件明细!D:D,B7) -> 105 | K7: =SUMIFS(CSM配件!AB:AB,CSM配件!R:R,$K$2,CSM配件!D:D,B7)+SUMIFS(WMS网点买断配件明细!I:I,WMS网点买断配件明细!K:K,$K$2,WMS网点买断配件明细!D:D,B7) -> 0 | L7: =SUMIFS(CSM配件!AB:AB,CSM配件!R:R,$L$2,CSM配件!D:D,B7)+SUMIFS(WMS网点买断配件明细!I:I,WMS网点买断配件明细!K:K,$L$2,WMS网点买断配件明细!D:D,B7) -> 0 | M7: =SUMIFS(CSM配件!AB:AB,CSM配件!R:R,$M$2,CSM配件!D:D,B7)+SUMIFS(WMS网点买断配件明细!I:I,WMS网点买断配件明细!K:K,$M$2,WMS网点买断配件明细!D:D,B7) -> 0 | N7: =SUMIFS(CSM配件!AB:AB,CSM配件!R:R,$N$2,CSM配件!D:D,B7)+SUMIFS(WMS网点买断配件明细!I:I,WMS网点买断配件明细!K:K,$N$2,WMS网点买断配件明细!D:D,B7) -> 0 | O7: =SUMIFS(CSM配件!AB:AB,CSM配件!R:R,$O$2,CSM配件!D:D,B7)+SUMIFS(WMS网点买断配件明细!I:I,WMS网点买断配件明细!K:K,$O$2,WMS网点买断配件明细!D:D,B7) -> 0 | P7: =SUMIFS(CSM配件!AB:AB,CSM配件!R:R,$P$2,CSM配件!D:D,B7)+SUMIFS(WMS网点买断配件明细!I:I,WMS网点买断配件明细!K:K,$P$2,WMS网点买断配件明细!D:D,B7) -> 0 | Q7: =SUM(C7:P7) -> 2000 | R7: =C7+D7+G7 -> 228
A8: 包头办事处 | B8: 昆都仑区王宏明家电安装部 | C8: =SUMIFS(CSM服务项目!Y:Y,CSM服务项目!Q:Q,$C$2,CSM服务项目!D:D,B8) -> 0 | D8: =SUMIFS(CSM服务项目!Y:Y,CSM服务项目!Q:Q,$D$2,CSM服务项目!D:D,B8) -> 0 | E8: =SUMIFS(CSM配件!AB:AB,CSM配件!R:R,$E$2,CSM配件!D:D,B8) -> 100 | F8: =SUMIFS(CSM配件!AB:AB,CSM配件!R:R,$F$2,CSM配件!D:D,B8) -> 0 | G8: =SUMIFS(CSM配件!AB:AB,CSM配件!R:R,$G$2,CSM配件!D:D,B8)+SUMIFS(WMS网点买断配件明细!I:I,WMS网点买断配件明细!K:K,$G$2,WMS网点买断配件明细!D:D,B8) -> 40 | H8: =SUMIFS(CSM配件!AB:AB,CSM配件!R:R,$H$2,CSM配件!D:D,B8)+SUMIFS(WMS网点买断配件明细!I:I,WMS网点买断配件明细!K:K,$H$2,WMS网点买断配件明细!D:D,B8) -> 0 | I8: =SUMIFS(CSM配件!AB:AB,CSM配件!R:R,$I$2,CSM配件!D:D,B8)+SUMIFS(WMS网点买断配件明细!I:I,WMS网点买断配件明细!K:K,$I$2,WMS网点买断配件明细!D:D,B8) -> 280 | J8: =SUMIFS(CSM配件!AB:AB,CSM配件!R:R,$J$2,CSM配件!D:D,B8)+SUMIFS(WMS网点买断配件明细!I:I,WMS网点买断配件明细!K:K,$J$2,WMS网点买断配件明细!D:D,B8) -> 0 | K8: =SUMIFS(CSM配件!AB:AB,CSM配件!R:R,$K$2,CSM配件!D:D,B8)+SUMIFS(WMS网点买断配件明细!I:I,WMS网点买断配件明细!K:K,$K$2,WMS网点买断配件明细!D:D,B8) -> 0 | L8: =SUMIFS(CSM配件!AB:AB,CSM配件!R:R,$L$2,CSM配件!D:D,B8)+SUMIFS(WMS网点买断配件明细!I:I,WMS网点买断配件明细!K:K,$L$2,WMS网点买断配件明细!D:D,B8) -> 0 | M8: =SUMIFS(CSM配件!AB:AB,CSM配件!R:R,$M$2,CSM配件!D:D,B8)+SUMIFS(WMS网点买断配件明细!I:I,WMS网点买断配件明细!K:K,$M$2,WMS网点买断配件明细!D:D,B8) -> 52.5 | N8: =SUMIFS(CSM配件!AB:AB,CSM配件!R:R,$N$2,CSM配件!D:D,B8)+SUMIFS(WMS网点买断配件明细!I:I,WMS网点买断配件明细!K:K,$N$2,WMS网点买断配件明细!D:D,B8) -> 0 | O8: =SUMIFS(CSM配件!AB:AB,CSM配件!R:R,$O$2,CSM配件!D:D,B8)+SUMIFS(WMS网点买断配件明细!I:I,WMS网点买断配件明细!K:K,$O$2,WMS网点买断配件明细!D:D,B8) -> 0 | P8: =SUMIFS(CSM配件!AB:AB,CSM配件!R:R,$P$2,CSM配件!D:D,B8)+SUMIFS(WMS网点买断配件明细!I:I,WMS网点买断配件明细!K:K,$P$2,WMS网点买断配件明细!D:D,B8) -> 0 | Q8: =SUM(C8:P8) -> 472.5 | R8: =C8+D8+G8 -> 40
A9: 包头办事处 | B9: 临河区范慧明家电维修中心 | C9: =SUMIFS(CSM服务项目!Y:Y,CSM服务项目!Q:Q,$C$2,CSM服务项目!D:D,B9) -> 75 | D9: =SUMIFS(CSM服务项目!Y:Y,CSM服务项目!Q:Q,$D$2,CSM服务项目!D:D,B9) -> 0 | E9: =SUMIFS(CSM配件!AB:AB,CSM配件!R:R,$E$2,CSM配件!D:D,B9) -> 300 | F9: =SUMIFS(CSM配件!AB:AB,CSM配件!R:R,$F$2,CSM配件!D:D,B9) -> 0 | G9: =SUMIFS(CSM配件!AB:AB,CSM配件!R:R,$G$2,CSM配件!D:D,B9)+SUMIFS(WMS网点买断配件明细!I:I,WMS网点买断配件明细!K:K,$G$2,WMS网点买断配件明细!D:D,B9) -> 0 | H9: =SUMIFS(CSM配件!AB:AB,CSM配件!R:R,$H$2,CSM配件!D:D,B9)+SUMIFS(WMS网点买断配件明细!I:I,WMS网点买断配件明细!K:K,$H$2,WMS网点买断配件明细!D:D,B9) -> 0 | I9: =SUMIFS(CSM配件!AB:AB,CSM配件!R:R,$I$2,CSM配件!D:D,B9)+SUMIFS(WMS网点买断配件明细!I:I,WMS网点买断配件明细!K:K,$I$2,WMS网点买断配件明细!D:D,B9) -> 210 | J9: =SUMIFS(CSM配件!AB:AB,CSM配件!R:R,$J$2,CSM配件!D:D,B9)+SUMIFS(WMS网点买断配件明细!I:I,WMS网点买断配件明细!K:K,$J$2,WMS网点买断配件明细!D:D,B9) -> 129.5 | K9: =SUMIFS(CSM配件!AB:AB,CSM配件!R:R,$K$2,CSM配件!D:D,B9)+SUMIFS(WMS网点买断配件明细!I:I,WMS网点买断配件明细!K:K,$K$2,WMS网点买断配件明细!D:D,B9) -> 0 | L9: =SUMIFS(CSM配件!AB:AB,CSM配件!R:R,$L$2,CSM配件!D:D,B9)+SUMIFS(WMS网点买断配件明细!I:I,WMS网点买断配件明细!K:K,$L$2,WMS网点买断配件明细!D:D,B9) -> 0 | M9: =SUMIFS(CSM配件!AB:AB,CSM配件!R:R,$M$2,CSM配件!D:D,B9)+SUMIFS(WMS网点买断配件明细!I:I,WMS网点买断配件明细!K:K,$M$2,WMS网点买断配件明细!D:D,B9) -> 0 | N9: =SUMIFS(CSM配件!AB:AB,CSM配件!R:R,$N$2,CSM配件!D:D,B9)+SUMIFS(WMS网点买断配件明细!I:I,WMS网点买断配件明细!K:K,$N$2,WMS网点买断配件明细!D:D,B9) -> 0 | O9: =SUMIFS(CSM配件!AB:AB,CSM配件!R:R,$O$2,CSM配件!D:D,B9)+SUMIFS(WMS网点买断配件明细!I:I,WMS网点买断配件明细!K:K,$O$2,WMS网点买断配件明细!D:D,B9) -> 0 | P9: =SUMIFS(CSM配件!AB:AB,CSM配件!R:R,$P$2,CSM配件!D:D,B9)+SUMIFS(WMS网点买断配件明细!I:I,WMS网点买断配件明细!K:K,$P$2,WMS网点买断配件明细!D:D,B9) -> 0 | Q9: =SUM(C9:P9) -> 714.5 | R9: =C9+D9+G9 -> 75
A10: 包头办事处 | B10: 青山区厨小帮家电维修门店 | C10: =SUMIFS(CSM服务项目!Y:Y,CSM服务项目!Q:Q,$C$2,CSM服务项目!D:D,B10) -> 450 | D10: =SUMIFS(CSM服务项目!Y:Y,CSM服务项目!Q:Q,$D$2,CSM服务项目!D:D,B10) -> 343.5 | E10: =SUMIFS(CSM配件!AB:AB,CSM配件!R:R,$E$2,CSM配件!D:D,B10) -> 200 | F10: =SUMIFS(CSM配件!AB:AB,CSM配件!R:R,$F$2,CSM配件!D:D,B10) -> 0 | G10: =SUMIFS(CSM配件!AB:AB,CSM配件!R:R,$G$2,CSM配件!D:D,B10)+SUMIFS(WMS网点买断配件明细!I:I,WMS网点买断配件明细!K:K,$G$2,WMS网点买断配件明细!D:D,B10) -> 520 | H10: =SUMIFS(CSM配件!AB:AB,CSM配件!R:R,$H$2,CSM配件!D:D,B10)+SUMIFS(WMS网点买断配件明细!I:I,WMS网点买断配件明细!K:K,$H$2,WMS网点买断配件明细!D:D,B10) -> 408.21 | I10: =SUMIFS(CSM配件!AB:AB,CSM配件!R:R,$I$2,CSM配件!D:D,B10)+SUMIFS(WMS网点买断配件明细!I:I,WMS网点买断配件明细!K:K,$I$2,WMS网点买断配件明细!D:D,B10) -> 560 | J10: =SUMIFS(CSM配件!AB:AB,CSM配件!R:R,$J$2,CSM配件!D:D,B10)+SUMIFS(WMS网点买断配件明细!I:I,WMS网点买断配件明细!K:K,$J$2,WMS网点买断配件明细!D:D,B10) -> 0 | K10: =SUMIFS(CSM配件!AB:AB,CSM配件!R:R,$K$2,CSM配件!D:D,B10)+SUMIFS(WMS网点买断配件明细!I:I,WMS网点买断配件明细!K:K,$K$2,WMS网点买断配件明细!D:D,B10) -> 0 | L10: =SUMIFS(CSM配件!AB:AB,CSM配件!R:R,$L$2,CSM配件!D:D,B10)+SUMIFS(WMS网点买断配件明细!I:I,WMS网点买断配件明细!K:K,$L$2,WMS网点买断配件明细!D:D,B10) -> 0 | M10: =SUMIFS(CSM配件!AB:AB,CSM配件!R:R,$M$2,CSM配件!D:D,B10)+SUMIFS(WMS网点买断配件明细!I:I,WMS网点买断配件明细!K:K,$M$2,WMS网点买断配件明细!D:D,B10) -> 35 | N10: =SUMIFS(CSM配件!AB:AB,CSM配件!R:R,$N$2,CSM配件!D:D,B10)+SUMIFS(WMS网点买断配件明细!I:I,WMS网点买断配件明细!K:K,$N$2,WMS网点买断配件明细!D:D,B10) -> 0 | O10: =SUMIFS(CSM配件!AB:AB,CSM配件!R:R,$O$2,CSM配件!D:D,B10)+SUMIFS(WMS网点买断配件明细!I:I,WMS网点买断配件明细!K:K,$O$2,WMS网点买断配件明细!D:D,B10) -> 44.4 | P10: =SUMIFS(CSM配件!AB:AB,CSM配件!R:R,$P$2,CSM配件!D:D,B10)+SUMIFS(WMS网点买断配件明细!I:I,WMS网点买断配件明细!K:K,$P$2,WMS网点买断配件明细!D:D,B10) -> 0 | Q10: =SUM(C10:P10) -> 2561.11 | R10: =C10+D10+G10 -> 1313.5
A11: 包头办事处 | B11: 乌拉特前旗乌拉山方容厨房电器 | C11: =SUMIFS(CSM服务项目!Y:Y,CSM服务项目!Q:Q,$C$2,CSM服务项目!D:D,B11) -> 0 | D11: =SUMIFS(CSM服务项目!Y:Y,CSM服务项目!Q:Q,$D$2,CSM服务项目!D:D,B11) -> 0 | E11: =SUMIFS(CSM配件!AB:AB,CSM配件!R:R,$E$2,CSM配件!D:D,B11) -> 0 | F11: =SUMIFS(CSM配件!AB:AB,CSM配件!R:R,$F$2,CSM配件!D:D,B11) -> 0 | G11: =SUMIFS(CSM配件!AB:AB,CSM配件!R:R,$G$2,CSM配件!D:D,B11)+SUMIFS(WMS网点买断配件明细!I:I,WMS网点买断配件明细!K:K,$G$2,WMS网点买断配件明细!D:D,B11) -> 152 | H11: =SUMIFS(CSM配件!AB:AB,CSM配件!R:R,$H$2,CSM配件!D:D,B11)+SUMIFS(WMS网点买断配件明细!I:I,WMS网点买断配件明细!K:K,$H$2,WMS网点买断配件明细!D:D,B11) -> 0 | I11: =SUMIFS(CSM配件!AB:AB,CSM配件!R:R,$I$2,CSM配件!D:D,B11)+SUMIFS(WMS网点买断配件明细!I:I,WMS网点买断配件明细!K:K,$I$2,WMS网点买断配件明细!D:D,B11) -> 0 | J11: =SUMIFS(CSM配件!AB:AB,CSM配件!R:R,$J$2,CSM配件!D:D,B11)+SUMIFS(WMS网点买断配件明细!I:I,WMS网点买断配件明细!K:K,$J$2,WMS网点买断配件明细!D:D,B11) -> 0 | K11: =SUMIFS(CSM配件!AB:AB,CSM配件!R:R,$K$2,CSM配件!D:D,B11)+SUMIFS(WMS网点买断配件明细!I:I,WMS网点买断配件明细!K:K,$K$2,WMS网点买断配件明细!D:D,B11) -> 0 | L11: =SUMIFS(CSM配件!AB:AB,CSM配件!R:R,$L$2,CSM配件!D:D,B11)+SUMIFS(WMS网点买断配件明细!I:I,WMS网点买断配件明细!K:K,$L$2,WMS网点买断配件明细!D:D,B11) -> 0 | M11: =SUMIFS(CSM配件!AB:AB,CSM配件!R:R,$M$2,CSM配件!D:D,B11)+SUMIFS(WMS网点买断配件明细!I:I,WMS网点买断配件明细!K:K,$M$2,WMS网点买断配件明细!D:D,B11) -> 0 | N11: =SUMIFS(CSM配件!AB:AB,CSM配件!R:R,$N$2,CSM配件!D:D,B11)+SUMIFS(WMS网点买断配件明细!I:I,WMS网点买断配件明细!K:K,$N$2,WMS网点买断配件明细!D:D,B11) -> 0 | O11: =SUMIFS(CSM配件!AB:AB,CSM配件!R:R,$O$2,CSM配件!D:D,B11)+SUMIFS(WMS网点买断配件明细!I:I,WMS网点买断配件明细!K:K,$O$2,WMS网点买断配件明细!D:D,B11) -> 0 | P11: =SUMIFS(CSM配件!AB:AB,CSM配件!R:R,$P$2,CSM配件!D:D,B11)+SUMIFS(WMS网点买断配件明细!I:I,WMS网点买断配件明细!K:K,$P$2,WMS网点买断配件明细!D:D,B11) -> 0 | Q11: =SUM(C11:P11) -> 152 | R11: =C11+D11+G11 -> 152
A12: 包头办事处 | B12: 五原县万佳电器服务中心 | C12: =SUMIFS(CSM服务项目!Y:Y,CSM服务项目!Q:Q,$C$2,CSM服务项目!D:D,B12) -> 0 | D12: =SUMIFS(CSM服务项目!Y:Y,CSM服务项目!Q:Q,$D$2,CSM服务项目!D:D,B12) -> 0 | E12: =SUMIFS(CSM配件!AB:AB,CSM配件!R:R,$E$2,CSM配件!D:D,B12) -> 0 | F12: =SUMIFS(CSM配件!AB:AB,CSM配件!R:R,$F$2,CSM配件!D:D,B12) -> 0 | G12: =SUMIFS(CSM配件!AB:AB,CSM配件!R:R,$G$2,CSM配件!D:D,B12)+SUMIFS(WMS网点买断配件明细!I:I,WMS网点买断配件明细!K:K,$G$2,WMS网点买断配件明细!D:D,B12) -> 0 | H12: =SUMIFS(CSM配件!AB:AB,CSM配件!R:R,$H$2,CSM配件!D:D,B12)+SUMIFS(WMS网点买断配件明细!I:I,WMS网点买断配件明细!K:K,$H$2,WMS网点买断配件明细!D:D,B12) -> 0 | I12: =SUMIFS(CSM配件!AB:AB,CSM配件!R:R,$I$2,CSM配件!D:D,B12)+SUMIFS(WMS网点买断配件明细!I:I,WMS网点买断配件明细!K:K,$I$2,WMS网点买断配件明细!D:D,B12) -> 0 | J12: =SUMIFS(CSM配件!AB:AB,CSM配件!R:R,$J$2,CSM配件!D:D,B12)+SUMIFS(WMS网点买断配件明细!I:I,WMS网点买断配件明细!K:K,$J$2,WMS网点买断配件明细!D:D,B12) -> 0 | K12: =SUMIFS(CSM配件!AB:AB,CSM配件!R:R,$K$2,CSM配件!D:D,B12)+SUMIFS(WMS网点买断配件明细!I:I,WMS网点买断配件明细!K:K,$K$2,WMS网点买断配件明细!D:D,B12) -> 0 | L12: =SUMIFS(CSM配件!AB:AB,CSM配件!R:R,$L$2,CSM配件!D:D,B12)+SUMIFS(WMS网点买断配件明细!I:I,WMS网点买断配件明细!K:K,$L$2,WMS网点买断配件明细!D:D,B12) -> 0 | M12: =SUMIFS(CSM配件!AB:AB,CSM配件!R:R,$M$2,CSM配件!D:D,B12)+SUMIFS(WMS网点买断配件明细!I:I,WMS网点买断配件明细!K:K,$M$2,WMS网点买断配件明细!D:D,B12) -> 0 | N12: =SUMIFS(CSM配件!AB:AB,CSM配件!R:R,$N$2,CSM配件!D:D,B12)+SUMIFS(WMS网点买断配件明细!I:I,WMS网点买断配件明细!K:K,$N$2,WMS网点买断配件明细!D:D,B12) -> 0 | O12: =SUMIFS(CSM配件!AB:AB,CSM配件!R:R,$O$2,CSM配件!D:D,B12)+SUMIFS(WMS网点买断配件明细!I:I,WMS网点买断配件明细!K:K,$O$2,WMS网点买断配件明细!D:D,B12) -> 0 | P12: =SUMIFS(CSM配件!AB:AB,CSM配件!R:R,$P$2,CSM配件!D:D,B12)+SUMIFS(WMS网点买断配件明细!I:I,WMS网点买断配件明细!K:K,$P$2,WMS网点买断配件明细!D:D,B12) -> 0 | Q12: =SUM(C12:P12) -> 0 | R12: =C12+D12+G12 -> 0
A13: 包头办事处 | B13: 伊金霍洛旗刘庆春电器店 | C13: =SUMIFS(CSM服务项目!Y:Y,CSM服务项目!Q:Q,$C$2,CSM服务项目!D:D,B13) -> 0 | D13: =SUMIFS(CSM服务项目!Y:Y,CSM服务项目!Q:Q,$D$2,CSM服务项目!D:D,B13) -> 0 | E13: =SUMIFS(CSM配件!AB:AB,CSM配件!R:R,$E$2,CSM配件!D:D,B13) -> 100 | F13: =SUMIFS(CSM配件!AB:AB,CSM配件!R:R,$F$2,CSM配件!D:D,B13) -> 0 | G13: =SUMIFS(CSM配件!AB:AB,CSM配件!R:R,$G$2,CSM配件!D:D,B13)+SUMIFS(WMS网点买断配件明细!I:I,WMS网点买断配件明细!K:K,$G$2,WMS网点买断配件明细!D:D,B13) -> 0 | H13: =SUMIFS(CSM配件!AB:AB,CSM配件!R:R,$H$2,CSM配件!D:D,B13)+SUMIFS(WMS网点买断配件明细!I:I,WMS网点买断配件明细!K:K,$H$2,WMS网点买断配件明细!D:D,B13) -> 0 | I13: =SUMIFS(CSM配件!AB:AB,CSM配件!R:R,$I$2,CSM配件!D:D,B13)+SUMIFS(WMS网点买断配件明细!I:I,WMS网点买断配件明细!K:K,$I$2,WMS网点买断配件明细!D:D,B13) -> 280 | J13: =SUMIFS(CSM配件!AB:AB,CSM配件!R:R,$J$2,CSM配件!D:D,B13)+SUMIFS(WMS网点买断配件明细!I:I,WMS网点买断配件明细!K:K,$J$2,WMS网点买断配件明细!D:D,B13) -> 35 | K13: =SUMIFS(CSM配件!AB:AB,CSM配件!R:R,$K$2,CSM配件!D:D,B13)+SUMIFS(WMS网点买断配件明细!I:I,WMS网点买断配件明细!K:K,$K$2,WMS网点买断配件明细!D:D,B13) -> 0 | L13: =SUMIFS(CSM配件!AB:AB,CSM配件!R:R,$L$2,CSM配件!D:D,B13)+SUMIFS(WMS网点买断配件明细!I:I,WMS网点买断配件明细!K:K,$L$2,WMS网点买断配件明细!D:D,B13) -> 0 | M13: =SUMIFS(CSM配件!AB:AB,CSM配件!R:R,$M$2,CSM配件!D:D,B13)+SUMIFS(WMS网点买断配件明细!I:I,WMS网点买断配件明细!K:K,$M$2,WMS网点买断配件明细!D:D,B13) -> 0 | N13: =SUMIFS(CSM配件!AB:AB,CSM配件!R:R,$N$2,CSM配件!D:D,B13)+SUMIFS(WMS网点买断配件明细!I:I,WMS网点买断配件明细!K:K,$N$2,WMS网点买断配件明细!D:D,B13) -> 0 | O13: =SUMIFS(CSM配件!AB:AB,CSM配件!R:R,$O$2,CSM配件!D:D,B13)+SUMIFS(WMS网点买断配件明细!I:I,WMS网点买断配件明细!K:K,$O$2,WMS网点买断配件明细!D:D,B13) -> 0 | P13: =SUMIFS(CSM配件!AB:AB,CSM配件!R:R,$P$2,CSM配件!D:D,B13)+SUMIFS(WMS网点买断配件明细!I:I,WMS网点买断配件明细!K:K,$P$2,WMS网点买断配件明细!D:D,B13) -> 0 | Q13: =SUM(C13:P13) -> 415 | R13: =C13+D13+G13 -> 0
A14: 呼和浩特办事处 | B14: 呼和浩特服务中心零售网点 | C14: =SUMIFS(CSM服务项目!Y:Y,CSM服务项目!Q:Q,$C$2,CSM服务项目!D:D,B14) -> 0 | D14: =SUMIFS(CSM服务项目!Y:Y,CSM服务项目!Q:Q,$D$2,CSM服务项目!D:D,B14) -> 0 | E14: =SUMIFS(CSM配件!AB:AB,CSM配件!R:R,$E$2,CSM配件!D:D,B14) -> 180 | F14: =SUMIFS(CSM配件!AB:AB,CSM配件!R:R,$F$2,CSM配件!D:D,B14) -> 0 | G14: =SUMIFS(CSM配件!AB:AB,CSM配件!R:R,$G$2,CSM配件!D:D,B14)+SUMIFS(WMS网点买断配件明细!I:I,WMS网点买断配件明细!K:K,$G$2,WMS网点买断配件明细!D:D,B14) -> 221 | H14: =SUMIFS(CSM配件!AB:AB,CSM配件!R:R,$H$2,CSM配件!D:D,B14)+SUMIFS(WMS网点买断配件明细!I:I,WMS网点买断配件明细!K:K,$H$2,WMS网点买断配件明细!D:D,B14) -> 150 | I14: =SUMIFS(CSM配件!AB:AB,CSM配件!R:R,$I$2,CSM配件!D:D,B14)+SUMIFS(WMS网点买断配件明细!I:I,WMS网点买断配件明细!K:K,$I$2,WMS网点买断配件明细!D:D,B14) -> 705 | J14: =SUMIFS(CSM配件!AB:AB,CSM配件!R:R,$J$2,CSM配件!D:D,B14)+SUMIFS(WMS网点买断配件明细!I:I,WMS网点买断配件明细!K:K,$J$2,WMS网点买断配件明细!D:D,B14) -> 220 | K14: =SUMIFS(CSM配件!AB:AB,CSM配件!R:R,$K$2,CSM配件!D:D,B14)+SUMIFS(WMS网点买断配件明细!I:I,WMS网点买断配件明细!K:K,$K$2,WMS网点买断配件明细!D:D,B14) -> 720 | L14: =SUMIFS(CSM配件!AB:AB,CSM配件!R:R,$L$2,CSM配件!D:D,B14)+SUMIFS(WMS网点买断配件明细!I:I,WMS网点买断配件明细!K:K,$L$2,WMS网点买断配件明细!D:D,B14) -> 0 | M14: =SUMIFS(CSM配件!AB:AB,CSM配件!R:R,$M$2,CSM配件!D:D,B14)+SUMIFS(WMS网点买断配件明细!I:I,WMS网点买断配件明细!K:K,$M$2,WMS网点买断配件明细!D:D,B14) -> 0 | N14: =SUMIFS(CSM配件!AB:AB,CSM配件!R:R,$N$2,CSM配件!D:D,B14)+SUMIFS(WMS网点买断配件明细!I:I,WMS网点买断配件明细!K:K,$N$2,WMS网点买断配件明细!D:D,B14) -> 0 | O14: =SUMIFS(CSM配件!AB:AB,CSM配件!R:R,$O$2,CSM配件!D:D,B14)+SUMIFS(WMS网点买断配件明细!I:I,WMS网点买断配件明细!K:K,$O$2,WMS网点买断配件明细!D:D,B14) -> 0 | P14: =SUMIFS(CSM配件!AB:AB,CSM配件!R:R,$P$2,CSM配件!D:D,B14)+SUMIFS(WMS网点买断配件明细!I:I,WMS网点买断配件明细!K:K,$P$2,WMS网点买断配件明细!D:D,B14) -> 0 | Q14: =SUM(C14:P14) -> 2196 | R14: =C14+D14+G14 -> 221
... A105: 新疆办事处 | B105: 伊宁边境经济合作区谢振升家电维修服务部 | C105: =SUMIFS(CSM服务项目!Y:Y,CSM服务项目!Q:Q,$C$2,CSM服务项目!D:D,B105) -> 150 | D105: =SUMIFS(CSM服务项目!Y:Y,CSM服务项目!Q:Q,$D$2,CSM服务项目!D:D,B105) -> 0 | E105: =SUMIFS(CSM配件!AB:AB,CSM配件!R:R,$E$2,CSM配件!D:D,B105) -> 1300 | F105: =SUMIFS(CSM配件!AB:AB,CSM配件!R:R,$F$2,CSM配件!D:D,B105) -> 0 | G105: =SUMIFS(CSM配件!AB:AB,CSM配件!R:R,$G$2,CSM配件!D:D,B105)+SUMIFS(WMS网点买断配件明细!I:I,WMS网点买断配件明细!K:K,$G$2,WMS网点买断配件明细!D:D,B105) -> 15 | H105: =SUMIFS(CSM配件!AB:AB,CSM配件!R:R,$H$2,CSM配件!D:D,B105)+SUMIFS(WMS网点买断配件明细!I:I,WMS网点买断配件明细!K:K,$H$2,WMS网点买断配件明细!D:D,B105) -> 0 | I105: =SUMIFS(CSM配件!AB:AB,CSM配件!R:R,$I$2,CSM配件!D:D,B105)+SUMIFS(WMS网点买断配件明细!I:I,WMS网点买断配件明细!K:K,$I$2,WMS网点买断配件明细!D:D,B105) -> 140 | J105: =SUMIFS(CSM配件!AB:AB,CSM配件!R:R,$J$2,CSM配件!D:D,B105)+SUMIFS(WMS网点买断配件明细!I:I,WMS网点买断配件明细!K:K,$J$2,WMS网点买断配件明细!D:D,B105) -> 175 | K105: =SUMIFS(CSM配件!AB:AB,CSM配件!R:R,$K$2,CSM配件!D:D,B105)+SUMIFS(WMS网点买断配件明细!I:I,WMS网点买断配件明细!K:K,$K$2,WMS网点买断配件明细!D:D,B105) -> 0 | L105: =SUMIFS(CSM配件!AB:AB,CSM配件!R:R,$L$2,CSM配件!D:D,B105)+SUMIFS(WMS网点买断配件明细!I:I,WMS网点买断配件明细!K:K,$L$2,WMS网点买断配件明细!D:D,B105) -> 0 | M105: =SUMIFS(CSM配件!AB:AB,CSM配件!R:R,$M$2,CSM配件!D:D,B105)+SUMIFS(WMS网点买断配件明细!I:I,WMS网点买断配件明细!K:K,$M$2,WMS网点买断配件明细!D:D,B105) -> 0 | N105: =SUMIFS(CSM配件!AB:AB,CSM配件!R:R,$N$2,CSM配件!D:D,B105)+SUMIFS(WMS网点买断配件明细!I:I,WMS网点买断配件明细!K:K,$N$2,WMS网点买断配件明细!D:D,B105) -> 0 | O105: =SUMIFS(CSM配件!AB:AB,CSM配件!R:R,$O$2,CSM配件!D:D,B105)+SUMIFS(WMS网点买断配件明细!I:I,WMS网点买断配件明细!K:K,$O$2,WMS网点买断配件明细!D:D,B105) -> 0 | P105: =SUMIFS(CSM配件!AB:AB,CSM配件!R:R,$P$2,CSM配件!D:D,B105)+SUMIFS(WMS网点买断配件明细!I:I,WMS网点买断配件明细!K:K,$P$2,WMS网点买断配件明细!D:D,B105) -> 0 | Q105: =SUM(C105:P105) -> 1780 | R105: =C105+D105+G105 -> 165

Sheet 技师数据
A1: 西北大区服务技师收入统计
A2: 办事处 | B2: 服务网点 | C2: 服务技师 | D2: 清洗保养 | E2: 延保服务 | F2: 止回阀 | G2: 装饰罩 | H2: 清洁耗材 | I2: 水/气路金属软管 | J2: 其他产品线专用 | K2: 排烟出风管 | L2: 其他水路辅材 | M2: 其他气路辅材 | N2: 橱柜类辅材 | O2: 水气路通用辅材 | P2: 燃气管快速接头 | Q2: 工具 | R2: 合计 | S2: 三大爆品合计 | T2: 任务 | U2: 完成进度 | V2: 烟机安装 | W2: 止回阀 | X2: 止回阀使用率
A3: 新疆办事处 | B3: 阿克苏市零壹家电维修部 | C3: 张蒙光 | D3: =SUMIFS(CSM服务项目!Y:Y,CSM服务项目!Q:Q,$D$2,CSM服务项目!F:F,C3) -> 0 | E3: =SUMIFS(CSM服务项目!Y:Y,CSM服务项目!Q:Q,$E$2,CSM服务项目!F:F,C3) -> 0 | F3: =SUMIFS(CSM配件!AB:AB,CSM配件!R:R,$F$2,CSM配件!F:F,C3) -> 800 | G3: =SUMIFS(CSM配件!AB:AB,CSM配件!R:R,$G$2,CSM配件!F:F,C3) -> 0 | H3: =SUMIFS(CSM配件!AB:AB,CSM配件!R:R,$H$2,CSM配件!F:F,C3) -> 0 | I3: =SUMIFS(CSM配件!AB:AB,CSM配件!R:R,$I$2,CSM配件!F:F,C3) -> 0 | J3: =SUMIFS(CSM配件!AB:AB,CSM配件!R:R,$J$2,CSM配件!F:F,C3) -> 98 | K3: =SUMIFS(CSM配件!AB:AB,CSM配件!R:R,$K$2,CSM配件!F:F,C3) -> 28 | L3: =SUMIFS(CSM配件!AB:AB,CSM配件!R:R,$L$2,CSM配件!F:F,C3) -> 0 | M3: =SUMIFS(CSM配件!AB:AB,CSM配件!R:R,$M$2,CSM配件!F:F,C3) -> 0 | N3: =SUMIFS(CSM配件!AB:AB,CSM配件!R:R,$N$2,CSM配件!F:F,C3) -> 0 | O3: =SUMIFS(CSM配件!AB:AB,CSM配件!R:R,$O$2,CSM配件!F:F,C3) -> 0 | P3: =SUMIFS(CSM配件!AB:AB,CSM配件!R:R,$P$2,CSM配件!F:F,C3) -> 0 | Q3: =SUMIFS(CSM配件!AB:AB,CSM配件!R:R,$Q$2,CSM配件!F:F,C3) -> 0 | R3: =SUM(D3:Q3) -> 926 | S3: =D3+E3+H3 -> 0 | V3: =COUNTIFS(工单!BV:BV,"吸油烟机",工单!BF:BF,"安装",工单!BD:BD,C3)+COUNTIFS(工单!BV:BV,"吸油烟机",工单!BF:BF,"改装",工单!BD:BD,C3)+COUNTIFS(工单!BV:BV,"吸油烟机",工单!BF:BF,"油烟机预埋烟管",工单!BD:BD,C3) -> 12 | W3: =COUNTIFS(CSM配件!R:R,$W$2,CSM配件!F:F,C3)+COUNTIFS(工单自购配件明细!N:N,"防火止回阀",工单自购配件明细!R:R,C3) -> 8 | X3: =W3/V3 -> 0.66666667
A4: 新疆办事处 | B4: 阿克苏市零壹家电维修部 | C4: 姚双全 | D4: =SUMIFS(CSM服务项目!Y:Y,CSM服务项目!Q:Q,$D$2,CSM服务项目!F:F,C4) -> 0 | E4: =SUMIFS(CSM服务项目!Y:Y,CSM服务项目!Q:Q,$E$2,CSM服务项目!F:F,C4) -> 0 | F4: =SUMIFS(CSM配件!AB:AB,CSM配件!R:R,$F$2,CSM配件!F:F,C4) -> 400 | G4: =SUMIFS(CSM配件!AB:AB,CSM配件!R:R,$G$2,CSM配件!F:F,C4) -> 0 | H4: =SUMIFS(CSM配件!AB:AB,CSM配件!R:R,$H$2,CSM配件!F:F,C4) -> 0 | I4: =SUMIFS(CSM配件!AB:AB,CSM配件!R:R,$I$2,CSM配件!F:F,C4) -> 0 | J4: =SUMIFS(CSM配件!AB:AB,CSM配件!R:R,$J$2,CSM配件!F:F,C4) -> 0 | K4: =SUMIFS(CSM配件!AB:AB,CSM配件!R:R,$K$2,CSM配件!F:F,C4) -> 0 | L4: =SUMIFS(CSM配件!AB:AB,CSM配件!R:R,$L$2,CSM配件!F:F,C4) -> 0 | M4: =SUMIFS(CSM配件!AB:AB,CSM配件!R:R,$M$2,CSM配件!F:F,C4) -> 0 | N4: =SUMIFS(CSM配件!AB:AB,CSM配件!R:R,$N$2,CSM配件!F:F,C4) -> 0 | O4: =SUMIFS(CSM配件!AB:AB,CSM配件!R:R,$O$2,CSM配件!F:F,C4) -> 0 | P4: =SUMIFS(CSM配件!AB:AB,CSM配件!R:R,$P$2,CSM配件!F:F,C4) -> 0 | Q4: =SUMIFS(CSM配件!AB:AB,CSM配件!R:R,$Q$2,CSM配件!F:F,C4) -> 0 | R4: =SUM(D4:Q4) -> 400 | S4: =D4+E4+H4 -> 0 | V4: =COUNTIFS(工单!BV:BV,"吸油烟机",工单!BF:BF,"安装",工单!BD:BD,C4)+COUNTIFS(工单!BV:BV,"吸油烟机",工单!BF:BF,"改装",工单!BD:BD,C4)+COUNTIFS(工单!BV:BV,"吸油烟机",工单!BF:BF,"油烟机预埋烟管",工单!BD:BD,C4) -> 2 | W4: =COUNTIFS(CSM配件!R:R,$W$2,CSM配件!F:F,C4)+COUNTIFS(工单自购配件明细!N:N,"防火止回阀",工单自购配件明细!R:R,C4) -> 4 | X4: =W4/V4 -> 2
A5: 新疆办事处 | B5: 北屯市安家厨房电器维修店（个体工商户） | C5: 赵灿明 | D5: =SUMIFS(CSM服务项目!Y:Y,CSM服务项目!Q:Q,$D$2,CSM服务项目!F:F,C5) -> 0 | E5: =SUMIFS(CSM服务项目!Y:Y,CSM服务项目!Q:Q,$E$2,CSM服务项目!F:F,C5) -> 1419.8 | F5: =SUMIFS(CSM配件!AB:AB,CSM配件!R:R,$F$2,CSM配件!F:F,C5) -> 100 | G5: =SUMIFS(CSM配件!AB:AB,CSM配件!R:R,$G$2,CSM配件!F:F,C5) -> 0 | H5: =SUMIFS(CSM配件!AB:AB,CSM配件!R:R,$H$2,CSM配件!F:F,C5) -> 0 | I5: =SUMIFS(CSM配件!AB:AB,CSM配件!R:R,$I$2,CSM配件!F:F,C5) -> 0 | J5: =SUMIFS(CSM配件!AB:AB,CSM配件!R:R,$J$2,CSM配件!F:F,C5) -> 105 | K5: =SUMIFS(CSM配件!AB:AB,CSM配件!R:R,$K$2,CSM配件!F:F,C5) -> 101.5 | L5: =SUMIFS(CSM配件!AB:AB,CSM配件!R:R,$L$2,CSM配件!F:F,C5) -> 0 | M5: =SUMIFS(CSM配件!AB:AB,CSM配件!R:R,$M$2,CSM配件!F:F,C5) -> 0 | N5: =SUMIFS(CSM配件!AB:AB,CSM配件!R:R,$N$2,CSM配件!F:F,C5) -> 0 | O5: =SUMIFS(CSM配件!AB:AB,CSM配件!R:R,$O$2,CSM配件!F:F,C5) -> 0 | P5: =SUMIFS(CSM配件!AB:AB,CSM配件!R:R,$P$2,CSM配件!F:F,C5) -> 0 | Q5: =SUMIFS(CSM配件!AB:AB,CSM配件!R:R,$Q$2,CSM配件!F:F,C5) -> 0 | R5: =SUM(D5:Q5) -> 1726.3 | S5: =D5+E5+H5 -> 1419.8 | V5: =COUNTIFS(工单!BV:BV,"吸油烟机",工单!BF:BF,"安装",工单!BD:BD,C5)+COUNTIFS(工单!BV:BV,"吸油烟机",工单!BF:BF,"改装",工单!BD:BD,C5)+COUNTIFS(工单!BV:BV,"吸油烟机",工单!BF:BF,"油烟机预埋烟管",工单!BD:BD,C5) -> 7 | W5: =COUNTIFS(CSM配件!R:R,$W$2,CSM配件!F:F,C5)+COUNTIFS(工单自购配件明细!N:N,"防火止回阀",工单自购配件明细!R:R,C5) -> 1 | X5: =W5/V5 -> 0.14285714
A6: 新疆办事处 | B6: 北屯市速达厨电安装中心 | C6: 王成良 | D6: =SUMIFS(CSM服务项目!Y:Y,CSM服务项目!Q:Q,$D$2,CSM服务项目!F:F,C6) -> 0 | E6: =SUMIFS(CSM服务项目!Y:Y,CSM服务项目!Q:Q,$E$2,CSM服务项目!F:F,C6) -> 0 | F6: =SUMIFS(CSM配件!AB:AB,CSM配件!R:R,$F$2,CSM配件!F:F,C6) -> 0 | G6: =SUMIFS(CSM配件!AB:AB,CSM配件!R:R,$G$2,CSM配件!F:F,C6) -> 0 | H6: =SUMIFS(CSM配件!AB:AB,CSM配件!R:R,$H$2,CSM配件!F:F,C6) -> 0 | I6: =SUMIFS(CSM配件!AB:AB,CSM配件!R:R,$I$2,CSM配件!F:F,C6) -> 0 | J6: =SUMIFS(CSM配件!AB:AB,CSM配件!R:R,$J$2,CSM配件!F:F,C6) -> 0 | K6: =SUMIFS(CSM配件!AB:AB,CSM配件!R:R,$K$2,CSM配件!F:F,C6) -> 0 | L6: =SUMIFS(CSM配件!AB:AB,CSM配件!R:R,$L$2,CSM配件!F:F,C6) -> 0 | M6: =SUMIFS(CSM配件!AB:AB,CSM配件!R:R,$M$2,CSM配件!F:F,C6) -> 0 | N6: =SUMIFS(CSM配件!AB:AB,CSM配件!R:R,$N$2,CSM配件!F:F,C6) -> 0 | O6: =SUMIFS(CSM配件!AB:AB,CSM配件!R:R,$O$2,CSM配件!F:F,C6) -> 0 | P6: =SUMIFS(CSM配件!AB:AB,CSM配件!R:R,$P$2,CSM配件!F:F,C6) -> 0 | Q6: =SUMIFS(CSM配件!AB:AB,CSM配件!R:R,$Q$2,CSM配件!F:F,C6) -> 0 | R6: =SUM(D6:Q6) -> 0 | S6: =D6+E6+H6 -> 0 | V6: =COUNTIFS(工单!BV:BV,"吸油烟机",工单!BF:BF,"安装",工单!BD:BD,C6)+COUNTIFS(工单!BV:BV,"吸油烟机",工单!BF:BF,"改装",工单!BD:BD,C6)+COUNTIFS(工单!BV:BV,"吸油烟机",工单!BF:BF,"油烟机预埋烟管",工单!BD:BD,C6) -> 0 | W6: =COUNTIFS(CSM配件!R:R,$W$2,CSM配件!F:F,C6)+COUNTIFS(工单自购配件明细!N:N,"防火止回阀",工单自购配件明细!R:R,C6) -> 0 | X6: =W6/V6 -> #DIV/0!
A7: 新疆办事处 | B7: 北屯市速达厨电安装中心 | C7: 杨继认 | D7: =SUMIFS(CSM服务项目!Y:Y,CSM服务项目!Q:Q,$D$2,CSM服务项目!F:F,C7) -> 0 | E7: =SUMIFS(CSM服务项目!Y:Y,CSM服务项目!Q:Q,$E$2,CSM服务项目!F:F,C7) -> 0 | F7: =SUMIFS(CSM配件!AB:AB,CSM配件!R:R,$F$2,CSM配件!F:F,C7) -> 0 | G7: =SUMIFS(CSM配件!AB:AB,CSM配件!R:R,$G$2,CSM配件!F:F,C7) -> 0 | H7: =SUMIFS(CSM配件!AB:AB,CSM配件!R:R,$H$2,CSM配件!F:F,C7) -> 0 | I7: =SUMIFS(CSM配件!AB:AB,CSM配件!R:R,$I$2,CSM配件!F:F,C7) -> 0 | J7: =SUMIFS(CSM配件!AB:AB,CSM配件!R:R,$J$2,CSM配件!F:F,C7) -> 0 | K7: =SUMIFS(CSM配件!AB:AB,CSM配件!R:R,$K$2,CSM配件!F:F,C7) -> 0 | L7: =SUMIFS(CSM配件!AB:AB,CSM配件!R:R,$L$2,CSM配件!F:F,C7) -> 0 | M7: =SUMIFS(CSM配件!AB:AB,CSM配件!R:R,$M$2,CSM配件!F:F,C7) -> 0 | N7: =SUMIFS(CSM配件!AB:AB,CSM配件!R:R,$N$2,CSM配件!F:F,C7) -> 0 | O7: =SUMIFS(CSM配件!AB:AB,CSM配件!R:R,$O$2,CSM配件!F:F,C7) -> 0 | P7: =SUMIFS(CSM配件!AB:AB,CSM配件!R:R,$P$2,CSM配件!F:F,C7) -> 0 | Q7: =SUMIFS(CSM配件!AB:AB,CSM配件!R:R,$Q$2,CSM配件!F:F,C7) -> 0 | R7: =SUM(D7:Q7) -> 0 | S7: =D7+E7+H7 -> 0 | V7: =COUNTIFS(工单!BV:BV,"吸油烟机",工单!BF:BF,"安装",工单!BD:BD,C7)+COUNTIFS(工单!BV:BV,"吸油烟机",工单!BF:BF,"改装",工单!BD:BD,C7)+COUNTIFS(工单!BV:BV,"吸油烟机",工单!BF:BF,"油烟机预埋烟管",工单!BD:BD,C7) -> 0 | W7: =COUNTIFS(CSM配件!R:R,$W$2,CSM配件!F:F,C7)+COUNTIFS(工单自购配件明细!N:N,"防火止回阀",工单自购配件明细!R:R,C7) -> 0 | X7: =W7/V7 -> #DIV/0!
A8: 新疆办事处 | B8: 北屯市王金女家电维修店 | C8: 古永洪 | D8: =SUMIFS(CSM服务项目!Y:Y,CSM服务项目!Q:Q,$D$2,CSM服务项目!F:F,C8) -> 1875 | E8: =SUMIFS(CSM服务项目!Y:Y,CSM服务项目!Q:Q,$E$2,CSM服务项目!F:F,C8) -> 0 | F8: =SUMIFS(CSM配件!AB:AB,CSM配件!R:R,$F$2,CSM配件!F:F,C8) -> 0 | G8: =SUMIFS(CSM配件!AB:AB,CSM配件!R:R,$G$2,CSM配件!F:F,C8) -> 0 | H8: =SUMIFS(CSM配件!AB:AB,CSM配件!R:R,$H$2,CSM配件!F:F,C8) -> 0 | I8: =SUMIFS(CSM配件!AB:AB,CSM配件!R:R,$I$2,CSM配件!F:F,C8) -> 0 | J8: =SUMIFS(CSM配件!AB:AB,CSM配件!R:R,$J$2,CSM配件!F:F,C8) -> 0 | K8: =SUMIFS(CSM配件!AB:AB,CSM配件!R:R,$K$2,CSM配件!F:F,C8) -> 0 | L8: =SUMIFS(CSM配件!AB:AB,CSM配件!R:R,$L$2,CSM配件!F:F,C8) -> 0 | M8: =SUMIFS(CSM配件!AB:AB,CSM配件!R:R,$M$2,CSM配件!F:F,C8) -> 0 | N8: =SUMIFS(CSM配件!AB:AB,CSM配件!R:R,$N$2,CSM配件!F:F,C8) -> 0 | O8: =SUMIFS(CSM配件!AB:AB,CSM配件!R:R,$O$2,CSM配件!F:F,C8) -> 0 | P8: =SUMIFS(CSM配件!AB:AB,CSM配件!R:R,$P$2,CSM配件!F:F,C8) -> 0 | Q8: =SUMIFS(CSM配件!AB:AB,CSM配件!R:R,$Q$2,CSM配件!F:F,C8) -> 0 | R8: =SUM(D8:Q8) -> 1875 | S8: =D8+E8+H8 -> 1875 | V8: =COUNTIFS(工单!BV:BV,"吸油烟机",工单!BF:BF,"安装",工单!BD:BD,C8)+COUNTIFS(工单!BV:BV,"吸油烟机",工单!BF:BF,"改装",工单!BD:BD,C8)+COUNTIFS(工单!BV:BV,"吸油烟机",工单!BF:BF,"油烟机预埋烟管",工单!BD:BD,C8) -> 0 | W8: =COUNTIFS(CSM配件!R:R,$W$2,CSM配件!F:F,C8)+COUNTIFS(工单自购配件明细!N:N,"防火止回阀",工单自购配件明细!R:R,C8) -> 0 | X8: =W8/V8 -> #DIV/0!
A9: 新疆办事处 | B9: 北屯市王金女家电维修店 | C9: 张喜珠 | D9: =SUMIFS(CSM服务项目!Y:Y,CSM服务项目!Q:Q,$D$2,CSM服务项目!F:F,C9) -> 100 | E9: =SUMIFS(CSM服务项目!Y:Y,CSM服务项目!Q:Q,$E$2,CSM服务项目!F:F,C9) -> 0 | F9: =SUMIFS(CSM配件!AB:AB,CSM配件!R:R,$F$2,CSM配件!F:F,C9) -> 100 | G9: =SUMIFS(CSM配件!AB:AB,CSM配件!R:R,$G$2,CSM配件!F:F,C9) -> 0 | H9: =SUMIFS(CSM配件!AB:AB,CSM配件!R:R,$H$2,CSM配件!F:F,C9) -> 380 | I9: =SUMIFS(CSM配件!AB:AB,CSM配件!R:R,$I$2,CSM配件!F:F,C9) -> 0 | J9: =SUMIFS(CSM配件!AB:AB,CSM配件!R:R,$J$2,CSM配件!F:F,C9) -> 35 | K9: =SUMIFS(CSM配件!AB:AB,CSM配件!R:R,$K$2,CSM配件!F:F,C9) -> 108.5 | L9: =SUMIFS(CSM配件!AB:AB,CSM配件!R:R,$L$2,CSM配件!F:F,C9) -> 28 | M9: =SUMIFS(CSM配件!AB:AB,CSM配件!R:R,$M$2,CSM配件!F:F,C9) -> 0 | N9: =SUMIFS(CSM配件!AB:AB,CSM配件!R:R,$N$2,CSM配件!F:F,C9) -> 0 | O9: =SUMIFS(CSM配件!AB:AB,CSM配件!R:R,$O$2,CSM配件!F:F,C9) -> 0 | P9: =SUMIFS(CSM配件!AB:AB,CSM配件!R:R,$P$2,CSM配件!F:F,C9) -> 0 | Q9: =SUMIFS(CSM配件!AB:AB,CSM配件!R:R,$Q$2,CSM配件!F:F,C9) -> 0 | R9: =SUM(D9:Q9) -> 751.5 | S9: =D9+E9+H9 -> 480 | V9: =COUNTIFS(工单!BV:BV,"吸油烟机",工单!BF:BF,"安装",工单!BD:BD,C9)+COUNTIFS(工单!BV:BV,"吸油烟机",工单!BF:BF,"改装",工单!BD:BD,C9)+COUNTIFS(工单!BV:BV,"吸油烟机",工单!BF:BF,"油烟机预埋烟管",工单!BD:BD,C9) -> 1 | W9: =COUNTIFS(CSM配件!R:R,$W$2,CSM配件!F:F,C9)+COUNTIFS(工单自购配件明细!N:N,"防火止回阀",工单自购配件明细!R:R,C9) -> 1 | X9: =W9/V9 -> 1
A10: 新疆办事处 | B10: 北屯市王金女家电维修店 | C10: 赵飞飞 | D10: =SUMIFS(CSM服务项目!Y:Y,CSM服务项目!Q:Q,$D$2,CSM服务项目!F:F,C10) -> 0 | E10: =SUMIFS(CSM服务项目!Y:Y,CSM服务项目!Q:Q,$E$2,CSM服务项目!F:F,C10) -> 0 | F10: =SUMIFS(CSM配件!AB:AB,CSM配件!R:R,$F$2,CSM配件!F:F,C10) -> 600 | G10: =SUMIFS(CSM配件!AB:AB,CSM配件!R:R,$G$2,CSM配件!F:F,C10) -> 0 | H10: =SUMIFS(CSM配件!AB:AB,CSM配件!R:R,$H$2,CSM配件!F:F,C10) -> 160 | I10: =SUMIFS(CSM配件!AB:AB,CSM配件!R:R,$I$2,CSM配件!F:F,C10) -> 0 | J10: =SUMIFS(CSM配件!AB:AB,CSM配件!R:R,$J$2,CSM配件!F:F,C10) -> 343 | K10: =SUMIFS(CSM配件!AB:AB,CSM配件!R:R,$K$2,CSM配件!F:F,C10) -> 28 | L10: =SUMIFS(CSM配件!AB:AB,CSM配件!R:R,$L$2,CSM配件!F:F,C10) -> 112 | M10: =SUMIFS(CSM配件!AB:AB,CSM配件!R:R,$M$2,CSM配件!F:F,C10) -> 0 | N10: =SUMIFS(CSM配件!AB:AB,CSM配件!R:R,$N$2,CSM配件!F:F,C10) -> 0 | O10: =SUMIFS(CSM配件!AB:AB,CSM配件!R:R,$O$2,CSM配件!F:F,C10) -> 0 | P10: =SUMIFS(CSM配件!AB:AB,CSM配件!R:R,$P$2,CSM配件!F:F,C10) -> 0 | Q10: =SUMIFS(CSM配件!AB:AB,CSM配件!R:R,$Q$2,CSM配件!F:F,C10) -> 0 | R10: =SUM(D10:Q10) -> 1243 | S10: =D10+E10+H10 -> 160 | V10: =COUNTIFS(工单!BV:BV,"吸油烟机",工单!BF:BF,"安装",工单!BD:BD,C10)+COUNTIFS(工单!BV:BV,"吸油烟机",工单!BF:BF,"改装",工单!BD:BD,C10)+COUNTIFS(工单!BV:BV,"吸油烟机",工单!BF:BF,"油烟机预埋烟管",工单!BD:BD,C10) -> 7 | W10: =COUNTIFS(CSM配件!R:R,$W$2,CSM配件!F:F,C10)+COUNTIFS(工单自购配件明细!N:N,"防火止回阀",工单自购配件明细!R:R,C10) -> 6 | X10: =W10/V10 -> 0.85714286
A11: 新疆办事处 | B11: 北屯市王金女家电维修店 | C11: 车攀宁 | D11: =SUMIFS(CSM服务项目!Y:Y,CSM服务项目!Q:Q,$D$2,CSM服务项目!F:F,C11) -> 0 | E11: =SUMIFS(CSM服务项目!Y:Y,CSM服务项目!Q:Q,$E$2,CSM服务项目!F:F,C11) -> 0 | F11: =SUMIFS(CSM配件!AB:AB,CSM配件!R:R,$F$2,CSM配件!F:F,C11) -> 700 | G11: =SUMIFS(CSM配件!AB:AB,CSM配件!R:R,$G$2,CSM配件!F:F,C11) -> 0 | H11: =SUMIFS(CSM配件!AB:AB,CSM配件!R:R,$H$2,CSM配件!F:F,C11) -> 0 | I11: =SUMIFS(CSM配件!AB:AB,CSM配件!R:R,$I$2,CSM配件!F:F,C11) -> 0 | J11: =SUMIFS(CSM配件!AB:AB,CSM配件!R:R,$J$2,CSM配件!F:F,C11) -> 245 | K11: =SUMIFS(CSM配件!AB:AB,CSM配件!R:R,$K$2,CSM配件!F:F,C11) -> 0 | L11: =SUMIFS(CSM配件!AB:AB,CSM配件!R:R,$L$2,CSM配件!F:F,C11) -> 56 | M11: =SUMIFS(CSM配件!AB:AB,CSM配件!R:R,$M$2,CSM配件!F:F,C11) -> 0 | N11: =SUMIFS(CSM配件!AB:AB,CSM配件!R:R,$N$2,CSM配件!F:F,C11) -> 59.5 | O11: =SUMIFS(CSM配件!AB:AB,CSM配件!R:R,$O$2,CSM配件!F:F,C11) -> 0 | P11: =SUMIFS(CSM配件!AB:AB,CSM配件!R:R,$P$2,CSM配件!F:F,C11) -> 0 | Q11: =SUMIFS(CSM配件!AB:AB,CSM配件!R:R,$Q$2,CSM配件!F:F,C11) -> 0 | R11: =SUM(D11:Q11) -> 1060.5 | S11: =D11+E11+H11 -> 0 | V11: =COUNTIFS(工单!BV:BV,"吸油烟机",工单!BF:BF,"安装",工单!BD:BD,C11)+COUNTIFS(工单!BV:BV,"吸油烟机",工单!BF:BF,"改装",工单!BD:BD,C11)+COUNTIFS(工单!BV:BV,"吸油烟机",工单!BF:BF,"油烟机预埋烟管",工单!BD:BD,C11) -> 6 | W11: =COUNTIFS(CSM配件!R:R,$W$2,CSM配件!F:F,C11)+COUNTIFS(工单自购配件明细!N:N,"防火止回阀",工单自购配件明细!R:R,C11) -> 7 | X11: =W11/V11 -> 1.1666667
A12: 新疆办事处 | B12: 北屯市王金女家电维修店 | C12: 王伟俊 | D12: =SUMIFS(CSM服务项目!Y:Y,CSM服务项目!Q:Q,$D$2,CSM服务项目!F:F,C12) -> 0 | E12: =SUMIFS(CSM服务项目!Y:Y,CSM服务项目!Q:Q,$E$2,CSM服务项目!F:F,C12) -> 389.3 | F12: =SUMIFS(CSM配件!AB:AB,CSM配件!R:R,$F$2,CSM配件!F:F,C12) -> 900 | G12: =SUMIFS(CSM配件!AB:AB,CSM配件!R:R,$G$2,CSM配件!F:F,C12) -> 0 | H12: =SUMIFS(CSM配件!AB:AB,CSM配件!R:R,$H$2,CSM配件!F:F,C12) -> 0 | I12: =SUMIFS(CSM配件!AB:AB,CSM配件!R:R,$I$2,CSM配件!F:F,C12) -> 0 | J12: =SUMIFS(CSM配件!AB:AB,CSM配件!R:R,$J$2,CSM配件!F:F,C12) -> 280 | K12: =SUMIFS(CSM配件!AB:AB,CSM配件!R:R,$K$2,CSM配件!F:F,C12) -> 203 | L12: =SUMIFS(CSM配件!AB:AB,CSM配件!R:R,$L$2,CSM配件!F:F,C12) -> 56 | M12: =SUMIFS(CSM配件!AB:AB,CSM配件!R:R,$M$2,CSM配件!F:F,C12) -> 0 | N12: =SUMIFS(CSM配件!AB:AB,CSM配件!R:R,$N$2,CSM配件!F:F,C12) -> 0 | O12: =SUMIFS(CSM配件!AB:AB,CSM配件!R:R,$O$2,CSM配件!F:F,C12) -> 0 | P12: =SUMIFS(CSM配件!AB:AB,CSM配件!R:R,$P$2,CSM配件!F:F,C12) -> 0 | Q12: =SUMIFS(CSM配件!AB:AB,CSM配件!R:R,$Q$2,CSM配件!F:F,C12) -> 0 | R12: =SUM(D12:Q12) -> 1828.3 | S12: =D12+E12+H12 -> 389.3 | V12: =COUNTIFS(工单!BV:BV,"吸油烟机",工单!BF:BF,"安装",工单!BD:BD,C12)+COUNTIFS(工单!BV:BV,"吸油烟机",工单!BF:BF,"改装",工单!BD:BD,C12)+COUNTIFS(工单!BV:BV,"吸油烟机",工单!BF:BF,"油烟机预埋烟管",工单!BD:BD,C12) -> 7 | W12: =COUNTIFS(CSM配件!R:R,$W$2,CSM配件!F:F,C12)+COUNTIFS(工单自购配件明细!N:N,"防火止回阀",工单自购配件明细!R:R,C12) -> 9 | X12: =W12/V12 -> 1.2857143
A13: 新疆办事处 | B13: 北屯市王金女家电维修店 | C13: 孟凡新 | D13: =SUMIFS(CSM服务项目!Y:Y,CSM服务项目!Q:Q,$D$2,CSM服务项目!F:F,C13) -> 0 | E13: =SUMIFS(CSM服务项目!Y:Y,CSM服务项目!Q:Q,$E$2,CSM服务项目!F:F,C13) -> 343.5 | F13: =SUMIFS(CSM配件!AB:AB,CSM配件!R:R,$F$2,CSM配件!F:F,C13) -> 400 | G13: =SUMIFS(CSM配件!AB:AB,CSM配件!R:R,$G$2,CSM配件!F:F,C13) -> 0 | H13: =SUMIFS(CSM配件!AB:AB,CSM配件!R:R,$H$2,CSM配件!F:F,C13) -> 0 | I13: =SUMIFS(CSM配件!AB:AB,CSM配件!R:R,$I$2,CSM配件!F:F,C13) -> 0 | J13: =SUMIFS(CSM配件!AB:AB,CSM配件!R:R,$J$2,CSM配件!F:F,C13) -> 245 | K13: =SUMIFS(CSM配件!AB:AB,CSM配件!R:R,$K$2,CSM配件!F:F,C13) -> 0 | L13: =SUMIFS(CSM配件!AB:AB,CSM配件!R:R,$L$2,CSM配件!F:F,C13) -> 56 | M13: =SUMIFS(CSM配件!AB:AB,CSM配件!R:R,$M$2,CSM配件!F:F,C13) -> 0 | N13: =SUMIFS(CSM配件!AB:AB,CSM配件!R:R,$N$2,CSM配件!F:F,C13) -> 0 | O13: =SUMIFS(CSM配件!AB:AB,CSM配件!R:R,$O$2,CSM配件!F:F,C13) -> 0 | P13: =SUMIFS(CSM配件!AB:AB,CSM配件!R:R,$P$2,CSM配件!F:F,C13) -> 0 | Q13: =SUMIFS(CSM配件!AB:AB,CSM配件!R:R,$Q$2,CSM配件!F:F,C13) -> 0 | R13: =SUM(D13:Q13) -> 1044.5 | S13: =D13+E13+H13 -> 343.5 | V13: =COUNTIFS(工单!BV:BV,"吸油烟机",工单!BF:BF,"安装",工单!BD:BD,C13)+COUNTIFS(工单!BV:BV,"吸油烟机",工单!BF:BF,"改装",工单!BD:BD,C13)+COUNTIFS(工单!BV:BV,"吸油烟机",工单!BF:BF,"油烟机预埋烟管",工单!BD:BD,C13) -> 3 | W13: =COUNTIFS(CSM配件!R:R,$W$2,CSM配件!F:F,C13)+COUNTIFS(工单自购配件明细!N:N,"防火止回阀",工单自购配件明细!R:R,C13) -> 4 | X13: =W13/V13 -> 1.3333333
A14: 新疆办事处 | B14: 北屯市王金女家电维修店 | C14: 王立辉 | D14: =SUMIFS(CSM服务项目!Y:Y,CSM服务项目!Q:Q,$D$2,CSM服务项目!F:F,C14) -> 0 | E14: =SUMIFS(CSM服务项目!Y:Y,CSM服务项目!Q:Q,$E$2,CSM服务项目!F:F,C14) -> 0 | F14: =SUMIFS(CSM配件!AB:AB,CSM配件!R:R,$F$2,CSM配件!F:F,C14) -> 300 | G14: =SUMIFS(CSM配件!AB:AB,CSM配件!R:R,$G$2,CSM配件!F:F,C14) -> 0 | H14: =SUMIFS(CSM配件!AB:AB,CSM配件!R:R,$H$2,CSM配件!F:F,C14) -> 0 | I14: =SUMIFS(CSM配件!AB:AB,CSM配件!R:R,$I$2,CSM配件!F:F,C14) -> 0 | J14: =SUMIFS(CSM配件!AB:AB,CSM配件!R:R,$J$2,CSM配件!F:F,C14) -> 140 | K14: =SUMIFS(CSM配件!AB:AB,CSM配件!R:R,$K$2,CSM配件!F:F,C14) -> 206.5 | L14: =SUMIFS(CSM配件!AB:AB,CSM配件!R:R,$L$2,CSM配件!F:F,C14) -> 0 | M14: =SUMIFS(CSM配件!AB:AB,CSM配件!R:R,$M$2,CSM配件!F:F,C14) -> 0 | N14: =SUMIFS(CSM配件!AB:AB,CSM配件!R:R,$N$2,CSM配件!F:F,C14) -> 0 | O14: =SUMIFS(CSM配件!AB:AB,CSM配件!R:R,$O$2,CSM配件!F:F,C14) -> 0 | P14: =SUMIFS(CSM配件!AB:AB,CSM配件!R:R,$P$2,CSM配件!F:F,C14) -> 0 | Q14: =SUMIFS(CSM配件!AB:AB,CSM配件!R:R,$Q$2,CSM配件!F:F,C14) -> 0 | R14: =SUM(D14:Q14) -> 646.5 | S14: =D14+E14+H14 -> 0 | V14: =COUNTIFS(工单!BV:BV,"吸油烟机",工单!BF:BF,"安装",工单!BD:BD,C14)+COUNTIFS(工单!BV:BV,"吸油烟机",工单!BF:BF,"改装",工单!BD:BD,C14)+COUNTIFS(工单!BV:BV,"吸油烟机",工单!BF:BF,"油烟机预埋烟管",工单!BD:BD,C14) -> 4 | W14: =COUNTIFS(CSM配件!R:R,$W$2,CSM配件!F:F,C14)+COUNTIFS(工单自购配件明细!N:N,"防火止回阀",工单自购配件明细!R:R,C14) -> 3 | X14: =W14/V14 -> 0.75
... A281: 包头办事处 | B281: 伊金霍洛旗刘庆春电器店 | C281: 李勇 | D281: =SUMIFS(CSM服务项目!Y:Y,CSM服务项目!Q:Q,$D$2,CSM服务项目!F:F,C281) -> 0 | E281: =SUMIFS(CSM服务项目!Y:Y,CSM服务项目!Q:Q,$E$2,CSM服务项目!F:F,C281) -> 0 | F281: =SUMIFS(CSM配件!AB:AB,CSM配件!R:R,$F$2,CSM配件!F:F,C281) -> 100 | G281: =SUMIFS(CSM配件!AB:AB,CSM配件!R:R,$G$2,CSM配件!F:F,C281) -> 0 | H281: =SUMIFS(CSM配件!AB:AB,CSM配件!R:R,$H$2,CSM配件!F:F,C281) -> 0 | I281: =SUMIFS(CSM配件!AB:AB,CSM配件!R:R,$I$2,CSM配件!F:F,C281) -> 0 | J281: =SUMIFS(CSM配件!AB:AB,CSM配件!R:R,$J$2,CSM配件!F:F,C281) -> 280 | K281: =SUMIFS(CSM配件!AB:AB,CSM配件!R:R,$K$2,CSM配件!F:F,C281) -> 35 | L281: =SUMIFS(CSM配件!AB:AB,CSM配件!R:R,$L$2,CSM配件!F:F,C281) -> 0 | M281: =SUMIFS(CSM配件!AB:AB,CSM配件!R:R,$M$2,CSM配件!F:F,C281) -> 0 | N281: =SUMIFS(CSM配件!AB:AB,CSM配件!R:R,$N$2,CSM配件!F:F,C281) -> 0 | O281: =SUMIFS(CSM配件!AB:AB,CSM配件!R:R,$O$2,CSM配件!F:F,C281) -> 0 | P281: =SUMIFS(CSM配件!AB:AB,CSM配件!R:R,$P$2,CSM配件!F:F,C281) -> 0 | Q281: =SUMIFS(CSM配件!AB:AB,CSM配件!R:R,$Q$2,CSM配件!F:F,C281) -> 0 | R281: =SUM(D281:Q281) -> 415 | S281: =D281+E281+H281 -> 0 | V281: =COUNTIFS(工单!BV:BV,"吸油烟机",工单!BF:BF,"安装",工单!BD:BD,C281)+COUNTIFS(工单!BV:BV,"吸油烟机",工单!BF:BF,"改装",工单!BD:BD,C281)+COUNTIFS(工单!BV:BV,"吸油烟机",工单!BF:BF,"油烟机预埋烟管",工单!BD:BD,C281) -> 11 | W281: =COUNTIFS(CSM配件!R:R,$W$2,CSM配件!F:F,C281)+COUNTIFS(工单自购配件明细!N:N,"防火止回阀",工单自购配件明细!R:R,C281) -> 1 | X281: =W281/V281 -> 0.090909091

Sheet WMS网点买断配件明细
A1: WMS网点买断配件明细
A2: 大区 | B2: 办事处名称 | C2: 所属服务中心 | D2: CSM网点名称 | E2: 订单号 | F2: 配件编码 | G2: 配件名称 | H2: 数量 | I2: 实收总金额（上缴金额） | J2: 配件分类 | K2: 销售分类 | L2: 发货时间 | M2: 传输时间
A3: 西北大区部 | B3: 包头办事处 | C3: 包头服务中心 | D3: 青山区厨小帮家电维修门店 | E3: CK20260805000071 | F3: 1506040100586 | G3: 洗碗机专用盐-2KG/瓶-/ | H3: 4 | I3: 60 | J3: H | K3: 清洁耗材 | L3: 46242.521 | M3: 2026-08-08 23:00:01
A4: 西北大区部 | B4: 包头办事处 | C4: 包头服务中心 | D4: 青山区厨小帮家电维修门店 | E4: CK20260805000071 | F4: 1507020201567 | G4: 快速接头(螺纹)-RBG-S10×15-GB/T26002-WJ(2025) | H4: 10 | I4: 44.4 | J4: H | K4: 燃气管快速接头 | L4: 46242.521 | M4: 2026-08-08 23:00:01
A5: 西北大区部 | B5: 包头办事处 | C5: 包头服务中心 | D5: 青山区厨小帮家电维修门店 | E5: CK20260805000071 | F5: 1507020201554 | G5: 不锈钢波纹软管-RSB-10-GB/T26002-30m-WJ(2025) | H5: 1 | I5: 408.21 | J5: H | K5: 水/气路金属软管 | L5: 46242.521 | M5: 2026-08-08 23:00:01
A6: 西北大区部 | B6: 包头办事处 | C6: 包头服务中心 | D6: 青山区厨小帮家电维修门店 | E6: CK20260806000119 | F6: 1506040100619 | G6: 锅支架清洁膏(正式装)-250g膏体-/ | H6: 24 | I6: 384 | J6: B | K6: 清洁耗材 | L6: 46242.52 | M6: 2026-08-08 14:00:01
A7: 西北大区部 | B7: 兰州办事处 | C7: 兰州服务中心 | D7: 西峰区二牛电器维修服务中心 | E7: CK20260805000054 | F7: 1507020201554 | G7: 不锈钢波纹软管-RSB-10-GB/T26002-30m-WJ(2025) | H7: 3 | I7: 1224.63 | J7: H | K7: 水/气路金属软管 | L7: 46239.677 | M7: 2026-08-05 23:00:07
A8: 西北大区部 | B8: 兰州办事处 | C8: 兰州服务中心 | D8: 天水晨旺家电服务有限公司 | E8: CK20260805000051 | F8: 1507020201569 | G8: 快速接头(螺纹)-RBG-S13×15-GB/T26002-WJ(2025) | H8: 200 | I8: 1004 | J8: H | K8: 燃气管快速接头 | L8: 46239.676 | M8: 2026-08-05 23:00:08
A9: 西北大区部 | B9: 兰州办事处 | C9: 兰州服务中心 | D9: 天水晨旺家电服务有限公司 | E9: CK20260805000051 | F9: 1507020201557 | G9: 不锈钢波纹软管-RSB-13-GB/T26002-30m-WJ(2025) | H9: 8 | I9: 3702.24 | J9: H | K9: 水/气路金属软管 | L9: 46239.676 | M9: 2026-08-05 23:00:08
A10: 西北大区部 | B10: 兰州办事处 | C10: 兰州服务中心 | D10: 武都百佳润电器维修服务中心 | E10: CK20260805000050 | F10: 1507020201557 | G10: 不锈钢波纹软管-RSB-13-GB/T26002-30m-WJ(2025) | H10: 1 | I10: 462.78 | J10: H | K10: 水/气路金属软管 | L10: 46239.665 | M10: 2026-08-05 23:00:07
A11: 西北大区部 | B11: 兰州办事处 | C11: 兰州服务中心 | D11: 永登鑫元家电维修部（个体工商户） | E11: CK20260804000014 | F11: 1507020201554 | G11: 不锈钢波纹软管-RSB-10-GB/T26002-30m-WJ(2025) | H11: 5 | I11: 2041.05 | J11: H | K11: 水/气路金属软管 | L11: 46238.431 | M11: 2026-08-04 23:00:04
A12: 西北大区部 | B12: 西宁办事处 | C12: 兰州服务中心 | D12: 西宁广仁技术服务有限公司 | E12: CK20260729000093 | F12: 1506040100577 | G12: 蒸烤产品油污清洗套装-500ml-/ | H12: 1 | I12: 40 | J12: H | K12: 清洁耗材 | L12: 46232.686
A13: 西北大区部 | B13: 新疆办事处 | C13: 乌鲁木齐服务中心 | D13: 昌吉市井清家电维修服务部 | E13: CK20260805000031 | F13: 1507020201554 | G13: 不锈钢波纹软管-RSB-10-GB/T26002-30m-WJ(2025) | H13: 10 | I13: 4082.1 | J13: H | K13: 水/气路金属软管 | L13: 46239.451 | M13: 2026-08-05 23:00:06
A14: 西北大区部 | B14: 新疆办事处 | C14: 乌鲁木齐服务中心 | D14: 库尔勒泽玉家电维修服务中心（个体工商户） | E14: CK20260806000104 | F14: 1507020201567 | G14: 快速接头(螺纹)-RBG-S10×15-GB/T26002-WJ(2025) | H14: 50 | I14: 222 | J14: H | K14: 燃气管快速接头 | L14: 46240.761 | M14: 2026-08-06 23:00:05
A15: 西北大区部 | B15: 新疆办事处 | C15: 乌鲁木齐服务中心 | D15: 库尔勒泽玉家电维修服务中心（个体工商户） | E15: CK20260806000104 | F15: 1507020201554 | G15: 不锈钢波纹软管-RSB-10-GB/T26002-30m-WJ(2025) | H15: 1 | I15: 408.21 | J15: H | K15: 水/气路金属软管 | L15: 46240.761 | M15: 2026-08-06 23:00:05
A16: 西北大区部 | B16: 新疆办事处 | C16: 乌鲁木齐服务中心 | D16: 库尔勒远祥家电维修部 | E16: CK20260806000103 | F16: 1507020201567 | G16: 快速接头(螺纹)-RBG-S10×15-GB/T26002-WJ(2025) | H16: 50 | I16: 222 | J16: H | K16: 燃气管快速接头 | L16: 46240.738 | M16: 2026-08-06 23:00:04
A17: 西北大区部 | B17: 新疆办事处 | C17: 乌鲁木齐服务中心 | D17: 库尔勒远祥家电维修部 | E17: CK20260806000103 | F17: 1507020201554 | G17: 不锈钢波纹软管-RSB-10-GB/T26002-30m-WJ(2025) | H17: 1 | I17: 408.21 | J17: H | K17: 水/气路金属软管 | L17: 46240.738 | M17: 2026-08-06 23:00:04
A18: 西北大区部 | B18: 新疆办事处 | C18: 乌鲁木齐服务中心 | D18: 阿克苏市零壹家电维修部 | E18: CK20260806000099 | F18: 1507020201554 | G18: 不锈钢波纹软管-RSB-10-GB/T26002-30m-WJ(2025) | H18: 2 | I18: 816.42 | J18: H | K18: 水/气路金属软管 | L18: 46240.713 | M18: 2026-08-06 23:00:04
A19: 西北大区部 | B19: 新疆办事处 | C19: 乌鲁木齐服务中心 | D19: 阿克苏市零壹家电维修部 | E19: CK20260806000099 | F19: 1507020201567 | G19: 快速接头(螺纹)-RBG-S10×15-GB/T26002-WJ(2025) | H19: 50 | I19: 222 | J19: H | K19: 燃气管快速接头 | L19: 46240.713 | M19: 2026-08-06 23:00:04
A20: 西北大区部 | B20: 新疆办事处 | C20: 乌鲁木齐服务中心 | D20: 昌吉市井清家电维修服务部 | E20: CK20260806000097 | F20: 1507020201566 | G20: 快速接头(插口)-RBG-S10×Φ9.5-GB/T26002-WJ(2025) | H20: 100 | I20: 907 | J20: H | K20: 燃气管快速接头 | L20: 46240.708 | M20: 2026-08-06 23:00:04
A21: 西北大区部 | B21: 新疆办事处 | C21: 乌鲁木齐服务中心 | D21: 昌吉市井清家电维修服务部 | E21: CK20260806000097 | F21: 1507020201567 | G21: 快速接头(螺纹)-RBG-S10×15-GB/T26002-WJ(2025) | H21: 200 | I21: 888 | J21: H | K21: 燃气管快速接头 | L21: 46240.708 | M21: 2026-08-06 23:00:04
A22: 西北大区部 | B22: 新疆办事处 | C22: 乌鲁木齐服务中心 | D22: 昌吉市井清家电维修服务部 | E22: CK20260806000097 | F22: 1507020201554 | G22: 不锈钢波纹软管-RSB-10-GB/T26002-30m-WJ(2025) | H22: 5 | I22: 2041.05 | J22: H | K22: 水/气路金属软管 | L22: 46240.708 | M22: 2026-08-06 23:00:04
A23: 西北大区部 | B23: 呼和浩特办事处 | C23: 呼和浩特服务中心 | D23: 呼和浩特市回民区彦辰家电维修经营部 | E23: CK20260803000024 | F23: 1507020201532 | G23: 气路不锈钢波纹软管-螺纹+插口-2000-套塑-WJ(CCC) | H23: 2 | I23: 97.52 | J23: H | K23: 水/气路金属软管 | L23: 46238.429 | M23: 2026-08-04 23:00:03
A24: 西北大区部 | B24: 呼和浩特办事处 | C24: 呼和浩特服务中心 | D24: 呼和浩特市回民区彦辰家电维修经营部 | E24: CK20260803000024 | F24: 1507020201523 | G24: 气路不锈钢波纹软管-螺纹+插口-1000-套塑-WJ(CCC) | H24: 15 | I24: 387.45 | J24: H | K24: 水/气路金属软管 | L24: 46238.429 | M24: 2026-08-04 23:00:03
... A30: 西北大区部 | B30: 宁夏办事处 | C30: 宁夏服务中心 | D30: 永宁县杨和镇易玖利家电服务部 | E30: CK20260807000007 | F30: 1507020200781 | G30: 水路不锈钢波纹软管-(两端螺纹4")400-LF(厨小护) | H30: 8 | I30: 63.36 | J30: H | K30: 水/气路金属软管 | L30: 46241.372 | M30: 2026-08-07 23:00:04
A31: 西北大区部 | B31: 宁夏办事处 | C31: 宁夏服务中心 | D31: 永宁县杨和镇鑫界家电配送维修中心 | E31: CK20260806000095 | F31: 110100260088A | G31: 出风罩组件_白色_180_V1R1 | H31: 1 | I31: 45 | J31: A | L31: 46240.706 | M31: 2026-08-06 18:00:02
A32: 西北大区部 | B32: 宁夏办事处 | C32: 宁夏服务中心 | D32: 永宁县杨和镇鑫界家电配送维修中心 | E32: CK20260806000095 | F32: 110100092084G | G32: 油杯组件(EM31) | H32: 1 | I32: 35 | J32: A | L32: 46240.706 | M32: 2026-08-06 18:00:02
A33: 西北大区部 | B33: 宁夏办事处 | C33: 宁夏服务中心 | D33: 永宁县杨和镇鑫界家电配送维修中心 | E33: CK20260806000089 | F33: 1507020200781 | G33: 水路不锈钢波纹软管-(两端螺纹4")400-LF(厨小护) | H33: 8 | I33: 63.36 | J33: H | K33: 水/气路金属软管 | L33: 46240.693 | M33: 2026-08-06 23:00:04
A34: 西北大区部 | B34: 宁夏办事处 | C34: 宁夏服务中心 | D34: 永宁县杨和镇鑫界家电配送维修中心 | E34: CK20260806000089 | F34: 1507020200780 | G34: 水路不锈钢波纹软管-(两端螺纹4")500-LF(厨小护) | H34: 4 | I34: 36.8 | J34: H | K34: 水/气路金属软管 | L34: 46240.693 | M34: 2026-08-06 23:00:04
A35: 西北大区部 | B35: 宁夏办事处 | C35: 宁夏服务中心 | D35: 永宁县杨和镇鑫界家电配送维修中心 | E35: CK20260806000088 | F35: 1506040100621 | G35: 洗碗机专用洗涤粉-1KG/瓶(含包装盒)-/FW | H35: 3 | I35: 126 | J35: H | K35: 清洁耗材 | L35: 46240.688 | M35: 2026-08-06 23:00:03
A36: 西北大区部 | B36: 宁夏办事处 | C36: 宁夏服务中心 | D36: 永宁县杨和镇鑫界家电配送维修中心 | E36: CK20260806000088 | F36: 1506040100586 | G36: 洗碗机专用盐-2KG/瓶-/ | H36: 3 | I36: 45 | J36: H | K36: 清洁耗材 | L36: 46240.688 | M36: 2026-08-06 23:00:03
A37: 西北大区部 | B37: 宁夏办事处 | C37: 宁夏服务中心 | D37: 永宁县杨和镇鑫界家电配送维修中心 | E37: CK20260806000088 | F37: 1506040100585 | G37: 洗碗机专用漂洗剂-500ml/瓶-/ | H37: 3 | I37: 57 | J37: H | K37: 清洁耗材 | L37: 46240.688 | M37: 2026-08-06 23:00:03
A38: 西北大区部 | B38: 宁夏办事处 | C38: 宁夏服务中心 | D38: 永宁县杨和镇中天家电维修部 | E38: CK20260806000038 | F38: 1506040100577 | G38: 蒸烤产品油污清洗套装-500ml-/ | H38: 3 | I38: 120 | J38: H | K38: 清洁耗材 | L38: 46240.481 | M38: 2026-08-06 23:00:04
A39: 西北大区部 | B39: 宁夏办事处 | C39: 宁夏服务中心 | D39: 贺兰县家玺家电维修部 | E39: CK20260806000008 | F39: 1506040100565 | G39: 厨小护养护四件套-/-象山 | H39: 2 | I39: 178 | J39: H | K39: 清洁耗材 | L39: 46240.381 | M39: 2026-08-06 23:00:02
A40: 西北大区部 | B40: 宁夏办事处 | C40: 宁夏服务中心 | D40: 永宁县杨和镇中天家电维修部 | E40: CK20260804000009 | F40: 1507020200781 | G40: 水路不锈钢波纹软管-(两端螺纹4")400-LF(厨小护) | H40: 10 | I40: 79.2 | J40: H | K40: 水/气路金属软管 | L40: 46238.455 | M40: 2026-08-04 23:00:05
A41: 西北大区部 | B41: 宁夏办事处 | C41: 宁夏服务中心 | D41: 灵武市灵梅军家电快修店 | E41: CK20260809000022 | F41: 1507020200781 | G41: 水路不锈钢波纹软管-(两端螺纹4")400-LF(厨小护) | H41: 6 | I41: 47.52 | J41: H | K41: 水/气路金属软管 | L41: 46243.69 | M41: 2026-08-09 23:00:01
A42: 西北大区部 | B42: 宁夏办事处 | C42: 宁夏服务中心 | D42: 灵武市灵梅军家电快修店 | E42: CK20260809000022 | F42: 1507020200780 | G42: 水路不锈钢波纹软管-(两端螺纹4")500-LF(厨小护) | H42: 10 | I42: 92 | J42: H | K42: 水/气路金属软管 | L42: 46243.69 | M42: 2026-08-09 23:00:01
A43: 西北大区部 | B43: 宁夏办事处 | C43: 宁夏服务中心 | D43: 灵武市灵梅军家电快修店 | E43: CK20260802000012 | F43: 1506040100619 | G43: 锅支架清洁膏(正式装)-250g膏体-/ | H43: 10 | I43: 160 | J43: B | K43: 清洁耗材 | L43: 46236.465 | M43: 2026-08-02 13:00:01
A44: 西北大区部 | B44: 宁夏办事处 | C44: 宁夏服务中心 | D44: 永宁县杨和镇鑫界家电配送维修中心 | E44: CK20260731000037 | F44: 1506040100621 | G44: 洗碗机专用洗涤粉-1KG/瓶(含包装盒)-/FW | H44: 3 | I44: 126 | J44: H | K44: 清洁耗材 | L44: 46234.485
A45: 西北大区部 | B45: 宁夏办事处 | C45: 宁夏服务中心 | D45: 永宁县杨和镇鑫界家电配送维修中心 | E45: CK20260731000037 | F45: 1506040100586 | G45: 洗碗机专用盐-2KG/瓶-/ | H45: 3 | I45: 45 | J45: H | K45: 清洁耗材 | L45: 46234.485
A46: 西北大区部 | B46: 宁夏办事处 | C46: 宁夏服务中心 | D46: 永宁县杨和镇鑫界家电配送维修中心 | E46: CK20260731000037 | F46: 1506040100585 | G46: 洗碗机专用漂洗剂-500ml/瓶-/ | H46: 3 | I46: 57 | J46: H | K46: 清洁耗材 | L46: 46234.485
A47: 西北大区部 | B47: 宁夏办事处 | C47: 宁夏服务中心 | D47: 永宁县杨和镇鑫界家电配送维修中心 | E47: CK20260731000014 | F47: 1506040100619 | G47: 锅支架清洁膏(正式装)-250g膏体-/ | H47: 1 | I47: 16 | J47: B | K47: 清洁耗材 | L47: 46234.432
A48: 西北大区部 | B48: 宁夏办事处 | C48: 宁夏服务中心 | D48: 永宁县杨和镇易玖利家电服务部 | E48: CK20260731000002 | F48: 1506040100586 | G48: 洗碗机专用盐-2KG/瓶-/ | H48: 6 | I48: 90 | J48: H | K48: 清洁耗材 | L48: 46234.367
A49: 西北大区部 | B49: 宁夏办事处 | C49: 宁夏服务中心 | D49: 灵武市灵梅军家电快修店 | E49: CK20260730000045 | F49: 1506040100621 | G49: 洗碗机专用洗涤粉-1KG/瓶(含包装盒)-/FW | H49: 2 | I49: 84 | J49: H | K49: 清洁耗材 | L49: 46233.713
A50: 西北大区部 | B50: 宁夏办事处 | C50: 宁夏服务中心 | D50: 灵武市灵梅军家电快修店 | E50: CK20260730000045 | F50: 1506040100586 | G50: 洗碗机专用盐-2KG/瓶-/ | H50: 2 | I50: 30 | J50: H | K50: 清洁耗材 | L50: 46233.713
A51: 西北大区部 | B51: 宁夏办事处 | C51: 宁夏服务中心 | D51: 灵武市灵梅军家电快修店 | E51: CK20260730000045 | F51: 1506040100585 | G51: 洗碗机专用漂洗剂-500ml/瓶-/ | H51: 2 | I51: 38 | J51: H | K51: 清洁耗材 | L51: 46233.713
A52: 西北大区部 | B52: 宁夏办事处 | C52: 宁夏服务中心 | D52: 固原市原州区凯鑫电器经销部 | E52: CK20260730000039 | F52: 1506040100565 | G52: 厨小护养护四件套-/-象山 | H52: 1 | I52: 89 | J52: H | K52: 清洁耗材 | L52: 46233.686
A53: 西北大区部 | B53: 宁夏办事处 | C53: 宁夏服务中心 | D53: 固原市原州区凯鑫电器经销部 | E53: CK20260730000038 | F53: 1506040100565 | G53: 厨小护养护四件套-/-象山 | H53: 1 | I53: 89 | J53: H | K53: 清洁耗材 | L53: 46233.686
A54: 西北大区部 | B54: 宁夏办事处 | C54: 宁夏服务中心 | D54: 永宁县杨和镇中天家电维修部 | E54: CK20260729000099 | F54: 1506040100565 | G54: 厨小护养护四件套-/-象山 | H54: 3 | I54: 267 | J54: H | K54: 清洁耗材 | L54: 46232.736
A55: 西北大区部 | B55: 宁夏办事处 | C55: 宁夏服务中心 | D55: 固原市原州区凯鑫电器经销部 | E55: CK20260729000098 | F55: 1506040100586 | G55: 洗碗机专用盐-2KG/瓶-/ | H55: 2 | I55: 30 | J55: H | K55: 清洁耗材 | L55: 46232.714
... A70: 西北大区部 | B70: 宁夏办事处 | C70: 宁夏服务中心 | D70: 海原县宏志家电维修中心（个体工商户） | E70: CK20260728000056 | F70: 1506040100585 | G70: 洗碗机专用漂洗剂-500ml/瓶-/ | H70: 1 | I70: 19 | J70: H | K70: 清洁耗材 | L70: 46231.649
A71: 西北大区部 | B71: 宁夏办事处 | C71: 宁夏服务中心 | D71: 贺兰县家玺家电维修部 | E71: CK20260803000003 | F71: 1507020200780 | G71: 水路不锈钢波纹软管-(两端螺纹4")500-LF(厨小护) | H71: 6 | I71: 55.2 | J71: H | K71: 水/气路金属软管 | L71: 46237.385 | M71: 2026-08-03 23:00:04
A72: 西北大区部 | B72: 宁夏办事处 | C72: 宁夏服务中心 | D72: 永宁县杨和镇中天家电维修部 | E72: CK20260803000001 | F72: 1507020200781 | G72: 水路不锈钢波纹软管-(两端螺纹4")400-LF(厨小护) | H72: 8 | I72: 63.36 | J72: H | K72: 水/气路金属软管 | L72: 46237.378 | M72: 2026-08-03 23:00:04
A73: 西北大区部 | B73: 宁夏办事处 | C73: 宁夏服务中心 | D73: 永宁县杨和镇中天家电维修部 | E73: CK20260803000001 | F73: 1507020200780 | G73: 水路不锈钢波纹软管-(两端螺纹4")500-LF(厨小护) | H73: 4 | I73: 36.8 | J73: H | K73: 水/气路金属软管 | L73: 46237.378 | M73: 2026-08-03 23:00:04
A74: 西北大区部 | B74: 宁夏办事处 | C74: 宁夏服务中心 | D74: 固原市原州区凯鑫电器经销部 | E74: CK20260802000033 | F74: 1506040100619 | G74: 锅支架清洁膏(正式装)-250g膏体-/ | H74: 10 | I74: 160 | J74: B | K74: 清洁耗材 | L74: 46236.633 | M74: 2026-08-02 17:00:01
A75: 西北大区部 | B75: 宁夏办事处 | C75: 宁夏服务中心 | D75: 固原市原州区凯鑫电器经销部 | E75: CK20260802000032 | F75: 1506040100577 | G75: 蒸烤产品油污清洗套装-500ml-/ | H75: 2 | I75: 80 | J75: H | K75: 清洁耗材 | L75: 46236.633 | M75: 2026-08-02 23:00:11

Sheet CSM服务项目
A2: 大区 | B2: 办事处 | C2: 服务中心 | D2: 服务网点 | E2: 网点类型 | F2: 服务工程师 | G2: 服务工程师编号 | H2: 录入完成时间 | I2: 传SAP单号 | J2: 工单编号 | K2: 工单类型 | L2: 产品线 | M2: 保内外 | N2: 服务收费项目 | O2: 收费标准金额 | P2: 服务收费金额 | Q2: 销售分类 | R2: 服务收费类型 | S2: 工单应收费用 | T2: 工单实收费用 | U2: 实际收费汇总 | V2: 折扣费用 | W2: 折扣原因 | X2: 其他折扣原因 | Y2: 上缴金额 | Z2: 上缴标准 | AA2: 事业合作制扣款 | AB2: 网点缴费单状态 | AC2: 网点缴费确认时间 | AD2: 技师缴费单状态 | AE2: 技师缴费时间 | AF2: 收费方式 | AG2: 支付状态 | AH2: 开票日期 | AI2: 自购防火阀安装费用 | AJ2: 网点抵扣上缴 | AK2: 结算系列 | AL2: 备注
A3: 西北大区部 | B3: 新疆办事处 | C3: 乌鲁木齐服务中心 | D3: 乌鲁木齐经济技术开发区（头屯河区）明瑞商务服务工作室 | E3: 合作 | F3: 闫玉洁 | G3: JS000027179 | H3: 46241.645 | J3: FGDG20260806003701 | K3: 报修 | L3: 吸油烟机 | M3: 保外 | N3: 油烟机小保养 | O3: 198 | P3: 0 | Q3: 清洗保养 | R3: 标准服务费 | S3: 198 | T3: 0 | U3: 0 | V3: 198 | W3: 活动推广 | Y3: 0 | Z3: 75 | AG3: 未支付 | AH3: 42856 | AI3: 0 | AJ3: 75 | AK3: JQ系列油烟机
A4: 西北大区部 | B4: 新疆办事处 | C4: 乌鲁木齐服务中心 | D4: 阿克苏市零壹家电维修部 | E4: 合作 | F4: 张蒙光 | G4: JS000005116 | H4: 46242.567 | I4: 1-EXB71Y8 | J4: FGDG20260808012308 | K4: 报装 | L4: 嵌入式洗碗机 | M4: 保内 | N4: 橱柜层板、侧板切割 | O4: 100 | P4: 0 | R4: 改装服务费 | S4: 110 | T4: 110 | U4: 0 | V4: 100 | W4: 活动推广 | Y4: 0 | Z4: 0 | AF4: 现金收费 | AG4: 已支付 | AH4: 46241 | AI4: 0 | AJ4: 9999 | AK4: 嵌入式洗碗机
A5: 西北大区部 | B5: 新疆办事处 | C5: 乌鲁木齐服务中心 | D5: 阿克苏市零壹家电维修部 | E5: 合作 | F5: 张蒙光 | G5: JS000005116 | H5: 46242.567 | I5: 1-EXB71Y8 | J5: FGDG20260808012308 | K5: 报装 | L5: 嵌入式洗碗机 | M5: 保内 | N5: 水路整改 | O5: 90 | P5: 0 | R5: 改装服务费 | S5: 110 | T5: 110 | U5: 0 | V5: 90 | W5: 活动推广 | Y5: 0 | Z5: 0 | AF5: 现金收费 | AG5: 已支付 | AH5: 46241 | AI5: 0 | AJ5: 9999 | AK5: 嵌入式洗碗机
A6: 西北大区部 | B6: 新疆办事处 | C6: 乌鲁木齐服务中心 | D6: 阿克苏市零壹家电维修部 | E6: 合作 | F6: 张蒙光 | G6: JS000005116 | H6: 46242.567 | I6: 1-EXB71Y8 | J6: FGDG20260808012308 | K6: 报装 | L6: 嵌入式洗碗机 | M6: 保内 | N6: 橱柜层板和隔板开孔 | O6: 30 | P6: 0 | R6: 其他服务费 | S6: 110 | T6: 110 | U6: 0 | V6: 30 | W6: 活动推广 | Y6: 0 | Z6: 0 | AF6: 现金收费 | AG6: 已支付 | AH6: 46241 | AI6: 0 | AJ6: 9999 | AK6: 嵌入式洗碗机
A7: 西北大区部 | B7: 新疆办事处 | C7: 乌鲁木齐服务中心 | D7: 昌吉市井清家电维修服务部 | E7: 合作 | F7: 张喜泉 | G7: JS000032400 | H7: 46242.709 | J7: FGDG20260807018792 | K7: 报装 | L7: 吸油烟机 | M7: 保内 | N7: 客供防火阀、防烟宝、防雨罩安装费 | O7: 50 | P7: 0 | R7: 其他服务费 | S7: 0 | T7: 0 | U7: 0 | V7: 50 | W7: 活动推广 | Y7: 0 | Z7: 0 | AG7: 未支付 | AH7: 46212 | AI7: 0 | AJ7: 50 | AK7: JQ系列油烟机
A8: 西北大区部 | B8: 兰州办事处 | C8: 兰州服务中心 | D8: 白银区小顾电器维修服务经营部（个体工商户） | E8: 合作 | F8: 顾生德 | G8: JS000012141 | H8: 46242.467 | J8: FGDG20260807016424 | K8: 报装 | L8: 吸油烟机 | M8: 保内 | N8: 客供防火阀、防烟宝、防雨罩安装费 | O8: 50 | P8: 0 | R8: 其他服务费 | S8: 0 | T8: 0 | U8: 0 | V8: 50 | W8: 电商/每誉补贴 | Y8: 0 | Z8: 0 | AG8: 未支付 | AH8: 46176 | AI8: 0 | AJ8: 50 | AK8: JQ系列油烟机
A9: 西北大区部 | B9: 新疆办事处 | C9: 乌鲁木齐服务中心 | D9: 昌吉市井清家电维修服务部 | E9: 合作 | F9: 王忠义 | G9: JS000008869 | H9: 46243.742 | J9: FGDG20260807020740 | K9: 报装 | L9: 吸油烟机 | M9: 保内 | N9: 客供防火阀、防烟宝、防雨罩安装费 | O9: 50 | P9: 0 | R9: 其他服务费 | S9: 0 | T9: 0 | U9: 0 | V9: 50 | W9: 活动推广 | Y9: 0 | Z9: 0 | AG9: 未支付 | AH9: 46242 | AI9: 0 | AJ9: 50 | AK9: JQ系列油烟机
A10: 西北大区部 | B10: 新疆办事处 | C10: 乌鲁木齐服务中心 | D10: 阿克苏市零壹家电维修部 | E10: 合作 | F10: 张蒙光 | G10: JS000005116 | H10: 46236.55 | I10: 1-EVMJGLU | J10: FGDG20260801017491 | K10: 报装 | L10: 水槽洗碗机 | M10: 保内 | N10: 橱柜层板、侧板切割 | O10: 100 | P10: 0 | R10: 改装服务费 | S10: 120 | T10: 120 | U10: 0 | V10: 100 | W10: 活动推广 | Y10: 0 | Z10: 0 | AD10: 已确认 | AE10: 46239.704 | AF10: 现金收费 | AG10: 已支付 | AH10: 46235 | AI10: 0 | AJ10: 9999 | AK10: 水槽洗碗机
A11: 西北大区部 | B11: 新疆办事处 | C11: 乌鲁木齐服务中心 | D11: 阿克苏市零壹家电维修部 | E11: 合作 | F11: 张蒙光 | G11: JS000005116 | H11: 46236.55 | I11: 1-EVMJGLU | J11: FGDG20260801017491 | K11: 报装 | L11: 水槽洗碗机 | M11: 保内 | N11: 台面开扩孔 | O11: 160 | P11: 0 | R11: 改装服务费 | S11: 120 | T11: 120 | U11: 0 | V11: 160 | W11: 活动推广 | Y11: 0 | Z11: 0 | AD11: 已确认 | AE11: 46239.704 | AF11: 现金收费 | AG11: 已支付 | AH11: 46235 | AI11: 0 | AJ11: 9999 | AK11: 水槽洗碗机
A12: 西北大区部 | B12: 新疆办事处 | C12: 乌鲁木齐服务中心 | D12: 阿克苏市零壹家电维修部 | E12: 合作 | F12: 张蒙光 | G12: JS000005116 | H12: 46243.663 | J12: FGDG20260808017977 | K12: 报装 | L12: 吸油烟机 | M12: 保内 | N12: 客供防火阀、防烟宝、防雨罩安装费 | O12: 50 | P12: 0 | R12: 其他服务费 | S12: 0 | T12: 0 | U12: 0 | V12: 50 | W12: 活动推广 | Y12: 0 | Z12: 0 | AG12: 未支付 | AH12: 46241 | AI12: 0 | AJ12: 50 | AK12: JQ系列油烟机
A13: 西北大区部 | B13: 包头办事处 | C13: 包头服务中心 | D13: 包头服务中心零售网点 | E13: 自营 | F13: 张红峰 | G13: JS000001125 | H13: 46243.457 | J13: FGDG20260807019293 | K13: 报修 | L13: 吸油烟机 | M13: 保外 | N13: 油烟机小保养 | O13: 198 | P13: 0 | Q13: 清洗保养 | R13: 标准服务费 | S13: 198 | T13: 0 | U13: 0 | V13: 198 | W13: 活动推广 | Y13: 0 | Z13: 198 | AG13: 未支付 | AH13: 41497 | AI13: 0 | AJ13: 75 | AK13: 欧式油烟机
A14: 西北大区部 | B14: 包头办事处 | C14: 包头服务中心 | D14: 青山区厨小帮家电维修门店 | E14: 合作 | F14: 段亚南 | G14: JS000019834 | H14: 46236.43 | J14: FGDG20260801018303 | K14: 报装 | L14: 嵌入式洗碗机 | M14: 保内 | N14: 橱柜层板和隔板开孔 | O14: 30 | P14: 0 | R14: 其他服务费 | S14: 0 | T14: 0 | U14: 0 | V14: 30 | W14: 活动推广 | Y14: 0 | Z14: 0 | AG14: 未支付 | AH14: 46235 | AI14: 0 | AJ14: 9999 | AK14: 嵌入式洗碗机
A15: 西北大区部 | B15: 新疆办事处 | C15: 乌鲁木齐服务中心 | D15: 北屯市王金女家电维修店 | E15: 合作 | F15: 古永洪 | G15: JS000015956 | H15: 46236.726 | J15: FGDG20260801011265 | K15: 报修 | L15: 吸油烟机 | M15: 保外 | N15: 油烟机小保养 | O15: 198 | P15: 0 | Q15: 清洗保养 | R15: 标准服务费 | S15: 198 | T15: 0 | U15: 0 | V15: 198 | W15: 活动推广 | Y15: 0 | Z15: 75 | AG15: 未支付 | AH15: 43288 | AI15: 0 | AJ15: 75 | AK15: 欧式油烟机
A16: 西北大区部 | B16: 兰州办事处 | C16: 兰州服务中心 | D16: 金川区乐万佳家电维修中心 | E16: 合作 | F16: 冯玉祥 | G16: JS000021208 | H16: 46236.506 | J16: FGDG20260730026366 | K16: 报装 | L16: 吸油烟机 | M16: 保内 | N16: 客供防火阀、防烟宝、防雨罩安装费 | O16: 50 | P16: 0 | R16: 其他服务费 | S16: 0 | T16: 0 | U16: 0 | V16: 50 | W16: 活动推广 | Y16: 0 | Z16: 0 | AG16: 未支付 | AH16: 46205 | AI16: 0 | AJ16: 50 | AK16: JQ系列油烟机
A17: 西北大区部 | B17: 新疆办事处 | C17: 乌鲁木齐服务中心 | D17: 昌吉市井清家电维修服务部 | E17: 合作 | F17: 王文奎 | G17: JS000000576 | H17: 46236.497 | I17: 1-EVMJKJ2 | J17: FGDG20260730010790 | K17: 报装 | L17: 嵌入式洗碗机 | M17: 保内 | N17: 橱柜层板、侧板切割 | O17: 100 | P17: 0 | R17: 改装服务费 | S17: 50 | T17: 50 | U17: 0 | V17: 100 | W17: 活动推广 | Y17: 0 | Z17: 0 | AB17: 已确认 | AC17: 46239.714 | AD17: 已确认 | AE17: 46239.685 | AF17: 现金收费 | AG17: 已支付 | AH17: 46204 | AI17: 0 | AJ17: 9999 | AK17: 嵌入式洗碗机
A18: 西北大区部 | B18: 新疆办事处 | C18: 乌鲁木齐服务中心 | D18: 昌吉市井清家电维修服务部 | E18: 合作 | F18: 王文奎 | G18: JS000000576 | H18: 46236.497 | I18: 1-EVMJKJ2 | J18: FGDG20260730010790 | K18: 报装 | L18: 嵌入式洗碗机 | M18: 保内 | N18: 橱柜拆装 | O18: 80 | P18: 0 | R18: 其他服务费 | S18: 50 | T18: 50 | U18: 0 | V18: 80 | W18: 活动推广 | Y18: 0 | Z18: 0 | AB18: 已确认 | AC18: 46239.714 | AD18: 已确认 | AE18: 46239.685 | AF18: 现金收费 | AG18: 已支付 | AH18: 46204 | AI18: 0 | AJ18: 9999 | AK18: 嵌入式洗碗机
A19: 西北大区部 | B19: 新疆办事处 | C19: 乌鲁木齐服务中心 | D19: 昌吉市井清家电维修服务部 | E19: 合作 | F19: 王文奎 | G19: JS000000576 | H19: 46236.497 | I19: 1-EVMJKJ2 | J19: FGDG20260730010790 | K19: 报装 | L19: 嵌入式洗碗机 | M19: 保内 | N19: 橱柜层板和隔板开孔 | O19: 30 | P19: 0 | R19: 其他服务费 | S19: 50 | T19: 50 | U19: 0 | V19: 30 | W19: 活动推广 | Y19: 0 | Z19: 0 | AB19: 已确认 | AC19: 46239.714 | AD19: 已确认 | AE19: 46239.685 | AF19: 现金收费 | AG19: 已支付 | AH19: 46204 | AI19: 0 | AJ19: 9999 | AK19: 嵌入式洗碗机
A20: 西北大区部 | B20: 兰州办事处 | C20: 兰州服务中心 | D20: 七里河兴旺电器维修服务经营部 | E20: 合作 | F20: 王立杰 | G20: JS000035630 | H20: 46240.525 | J20: FGDG20260804009456 | K20: 报修 | L20: 吸油烟机 | M20: 保外 | N20: 油烟机小保养 | O20: 198 | P20: 0 | Q20: 清洗保养 | R20: 标准服务费 | S20: 198 | T20: 0 | U20: 0 | V20: 198 | W20: 活动推广 | Y20: 0 | Z20: 75 | AG20: 未支付 | AH20: 41188 | AI20: 0 | AJ20: 75 | AK20: 欧式油烟机
A21: 西北大区部 | B21: 兰州办事处 | C21: 兰州服务中心 | D21: 兰州百洁立家政服务有限公司 | E21: 合作 | F21: 张龙 | G21: JS000031493 | H21: 46240.467 | J21: FGDG20260804009735 | K21: 报装 | L21: 吸油烟机 | M21: 保内 | N21: 客供防火阀、防烟宝、防雨罩安装费 | O21: 50 | P21: 0 | R21: 其他服务费 | S21: 0 | T21: 0 | U21: 0 | V21: 50 | W21: 活动推广 | Y21: 0 | Z21: 0 | AG21: 未支付 | AH21: 46236 | AI21: 0 | AJ21: 50 | AK21: 欧式油烟机
A22: 西北大区部 | B22: 兰州办事处 | C22: 兰州服务中心 | D22: 永登鑫元家电维修部（个体工商户） | E22: 合作 | F22: 张天珍 | G22: JS000019822 | H22: 46241.761 | J22: FGDG20260807026880 | K22: 其他 | L22: 嵌入式洗碗机 | M22: 保内 | N22: 门板改造 | O22: 200 | P22: 0 | R22: 改装服务费 | S22: 0 | T22: 0 | U22: 0 | V22: 200 | W22: 电商/每誉补贴 | Y22: 0 | Z22: 0 | AG22: 未支付 | AH22: 46236 | AI22: 0 | AJ22: 9999 | AK22: 嵌入式洗碗机
A23: 西北大区部 | B23: 兰州办事处 | C23: 兰州服务中心 | D23: 永登鑫元家电维修部（个体工商户） | E23: 合作 | F23: 张天珍 | G23: JS000019822 | H23: 46241.761 | J23: FGDG20260807026880 | K23: 其他 | L23: 嵌入式洗碗机 | M23: 保内 | N23: 橱柜层板、侧板切割 | O23: 100 | P23: 0 | R23: 改装服务费 | S23: 0 | T23: 0 | U23: 0 | V23: 100 | W23: 电商/每誉补贴 | Y23: 0 | Z23: 0 | AG23: 未支付 | AH23: 46236 | AI23: 0 | AJ23: 9999 | AK23: 嵌入式洗碗机
A24: 西北大区部 | B24: 兰州办事处 | C24: 兰州服务中心 | D24: 永登鑫元家电维修部（个体工商户） | E24: 合作 | F24: 张天珍 | G24: JS000019822 | H24: 46241.761 | J24: FGDG20260807026880 | K24: 其他 | L24: 嵌入式洗碗机 | M24: 保内 | N24: 电源整改 | O24: 40 | P24: 0 | R24: 改装服务费 | S24: 0 | T24: 0 | U24: 0 | V24: 40 | W24: 电商/每誉补贴 | Y24: 0 | Z24: 0 | AG24: 未支付 | AH24: 46236 | AI24: 0 | AJ24: 9999 | AK24: 嵌入式洗碗机
A25: 西北大区部 | B25: 兰州办事处 | C25: 兰州服务中心 | D25: 永登鑫元家电维修部（个体工商户） | E25: 合作 | F25: 张天珍 | G25: JS000019822 | H25: 46241.761 | J25: FGDG20260807026880 | K25: 其他 | L25: 嵌入式洗碗机 | M25: 保内 | N25: 橱柜层板和隔板开孔 | O25: 30 | P25: 0 | R25: 其他服务费 | S25: 0 | T25: 0 | U25: 0 | V25: 30 | W25: 电商/每誉补贴 | Y25: 0 | Z25: 0 | AG25: 未支付 | AH25: 46236 | AI25: 0 | AJ25: 9999 | AK25: 嵌入式洗碗机
A26: 西北大区部 | B26: 新疆办事处 | C26: 乌鲁木齐服务中心 | D26: 乌鲁木齐经济技术开发区（头屯河区）明瑞商务服务工作室 | E26: 合作 | F26: 项光普 | G26: JS000016577 | H26: 46235.841 | I26: 1-EVCGRDX | J26: FGDG20260731014266 | K26: 报装 | L26: 水槽洗碗机 | M26: 保内 | N26: 橱柜层板、侧板切割 | O26: 100 | P26: 0 | R26: 改装服务费 | S26: 140 | T26: 140 | U26: 0 | V26: 100 | W26: 活动推广 | Y26: 0 | Z26: 0 | AB26: 已确认 | AC26: 46236.474 | AF26: 在线支付 | AG26: 已支付 | AH26: 46174 | AI26: 0 | AJ26: 9999 | AK26: 水槽洗碗机
A27: 西北大区部 | B27: 新疆办事处 | C27: 乌鲁木齐服务中心 | D27: 乌鲁木齐经济技术开发区（头屯河区）明瑞商务服务工作室 | E27: 合作 | F27: 项光普 | G27: JS000016577 | H27: 46235.841 | I27: 1-EVCGRDX | J27: FGDG20260731014266 | K27: 报装 | L27: 水槽洗碗机 | M27: 保内 | N27: 台面钻孔（净水机水龙头孔、燃气管道贯穿孔） | O27: 30 | P27: 0 | R27: 其他服务费 | S27: 140 | T27: 140 | U27: 0 | V27: 30 | W27: 活动推广 | Y27: 0 | Z27: 0 | AB27: 已确认 | AC27: 46236.474 | AF27: 在线支付 | AG27: 已支付 | AH27: 46174 | AI27: 0 | AJ27: 9999 | AK27: 水槽洗碗机
A28: 西北大区部 | B28: 新疆办事处 | C28: 乌鲁木齐服务中心 | D28: 乌鲁木齐经济技术开发区（头屯河区）明瑞商务服务工作室 | E28: 合作 | F28: 项光普 | G28: JS000016577 | H28: 46235.841 | I28: 1-EVCGRDX | J28: FGDG20260731014266 | K28: 报装 | L28: 水槽洗碗机 | M28: 保内 | N28: 台面开扩孔 | O28: 160 | P28: 0 | R28: 改装服务费 | S28: 140 | T28: 140 | U28: 0 | V28: 160 | W28: 活动推广 | Y28: 0 | Z28: 0 | AB28: 已确认 | AC28: 46236.474 | AF28: 在线支付 | AG28: 已支付 | AH28: 46174 | AI28: 0 | AJ28: 9999 | AK28: 水槽洗碗机
A29: 西北大区部 | B29: 新疆办事处 | C29: 乌鲁木齐服务中心 | D29: 新疆服务中心零售网点 | E29: 自营 | F29: 侯守云 | G29: JS000002991 | H29: 46238.715 | J29: FGDG20260803011220 | K29: 报修 | L29: 吸油烟机 | M29: 保内 | N29: 油烟机小保养 | O29: 198 | P29: 0 | Q29: 清洗保养 | R29: 标准服务费 | S29: 198 | T29: 0 | U29: 0 | V29: 198 | W29: 活动推广 | Y29: 0 | Z29: 198 | AG29: 未支付 | AH29: 45524 | AI29: 0 | AJ29: 75 | AK29: 欧式油烟机
A30: 西北大区部 | B30: 西宁办事处 | C30: 兰州服务中心 | D30: 西宁广仁技术服务有限公司 | E30: 合作 | F30: 赵久云 | G30: JS000037117 | H30: 46238.552 | J30: FGDG20260802005133 | K30: 报装 | L30: 吸油烟机 | M30: 保内 | N30: 客供防火阀、防烟宝、防雨罩安装费 | O30: 50 | P30: 0 | R30: 其他服务费 | S30: 0 | T30: 0 | U30: 0 | V30: 50 | W30: 活动推广 | Y30: 0 | Z30: 0 | AG30: 未支付 | AH30: 46237 | AI30: 0 | AJ30: 50 | AK30: JQ系列油烟机
A31: 西北大区部 | B31: 兰州办事处 | C31: 兰州服务中心 | D31: 西峰区二牛电器维修服务中心 | E31: 合作 | F31: 牛二伟 | G31: JS000023510 | H31: 46241.825 | J31: FGDG20260805022108 | K31: 其他 | L31: 水槽洗碗机 | M31: 保内 | N31: 橱柜层板、侧板切割 | O31: 100 | P31: 0 | R31: 改装服务费 | S31: 0 | T31: 0 | U31: 0 | V31: 100 | W31: 电商/每誉补贴 | Y31: 0 | Z31: 0 | AG31: 未支付 | AH31: 46237 | AI31: 0 | AJ31: 9999 | AK31: 水槽洗碗机
A32: 西北大区部 | B32: 兰州办事处 | C32: 兰州服务中心 | D32: 西峰区二牛电器维修服务中心 | E32: 合作 | F32: 牛二伟 | G32: JS000023510 | H32: 46241.825 | J32: FGDG20260805022108 | K32: 其他 | L32: 水槽洗碗机 | M32: 保内 | N32: 台面开扩孔 | O32: 160 | P32: 0 | R32: 改装服务费 | S32: 0 | T32: 0 | U32: 0 | V32: 160 | W32: 电商/每誉补贴 | Y32: 0 | Z32: 0 | AG32: 未支付 | AH32: 46237 | AI32: 0 | AJ32: 9999 | AK32: 水槽洗碗机
A33: 西北大区部 | B33: 兰州办事处 | C33: 兰州服务中心 | D33: 凉州区罗涛家电维修服务中心 | E33: 合作 | F33: 罗涛 | G33: JS000003912 | H33: 46235.417 | J33: FGDG20260731015078 | K33: 报装 | L33: 吸油烟机 | M33: 保外 | N33: 客供防火阀、防烟宝、防雨罩安装费 | O33: 50 | P33: 0 | R33: 其他服务费 | S33: 0 | T33: 0 | U33: 0 | V33: 50 | W33: 活动推广 | Y33: 0 | Z33: 0 | AG33: 未支付 | AI33: 0 | AJ33: 50 | AK33: JQ系列油烟机
A34: 西北大区部 | B34: 兰州办事处 | C34: 兰州服务中心 | D34: 甘肃瑞康通商贸有限公司 | E34: 合作 | F34: 冯治琮 | G34: JS000009205 | H34: 46238.728 | J34: FGDG20260802030209 | K34: 报装 | L34: 吸油烟机 | M34: 保内 | N34: 客供防火阀、防烟宝、防雨罩安装费 | O34: 50 | P34: 0 | R34: 其他服务费 | S34: 0 | T34: 0 | U34: 0 | V34: 50 | W34: 活动推广 | Y34: 0 | Z34: 0 | AG34: 未支付 | AH34: 46230 | AI34: 0 | AJ34: 50 | AK34: JQ系列油烟机
A35: 西北大区部 | B35: 兰州办事处 | C35: 兰州服务中心 | D35: 七里河兴旺电器维修服务经营部 | E35: 合作 | F35: 王文斌 | G35: JS000026313 | H35: 46241.516 | J35: FGDG20260806014294 | K35: 报装 | L35: 吸油烟机 | M35: 保内 | N35: 【电商】装饰罩安装费 | O35: 50 | P35: 0 | R35: 基础服务费 | S35: 50 | T35: 0 | U35: 0 | V35: 50 | W35: 活动推广 | Y35: 0 | Z35: 0 | AG35: 未支付 | AH35: 46235 | AI35: 0 | AJ35: 9999 | AK35: 欧式油烟机
A36: 西北大区部 | B36: 包头办事处 | C36: 包头服务中心 | D36: 伊金霍洛旗刘庆春电器店 | E36: 合作 | F36: 李勇 | G36: JS000028758 | H36: 46235.855 | I36: 1-EVCG9XA | J36: FGDG20260801025500 | K36: 报装 | L36: 吸油烟机 | M36: 保内 | N36: 客供防火阀、防烟宝、防雨罩安装费 | O36: 50 | P36: 0 | R36: 其他服务费 | S36: 320 | T36: 320 | U36: 0 | V36: 50 | W36: 客户端授权减免 | Y36: 0 | Z36: 0 | AF36: 现金收费 | AG36: 已支付 | AH36: 46228 | AI36: 0 | AJ36: 50 | AK36: 欧式油烟机
A37: 西北大区部 | B37: 兰州办事处 | C37: 兰州服务中心 | D37: 天水晨旺家电服务有限公司 | E37: 合作 | F37: 蒋涛 | G37: JS000012246 | H37: 46238.713 | J37: FGDG20260803004067 | K37: 报装 | L37: 吸油烟机 | M37: 保外 | N37: 客供防火阀、防烟宝、防雨罩安装费 | O37: 50 | P37: 0 | R37: 其他服务费 | S37: 0 | T37: 0 | U37: 0 | V37: 50 | W37: 活动推广 | Y37: 0 | Z37: 0 | AG37: 未支付 | AI37: 0 | AJ37: 50 | AK37: 欧式油烟机
A38: 西北大区部 | B38: 兰州办事处 | C38: 兰州服务中心 | D38: 庆阳加美电器服务有限公司 | E38: 合作 | F38: 葛志银 | G38: JS000037959 | H38: 46242.514 | J38: FGDG20260803008699 | K38: 报装 | L38: 吸油烟机 | M38: 保内 | N38: 客供防火阀、防烟宝、防雨罩安装费 | O38: 50 | P38: 0 | R38: 其他服务费 | S38: 0 | T38: 0 | U38: 0 | V38: 50 | W38: 电商/每誉补贴 | Y38: 0 | Z38: 0 | AG38: 未支付 | AH38: 46241 | AI38: 0 | AJ38: 50 | AK38: JQ系列油烟机
A39: 西北大区部 | B39: 新疆办事处 | C39: 乌鲁木齐服务中心 | D39: 独山子区湘龙家用燃具行 | E39: 合作 | F39: 赵家峰 | G39: JS000006770 | H39: 46235.795 | J39: FGDG20260801021426 | K39: 报装 | L39: 嵌入式洗碗机 | M39: 保内 | N39: 【套餐】单独收费项二（封顶300元） | O39: 300 | P39: 0 | R39: 其他服务费 | S39: 0 | T39: 0 | U39: 0 | V39: 300 | W39: 在线购买 | Y39: 0 | Z39: 0 | AG39: 未支付 | AH39: 46234 | AI39: 0 | AJ39: 9999 | AK39: 嵌入式洗碗机
A40: 西北大区部 | B40: 新疆办事处 | C40: 乌鲁木齐服务中心 | D40: 昌吉市井清家电维修服务部 | E40: 合作 | F40: 徐栋谍 | G40: JS000002811 | H40: 46235.537 | J40: FGDG20260730023728 | K40: 报装 | L40: 水槽洗碗机 | M40: 保内 | N40: 橱柜层板、侧板切割 | O40: 100 | P40: 0 | R40: 改装服务费 | S40: 0 | T40: 0 | U40: 0 | V40: 100 | W40: 电商/每誉补贴 | Y40: 0 | Z40: 0 | AG40: 未支付 | AH40: 46204 | AI40: 0 | AJ40: 9999 | AK40: 水槽洗碗机
A41: 西北大区部 | B41: 新疆办事处 | C41: 乌鲁木齐服务中心 | D41: 昌吉市井清家电维修服务部 | E41: 合作 | F41: 徐栋谍 | G41: JS000002811 | H41: 46235.537 | J41: FGDG20260730023728 | K41: 报装 | L41: 水槽洗碗机 | M41: 保内 | N41: 台面开扩孔 | O41: 160 | P41: 0 | R41: 改装服务费 | S41: 0 | T41: 0 | U41: 0 | V41: 160 | W41: 电商/每誉补贴 | Y41: 0 | Z41: 0 | AG41: 未支付 | AH41: 46204 | AI41: 0 | AJ41: 9999 | AK41: 水槽洗碗机
A42: 西北大区部 | B42: 呼和浩特办事处 | C42: 呼和浩特服务中心 | D42: 内蒙古洁莱电器安装服务有限公司 | E42: 合作 | F42: 侯小乐 | G42: JS000025735 | H42: 46240.653 | I42: 1-EWQXHKO | J42: FGDG20260731021700 | K42: 报装 | L42: 吸油烟机 | M42: 保内 | N42: 【电商】装饰罩安装费 | O42: 50 | P42: 0 | R42: 基础服务费 | S42: 130 | T42: 80 | U42: 0 | V42: 50 | W42: 重要/特殊客户 | Y42: 0 | Z42: 0 | AG42: 未支付 | AH42: 46082 | AI42: 0 | AJ42: 9999 | AK42: JQ系列油烟机
A43: 西北大区部 | B43: 宁夏办事处 | C43: 宁夏服务中心 | D43: 永宁县杨和镇易玖利家电服务部 | E43: 合作 | F43: 张凯祥 | G43: JS000013384 | H43: 46242.718 | J43: FGDG20260808025037 | K43: 其他 | L43: 吸油烟机 | M43: 保内 | N43: 客供防火阀、防烟宝、防雨罩安装费 | O43: 50 | P43: 0 | R43: 其他服务费 | S43: 0 | T43: 0 | U43: 0 | V43: 50 | W43: 活动推广 | Y43: 0 | Z43: 0 | AG43: 未支付 | AH43: 46241 | AI43: 0 | AJ43: 50 | AK43: JQ系列油烟机
A44: 西北大区部 | B44: 兰州办事处 | C44: 兰州服务中心 | D44: 七里河区盛远家电安装维修部 | E44: 合作 | F44: 王永成 | G44: JS000008359 | H44: 46241.739 | J44: FGDG20260806009460 | K44: 报装 | L44: 水槽洗碗机 | M44: 保内 | N44: 橱柜层板、侧板切割 | O44: 100 | P44: 0 | R44: 改装服务费 | S44: 0 | T44: 0 | U44: 0 | V44: 100 | W44: 活动推广 | Y44: 0 | Z44: 0 | AG44: 未支付 | AH44: 46239 | AI44: 0 | AJ44: 9999 | AK44: 水槽洗碗机
A45: 西北大区部 | B45: 兰州办事处 | C45: 兰州服务中心 | D45: 七里河区盛远家电安装维修部 | E45: 合作 | F45: 王永成 | G45: JS000008359 | H45: 46241.739 | J45: FGDG20260806009460 | K45: 报装 | L45: 水槽洗碗机 | M45: 保内 | N45: 台面开扩孔 | O45: 160 | P45: 0 | R45: 改装服务费 | S45: 0 | T45: 0 | U45: 0 | V45: 160 | W45: 活动推广 | Y45: 0 | Z45: 0 | AG45: 未支付 | AH45: 46239 | AI45: 0 | AJ45: 9999 | AK45: 水槽洗碗机
A46: 西北大区部 | B46: 兰州办事处 | C46: 兰州服务中心 | D46: 平凉市崆峒区向阳建材经销部 | E46: 合作 | F46: 王宝义 | G46: JS000003103 | H46: 46241.697 | I46: 1-EX0UDHI | J46: FGDG20260805026619 | K46: 报装 | L46: 吸油烟机 | M46: 保内 | N46: 客供防火阀、防烟宝、防雨罩安装费 | O46: 50 | P46: 0 | R46: 其他服务费 | S46: 50 | T46: 50 | U46: 0 | V46: 50 | W46: 活动推广 | Y46: 0 | Z46: 0 | AB46: 已提交 | AF46: 现金收费 | AG46: 已支付 | AH46: 46235 | AI46: 0 | AJ46: 50 | AK46: JQ系列油烟机
A47: 西北大区部 | B47: 兰州办事处 | C47: 兰州服务中心 | D47: 七里河兴旺电器维修服务经营部 | E47: 合作 | F47: 王立杰 | G47: JS000035630 | H47: 46233.632 | J47: FGDG20260730011950 | K47: 报装 | L47: 吸油烟机 | M47: 保内 | N47: 客供防火阀、防烟宝、防雨罩安装费 | O47: 50 | P47: 0 | R47: 其他服务费 | S47: 0 | T47: 0 | U47: 0 | V47: 50 | W47: 活动推广 | Y47: 0 | Z47: 0 | AG47: 未支付 | AH47: 46230 | AI47: 0 | AJ47: 50 | AK47: JQ系列油烟机
A48: 西北大区部 | B48: 新疆办事处 | C48: 乌鲁木齐服务中心 | D48: 昌吉市井清家电维修服务部 | E48: 合作 | F48: 徐栋谍 | G48: JS000002811 | H48: 46233.679 | J48: FGDG20260730022248 | K48: 报装 | L48: 吸油烟机 | M48: 保内 | N48: 客供防火阀、防烟宝、防雨罩安装费 | O48: 50 | P48: 0 | R48: 其他服务费 | S48: 0 | T48: 0 | U48: 0 | V48: 50 | W48: 在线购买 | Y48: 0 | Z48: 0 | AG48: 未支付 | AH48: 46226 | AI48: 0 | AJ48: 50 | AK48: JQ系列油烟机
A49: 西北大区部 | B49: 新疆办事处 | C49: 乌鲁木齐服务中心 | D49: 乌鲁木齐经济技术开发区（头屯河区）明瑞商务服务工作室 | E49: 合作 | F49: 张小强 | G49: JS000026680 | H49: 46233.544 | J49: FGDG20260728030754 | K49: 报修 | L49: 吸油烟机 | M49: 保外 | N49: 油烟机小保养 | O49: 198 | P49: 0 | Q49: 清洗保养 | R49: 标准服务费 | S49: 198 | T49: 0 | U49: 0 | V49: 198 | W49: 活动推广 | Y49: 0 | Z49: 75 | AG49: 未支付 | AH49: 43646 | AI49: 0 | AJ49: 75 | AK49: JQ系列油烟机
A50: 西北大区部 | B50: 新疆办事处 | C50: 乌鲁木齐服务中心 | D50: 北屯市王金女家电维修店 | E50: 合作 | F50: 赵飞飞 | G50: JS000030840 | H50: 46237.513 | I50: 1-EVWO1P0 | J50: FGDG20260802015778 | K50: 报装 | L50: 嵌入式洗碗机 | M50: 保内 | N50: 橱柜层板和隔板开孔 | O50: 30 | P50: 0 | R50: 其他服务费 | S50: 320 | T50: 320 | U50: 0 | V50: 30 | W50: 活动推广 | Y50: 0 | Z50: 0 | AB50: 已确认 | AC50: 46237.835 | AD50: 已确认 | AE50: 46238.459 | AF50: 现金收费 | AG50: 已支付 | AH50: 46206 | AI50: 0 | AJ50: 9999 | AK50: 嵌入式洗碗机
A51: 西北大区部 | B51: 西宁办事处 | C51: 兰州服务中心 | D51: 西宁广仁技术服务有限公司 | E51: 合作 | F51: 赵久云 | G51: JS000037117 | H51: 46237.61 | J51: FGDG20260803018699 | K51: 其他 | L51: 吸油烟机 | M51: 保内 | N51: 客供防火阀、防烟宝、防雨罩安装费 | O51: 50 | P51: 0 | R51: 其他服务费 | S51: 0 | T51: 0 | U51: 0 | V51: 50 | W51: 活动推广 | Y51: 0 | Z51: 0 | AG51: 未支付 | AH51: 46236 | AI51: 0 | AJ51: 50 | AK51: JQ系列油烟机
A52: 西北大区部 | B52: 包头办事处 | C52: 包头服务中心 | D52: 青山区厨小帮家电维修门店 | E52: 合作 | F52: 段亚南 | G52: JS000019834 | H52: 46234.734 | J52: FGDG20260731022832 | K52: 报装 | L52: 嵌入式洗碗机 | M52: 保内 | N52: 橱柜层板和隔板开孔 | O52: 30 | P52: 0 | R52: 其他服务费 | S52: 0 | T52: 0 | U52: 0 | V52: 30 | W52: 电商/每誉补贴 | Y52: 0 | Z52: 0 | AG52: 未支付 | AH52: 46233 | AI52: 0 | AJ52: 9999 | AK52: 嵌入式洗碗机
A53: 西北大区部 | B53: 包头办事处 | C53: 包头服务中心 | D53: 青山区厨小帮家电维修门店 | E53: 合作 | F53: 段亚南 | G53: JS000019834 | H53: 46234.734 | J53: FGDG20260731022832 | K53: 报装 | L53: 嵌入式洗碗机 | M53: 保内 | N53: 【套餐】单独收费项一（封顶300元） | O53: 300 | P53: 0 | R53: 其他服务费 | S53: 0 | T53: 0 | U53: 0 | V53: 300 | W53: 电商/每誉补贴 | Y53: 0 | Z53: 0 | AG53: 未支付 | AH53: 46233 | AI53: 0 | AJ53: 9999 | AK53: 嵌入式洗碗机
A54: 西北大区部 | B54: 宁夏办事处 | C54: 宁夏服务中心 | D54: 永宁县杨和镇中天家电维修部 | E54: 合作 | F54: 薛雷 | G54: JS000020413 | H54: 46234.403 | I54: 1-EV28R0S | J54: FGDG20260729011848 | K54: 报装 | L54: 吸油烟机 | M54: 保内 | N54: 客供防火阀、防烟宝、防雨罩安装费 | O54: 50 | P54: 0 | R54: 其他服务费 | S54: 50 | T54: 50 | U54: 0 | V54: 50 | W54: 活动推广 | Y54: 0 | Z54: 0 | AF54: 现金收费 | AG54: 已支付 | AH54: 46172 | AI54: 0 | AJ54: 50 | AK54: JQ系列油烟机
A55: 西北大区部 | B55: 兰州办事处 | C55: 兰州服务中心 | D55: 凉州区罗涛家电维修服务中心 | E55: 合作 | F55: 罗涛 | G55: JS000003912 | H55: 46239.507 | I55: 1-EWGWT6W | J55: FGDG20260802009007 | K55: 报装 | L55: 水槽洗碗机 | M55: 保内 | N55: 铰链移位 | O55: 15 | P55: 0 | R55: 其他服务费 | S55: 40 | T55: 40 | U55: 0 | V55: 15 | W55: 活动推广 | Y55: 0 | Z55: 0 | AD55: 已确认 | AE55: 46241.372 | AF55: 现金收费 | AG55: 已支付 | AH55: 46238 | AI55: 0 | AJ55: 9999 | AK55: 水槽洗碗机
A56: 西北大区部 | B56: 兰州办事处 | C56: 兰州服务中心 | D56: 凉州区罗涛家电维修服务中心 | E56: 合作 | F56: 罗涛 | G56: JS000003912 | H56: 46239.507 | I56: 1-EWGWT6W | J56: FGDG20260802009007 | K56: 报装 | L56: 水槽洗碗机 | M56: 保内 | N56: 橱柜层板、侧板切割 | O56: 100 | P56: 0 | R56: 改装服务费 | S56: 40 | T56: 40 | U56: 0 | V56: 100 | W56: 活动推广 | Y56: 0 | Z56: 0 | AD56: 已确认 | AE56: 46241.372 | AF56: 现金收费 | AG56: 已支付 | AH56: 46238 | AI56: 0 | AJ56: 9999 | AK56: 水槽洗碗机
A57: 西北大区部 | B57: 兰州办事处 | C57: 兰州服务中心 | D57: 凉州区罗涛家电维修服务中心 | E57: 合作 | F57: 罗涛 | G57: JS000003912 | H57: 46239.507 | I57: 1-EWGWT6W | J57: FGDG20260802009007 | K57: 报装 | L57: 水槽洗碗机 | M57: 保内 | N57: 台面钻孔（净水机水龙头孔、燃气管道贯穿孔） | O57: 30 | P57: 0 | R57: 其他服务费 | S57: 40 | T57: 40 | U57: 0 | V57: 30 | W57: 活动推广 | Y57: 0 | Z57: 0 | AD57: 已确认 | AE57: 46241.372 | AF57: 现金收费 | AG57: 已支付 | AH57: 46238 | AI57: 0 | AJ57: 9999 | AK57: 水槽洗碗机
A58: 西北大区部 | B58: 兰州办事处 | C58: 兰州服务中心 | D58: 凉州区罗涛家电维修服务中心 | E58: 合作 | F58: 罗涛 | G58: JS000003912 | H58: 46239.507 | I58: 1-EWGWT6W | J58: FGDG20260802009007 | K58: 报装 | L58: 水槽洗碗机 | M58: 保内 | N58: 台面开扩孔 | O58: 160 | P58: 0 | R58: 改装服务费 | S58: 40 | T58: 40 | U58: 0 | V58: 160 | W58: 活动推广 | Y58: 0 | Z58: 0 | AD58: 已确认 | AE58: 46241.372 | AF58: 现金收费 | AG58: 已支付 | AH58: 46238 | AI58: 0 | AJ58: 9999 | AK58: 水槽洗碗机
A59: 西北大区部 | B59: 宁夏办事处 | C59: 宁夏服务中心 | D59: 永宁县杨和镇中天家电维修部 | E59: 合作 | F59: 吴承峰 | G59: JS000027704 | H59: 46237.622 | J59: FGDG20260802007336 | K59: 报装 | L59: 吸油烟机 | M59: 保内 | N59: 客供防火阀、防烟宝、防雨罩安装费 | O59: 50 | P59: 0 | R59: 其他服务费 | S59: 0 | T59: 0 | U59: 0 | V59: 50 | W59: 活动推广 | Y59: 0 | Z59: 0 | AG59: 未支付 | AH59: 46230 | AI59: 0 | AJ59: 50 | AK59: JQ系列油烟机
A60: 西北大区部 | B60: 兰州办事处 | C60: 兰州服务中心 | D60: 七里河兴旺电器维修服务经营部 | E60: 合作 | F60: 王文斌 | G60: JS000026313 | H60: 46234.706 | J60: FGDG20260730017266 | K60: 其他 | L60: 吸油烟机 | M60: 保内 | N60: 【电商】装饰罩安装费 | O60: 50 | P60: 0 | R60: 基础服务费 | S60: 50 | T60: 0 | U60: 0 | V60: 50 | W60: 活动推广 | Y60: 0 | Z60: 0 | AG60: 未支付 | AH60: 46226 | AI60: 0 | AJ60: 9999 | AK60: JQ系列油烟机
A61: 西北大区部 | B61: 包头办事处 | C61: 包头服务中心 | D61: 昆都仑区王宏明家电安装部 | E61: 合作 | F61: 刘宇飞 | G61: JS000030277 | H61: 46234.69 | J61: FGDG20260722000705 | K61: 报装 | L61: 水槽洗碗机 | M61: 保内 | N61: 橱柜拆装 | O61: 80 | P61: 0 | R61: 其他服务费 | S61: 0 | T61: 0 | U61: 0 | V61: 80 | W61: 电商/每誉补贴 | Y61: 0 | Z61: 0 | AG61: 未支付 | AH61: 46173 | AI61: 0 | AJ61: 9999 | AK61: 水槽洗碗机
A62: 西北大区部 | B62: 包头办事处 | C62: 包头服务中心 | D62: 昆都仑区王宏明家电安装部 | E62: 合作 | F62: 刘宇飞 | G62: JS000030277 | H62: 46234.69 | J62: FGDG20260722000705 | K62: 报装 | L62: 水槽洗碗机 | M62: 保内 | N62: 橱柜层板和隔板开孔 | O62: 30 | P62: 0 | R62: 其他服务费 | S62: 0 | T62: 0 | U62: 0 | V62: 30 | W62: 电商/每誉补贴 | Y62: 0 | Z62: 0 | AG62: 未支付 | AH62: 46173 | AI62: 0 | AJ62: 9999 | AK62: 水槽洗碗机
A63: 西北大区部 | B63: 包头办事处 | C63: 包头服务中心 | D63: 昆都仑区王宏明家电安装部 | E63: 合作 | F63: 刘宇飞 | G63: JS000030277 | H63: 46234.69 | J63: FGDG20260722000705 | K63: 报装 | L63: 水槽洗碗机 | M63: 保内 | N63: 水路整改 | O63: 90 | P63: 0 | R63: 改装服务费 | S63: 0 | T63: 0 | U63: 0 | V63: 90 | W63: 电商/每誉补贴 | Y63: 0 | Z63: 0 | AG63: 未支付 | AH63: 46173 | AI63: 0 | AJ63: 9999 | AK63: 水槽洗碗机
A64: 西北大区部 | B64: 包头办事处 | C64: 包头服务中心 | D64: 昆都仑区王宏明家电安装部 | E64: 合作 | F64: 刘宇飞 | G64: JS000030277 | H64: 46234.69 | J64: FGDG20260722000705 | K64: 报装 | L64: 水槽洗碗机 | M64: 保内 | N64: 橱柜层板、侧板切割 | O64: 100 | P64: 0 | R64: 改装服务费 | S64: 0 | T64: 0 | U64: 0 | V64: 100 | W64: 电商/每誉补贴 | Y64: 0 | Z64: 0 | AG64: 未支付 | AH64: 46173 | AI64: 0 | AJ64: 9999 | AK64: 水槽洗碗机
A65: 西北大区部 | B65: 兰州办事处 | C65: 兰州服务中心 | D65: 天水晨旺家电服务有限公司 | E65: 合作 | F65: 宁杰 | G65: JS000037604 | H65: 46239.644 | I65: 1-EWGWT3Y | J65: FGDG20260805007838 | K65: 报装 | L65: 水槽洗碗机 | M65: 保内 | N65: 台面开扩孔 | O65: 160 | P65: 0 | R65: 改装服务费 | S65: 330 | T65: 330 | U65: 0 | V65: 160 | W65: 活动推广 | Y65: 0 | Z65: 0 | AD65: 已确认 | AE65: 46241.372 | AF65: 现金收费 | AG65: 已支付 | AH65: 46238 | AI65: 0 | AJ65: 9999 | AK65: 水槽洗碗机
A66: 西北大区部 | B66: 宁夏办事处 | C66: 宁夏服务中心 | D66: 永宁县杨和镇易玖利家电服务部 | E66: 合作 | F66: 张凯祥 | G66: JS000013384 | H66: 46234.628 | J66: FGDG20260725022937 | K66: 报装 | L66: 吸油烟机 | M66: 保外 | N66: 客供防火阀、防烟宝、防雨罩安装费 | O66: 50 | P66: 0 | R66: 其他服务费 | S66: 0 | T66: 0 | U66: 0 | V66: 50 | W66: 活动推广 | Y66: 0 | Z66: 0 | AG66: 未支付 | AI66: 0 | AJ66: 50 | AK66: JQ系列油烟机
A67: 西北大区部 | B67: 西宁办事处 | C67: 兰州服务中心 | D67: 西宁广仁技术服务有限公司 | E67: 合作 | F67: 赵久云 | G67: JS000037117 | H67: 46234.605 | J67: FGDG20260728030674 | K67: 报装 | L67: 吸油烟机 | M67: 保内 | N67: 客供防火阀、防烟宝、防雨罩安装费 | O67: 50 | P67: 0 | R67: 其他服务费 | S67: 0 | T67: 0 | U67: 0 | V67: 50 | W67: 活动推广 | Y67: 0 | Z67: 0 | AG67: 未支付 | AH67: 46233 | AI67: 0 | AJ67: 50 | AK67: JQ系列油烟机
A68: 西北大区部 | B68: 新疆办事处 | C68: 乌鲁木齐服务中心 | D68: 乌鲁木齐经济技术开发区（头屯河区）明瑞商务服务工作室 | E68: 合作 | F68: 苏勇强 | G68: JS000010906 | H68: 46239.511 | J68: FGDG20260804013302 | K68: 报装 | L68: 吸油烟机 | M68: 保内 | N68: 客供防火阀、防烟宝、防雨罩安装费 | O68: 50 | P68: 0 | R68: 其他服务费 | S68: 0 | T68: 0 | U68: 0 | V68: 50 | W68: 活动推广 | Y68: 0 | Z68: 0 | AG68: 未支付 | AH68: 46130 | AI68: 0 | AJ68: 50 | AK68: JQ系列油烟机
A69: 西北大区部 | B69: 兰州办事处 | C69: 兰州服务中心 | D69: 庆阳加美电器服务有限公司 | E69: 合作 | F69: 葛志银 | G69: JS000037959 | H69: 46239.396 | J69: FGDG20260804031027 | K69: 报装 | L69: 吸油烟机 | M69: 保外 | N69: 客供防火阀、防烟宝、防雨罩安装费 | O69: 50 | P69: 0 | R69: 其他服务费 | S69: 0 | T69: 0 | U69: 0 | V69: 50 | W69: 电商/每誉补贴 | Y69: 0 | Z69: 0 | AG69: 未支付 | AI69: 0 | AJ69: 50 | AK69: Z1T/Z3T系列油烟机
A70: 西北大区部 | B70: 新疆办事处 | C70: 乌鲁木齐服务中心 | D70: 昌吉市井清家电维修服务部 | E70: 合作 | F70: 王文奎 | G70: JS000000576 | H70: 46231.715 | I70: 1-EU81PB6 | J70: FGDG20260728004628 | K70: 报装 | L70: 吸油烟机 | M70: 保内 | N70: 客供防火阀、防烟宝、防雨罩安装费 | O70: 50 | P70: 0 | R70: 其他服务费 | S70: 50 | T70: 50 | U70: 0 | V70: 50 | W70: 活动推广 | Y70: 0 | Z70: 0 | AB70: 已确认 | AC70: 46236.466 | AD70: 已确认 | AE70: 46235.433 | AF70: 现金收费 | AG70: 已支付 | AH70: 46229 | AI70: 0 | AJ70: 50 | AK70: 欧式油烟机
A71: 西北大区部 | B71: 新疆办事处 | C71: 乌鲁木齐服务中心 | D71: 阿克苏市零壹家电维修部 | E71: 合作 | F71: 张蒙光 | G71: JS000005116 | H71: 46231.732 | J71: FGDG20260727025746 | K71: 报装 | L71: 吸油烟机 | M71: 保内 | N71: 客供防火阀、防烟宝、防雨罩安装费 | O71: 50 | P71: 0 | R71: 其他服务费 | S71: 0 | T71: 0 | U71: 0 | V71: 50 | W71: 活动推广 | Y71: 0 | Z71: 0 | AG71: 未支付 | AH71: 46230 | AI71: 0 | AJ71: 50 | AK71: J1系列油烟机
A72: 西北大区部 | B72: 呼和浩特办事处 | C72: 呼和浩特服务中心 | D72: 呼和浩特服务中心零售网点 | E72: 自营 | F72: 贾义 | G72: JS000005164 | H72: 46232.382 | J72: FGDG20260728000101 | K72: 报装 | L72: 吸油烟机 | M72: 保外 | N72: 客供防火阀、防烟宝、防雨罩安装费 | O72: 50 | P72: 0 | R72: 其他服务费 | S72: 0 | T72: 0 | U72: 0 | V72: 50 | W72: 活动推广 | Y72: 0 | Z72: 50 | AG72: 未支付 | AI72: 0 | AJ72: 50 | AK72: JQ系列油烟机
A73: 西北大区部 | B73: 宁夏办事处 | C73: 宁夏服务中心 | D73: 永宁县杨和镇鑫界家电配送维修中心 | E73: 合作 | F73: 贺亮 | G73: JS000016501 | H73: 46232.736 | I73: 1-EV26EJB | J73: FGDG20260727003983 | K73: 报装 | L73: 水槽洗碗机 | M73: 保内 | N73: 橱柜层板和隔板开孔 | O73: 30 | P73: 0 | R73: 其他服务费 | S73: 225 | T73: 200 | U73: 0 | V73: 30 | W73: 电商/每誉补贴 | Y73: 0 | Z73: 0 | AB73: 已确认 | AC73: 46234.584 | AF73: 现金收费 | AG73: 已支付 | AH73: 46202 | AI73: 0 | AJ73: 9999 | AK73: 水槽洗碗机
A74: 西北大区部 | B74: 宁夏办事处 | C74: 宁夏服务中心 | D74: 永宁县杨和镇鑫界家电配送维修中心 | E74: 合作 | F74: 贺亮 | G74: JS000016501 | H74: 46232.736 | I74: 1-EV26EJB | J74: FGDG20260727003983 | K74: 报装 | L74: 水槽洗碗机 | M74: 保内 | N74: 橱柜层板、侧板切割 | O74: 100 | P74: 0 | R74: 改装服务费 | S74: 225 | T74: 200 | U74: 0 | V74: 100 | W74: 电商/每誉补贴 | Y74: 0 | Z74: 0 | AB74: 已确认 | AC74: 46234.584 | AF74: 现金收费 | AG74: 已支付 | AH74: 46202 | AI74: 0 | AJ74: 9999 | AK74: 水槽洗碗机
A75: 西北大区部 | B75: 宁夏办事处 | C75: 宁夏服务中心 | D75: 永宁县杨和镇鑫界家电配送维修中心 | E75: 合作 | F75: 贺亮 | G75: JS000016501 | H75: 46232.736 | I75: 1-EV26EJB | J75: FGDG20260727003983 | K75: 报装 | L75: 水槽洗碗机 | M75: 保内 | N75: 台面开扩孔 | O75: 160 | P75: 0 | R75: 改装服务费 | S75: 225 | T75: 200 | U75: 0 | V75: 160 | W75: 电商/每誉补贴 | Y75: 0 | Z75: 0 | AB75: 已确认 | AC75: 46234.584 | AF75: 现金收费 | AG75: 已支付 | AH75: 46202 | AI75: 0 | AJ75: 9999 | AK75: 水槽洗碗机
A76: 西北大区部 | B76: 西宁办事处 | C76: 兰州服务中心 | D76: 西宁广仁技术服务有限公司 | E76: 合作 | F76: 张艳涛 | G76: JS000003413 | H76: 46232.801 | I76: 1-EV244LL | J76: FGDG20260728019628 | K76: 报装 | L76: 嵌入式洗碗机 | M76: 保内 | N76: 橱柜层板和隔板开孔 | O76: 30 | P76: 0 | R76: 其他服务费 | S76: 20 | T76: 20 | U76: 0 | V76: 30 | W76: 活动推广 | Y76: 0 | Z76: 0 | AF76: 现金收费 | AG76: 已支付 | AH76: 46230 | AI76: 0 | AJ76: 9999 | AK76: 嵌入式洗碗机
A77: 西北大区部 | B77: 西宁办事处 | C77: 兰州服务中心 | D77: 西宁广仁技术服务有限公司 | E77: 合作 | F77: 张艳涛 | G77: JS000003413 | H77: 46232.801 | I77: 1-EV244LL | J77: FGDG20260728019628 | K77: 报装 | L77: 嵌入式洗碗机 | M77: 保内 | N77: 【套餐】单独收费项二（封顶300元） | O77: 300 | P77: 0 | R77: 其他服务费 | S77: 20 | T77: 20 | U77: 0 | V77: 300 | W77: 活动推广 | Y77: 0 | Z77: 0 | AF77: 现金收费 | AG77: 已支付 | AH77: 46230 | AI77: 0 | AJ77: 9999 | AK77: 嵌入式洗碗机
A78: 西北大区部 | B78: 西宁办事处 | C78: 兰州服务中心 | D78: 西宁广仁技术服务有限公司 | E78: 合作 | F78: 张艳涛 | G78: JS000003413 | H78: 46232.801 | I78: 1-EV244LL | J78: FGDG20260728019628 | K78: 报装 | L78: 嵌入式洗碗机 | M78: 保内 | N78: 【套餐】单独收费项一（封顶300元） | O78: 300 | P78: 0 | R78: 其他服务费 | S78: 20 | T78: 20 | U78: 0 | V78: 300 | W78: 活动推广 | Y78: 0 | Z78: 0 | AF78: 现金收费 | AG78: 已支付 | AH78: 46230 | AI78: 0 | AJ78: 9999 | AK78: 嵌入式洗碗机
A79: 西北大区部 | B79: 新疆办事处 | C79: 乌鲁木齐服务中心 | D79: 乌鲁木齐经济技术开发区（头屯河区）明瑞商务服务工作室 | E79: 合作 | F79: 许东亚 | G79: JS000040323 | H79: 46231.542 | I79: 1-EU81P9I | J79: FGDG20260726012614 | K79: 报装 | L79: 吸油烟机 | M79: 保外 | N79: 客供防火阀、防烟宝、防雨罩安装费 | O79: 50 | P79: 0 | R79: 其他服务费 | S79: 120 | T79: 120 | U79: 0 | V79: 50 | W79: 活动推广 | Y79: 0 | Z79: 0 | AF79: 在线支付 | AG79: 已支付 | AI79: 0 | AJ79: 50 | AK79: JQ系列油烟机
A80: 西北大区部 | B80: 兰州办事处 | C80: 兰州服务中心 | D80: 天水晨旺家电服务有限公司 | E80: 合作 | F80: 蒋涛 | G80: JS000012246 | H80: 46231.481 | J80: FGDG20260725027099 | K80: 报装 | L80: 吸油烟机 | M80: 保外 | N80: 客供防火阀、防烟宝、防雨罩安装费 | O80: 50 | P80: 0 | R80: 其他服务费 | S80: 0 | T80: 0 | U80: 0 | V80: 50 | W80: 活动推广 | Y80: 0 | Z80: 0 | AG80: 未支付 | AI80: 0 | AJ80: 50 | AK80: 欧式油烟机
A81: 西北大区部 | B81: 新疆办事处 | C81: 乌鲁木齐服务中心 | D81: 伊宁边境经济合作区谢振升家电维修服务部 | E81: 合作 | F81: 吴亮 | G81: JS000014580 | H81: 46237.747 | I81: 1-EVWO1PY | J81: FGDG20260803012337 | K81: 报装 | L81: 热水器 | M81: 保内 | N81: 墙体开扩孔/公共烟道整改（切瓷砖） | O81: 120 | P81: 120 | R81: 改装服务费 | S81: 120 | T81: 120 | U81: 120 | V81: 0 | Y81: 0 | Z81: 0 | AD81: 已确认 | AE81: 46238.457 | AF81: 现金收费 | AG81: 已支付 | AH81: 46204 | AI81: 0 | AK81: 燃气热水器
A82: 西北大区部 | B82: 新疆办事处 | C82: 乌鲁木齐服务中心 | D82: 北屯市王金女家电维修店 | E82: 合作 | F82: 古永洪 | G82: JS000015956 | H82: 46241.46 | I82: 1-EX0UQ0Z | J82: FGDG20260806017580 | K82: 报修 | L82: 吸油烟机 | M82: 保内 | N82: 油烟机小保养 | O82: 198 | P82: 198 | Q82: 清洗保养 | R82: 标准服务费 | S82: 198 | T82: 198 | U82: 198 | V82: 0 | Y82: 75 | Z82: 75 | AB82: 已确认 | AC82: 46242.011 | AD82: 已确认 | AE82: 46242.008 | AF82: 现金收费 | AG82: 已支付 | AH82: 44476 | AI82: 0 | AK82: JQ系列油烟机
A83: 西北大区部 | B83: 新疆办事处 | C83: 乌鲁木齐服务中心 | D83: 北屯市王金女家电维修店 | E83: 合作 | F83: 古永洪 | G83: JS000015956 | H83: 46241.732 | I83: 1-EX0UQ0Z | J83: FGDG20260806028111 | K83: 报修 | L83: 吸油烟机 | M83: 保外 | N83: 油烟机小保养 | O83: 198 | P83: 198 | Q83: 清洗保养 | R83: 标准服务费 | S83: 198 | T83: 198 | U83: 198 | V83: 0 | Y83: 75 | Z83: 75 | AB83: 已确认 | AC83: 46242.011 | AD83: 已确认 | AE83: 46242.008 | AF83: 现金收费 | AG83: 已支付 | AH83: 40762 | AI83: 0 | AK83: 欧式油烟机
A84: 西北大区部 | B84: 新疆办事处 | C84: 乌鲁木齐服务中心 | D84: 北屯市王金女家电维修店 | E84: 合作 | F84: 古永洪 | G84: JS000015956 | H84: 46241.839 | I84: 1-EX0UQ0Z | J84: FGDG20260806025151 | K84: 报修 | L84: 吸油烟机 | M84: 保外 | N84: 油烟机小保养 | O84: 198 | P84: 198 | Q84: 清洗保养 | R84: 标准服务费 | S84: 198 | T84: 198 | U84: 198 | V84: 0 | Y84: 75 | Z84: 75 | AB84: 已确认 | AC84: 46242.011 | AD84: 已确认 | AE84: 46242.008 | AF84: 现金收费 | AG84: 已支付 | AH84: 40762 | AI84: 0 | AK84: 欧式油烟机
A85: 西北大区部 | B85: 新疆办事处 | C85: 乌鲁木齐服务中心 | D85: 阿克苏市零壹家电维修部 | E85: 合作 | F85: 姚双全 | G85: JS000039101 | H85: 46237.6 | I85: 1-EVWO1MW | J85: FGDG20260802022204 | K85: 报装 | L85: 吸油烟机 | M85: 保内 | N85: 客供防火阀、防烟宝、防雨罩安装费 | O85: 50 | P85: 50 | R85: 其他服务费 | S85: 50 | T85: 50 | U85: 50 | V85: 0 | Y85: 0 | Z85: 0 | AD85: 已确认 | AE85: 46238.458 | AF85: 现金收费 | AG85: 已支付 | AH85: 46236 | AI85: 0 | AK85: JQ系列油烟机
A86: 西北大区部 | B86: 新疆办事处 | C86: 乌鲁木齐服务中心 | D86: 北屯市王金女家电维修店 | E86: 合作 | F86: 车攀宁 | G86: JS000039122 | H86: 46238.676 | I86: 1-EW6RWOG | J86: FGDG20260803032536 | K86: 报装 | L86: 吸油烟机 | M86: 保内 | N86: 墙体开扩孔/公共烟道整改（切瓷砖） | O86: 120 | P86: 120 | R86: 改装服务费 | S86: 350 | T86: 350 | U86: 120 | V86: 0 | Y86: 0 | Z86: 0 | AB86: 已确认 | AC86: 46238.922 | AD86: 已确认 | AE86: 46238.697 | AF86: 现金收费 | AG86: 已支付 | AH86: 46223 | AI86: 0 | AK86: JQ系列油烟机
A87: 西北大区部 | B87: 新疆办事处 | C87: 乌鲁木齐服务中心 | D87: 伊宁边境经济合作区谢振升家电维修服务部 | E87: 合作 | F87: 吴亮 | G87: JS000014580 | H87: 46238.513 | I87: 1-EW6RWPP | J87: FGDG20260804010994 | K87: 报装 | L87: 吸油烟机 | M87: 保内 | N87: 墙体开扩孔/公共烟道整改（切瓷砖） | O87: 120 | P87: 120 | R87: 改装服务费 | S87: 300 | T87: 300 | U87: 120 | V87: 0 | Y87: 0 | Z87: 0 | AB87: 已确认 | AC87: 46239.725 | AD87: 已确认 | AE87: 46238.696 | AF87: 现金收费 | AG87: 已支付 | AH87: 46237 | AI87: 0 | AK87: 欧式油烟机
A88: 西北大区部 | B88: 新疆办事处 | C88: 乌鲁木齐服务中心 | D88: 昌吉市井清家电维修服务部 | E88: 合作 | F88: 袁鹏鹏 | G88: JS000047197 | H88: 46241.638 | I88: 1-EX0UQ20 | J88: FGDG20260807016389 | K88: 报装 | L88: 吸油烟机 | M88: 保内 | N88: 客供防火阀、防烟宝、防雨罩安装费 | O88: 50 | P88: 50 | R88: 其他服务费 | S88: 50 | T88: 50 | U88: 50 | V88: 0 | Y88: 0 | Z88: 0 | AD88: 已确认 | AE88: 46242.659 | AF88: 现金收费 | AG88: 已支付 | AH88: 46235 | AI88: 0 | AK88: JQ系列油烟机
A89: 西北大区部 | B89: 新疆办事处 | C89: 乌鲁木齐服务中心 | D89: 昌吉市井清家电维修服务部 | E89: 合作 | F89: 袁鹏鹏 | G89: JS000047197 | H89: 46241.786 | I89: 1-EX0UQ20 | J89: FGDG20260806027791 | K89: 报装 | L89: 吸油烟机 | M89: 保内 | N89: 墙体开扩孔/公共烟道整改（切瓷砖） | O89: 120 | P89: 120 | R89: 改装服务费 | S89: 300 | T89: 300 | U89: 120 | V89: 0 | Y89: 0 | Z89: 0 | AB89: 已确认 | AC89: 46242.677 | AD89: 已确认 | AE89: 46242.659 | AF89: 现金收费 | AG89: 已支付 | AH89: 46235 | AI89: 0 | AK89: JQ系列油烟机
A90: 西北大区部 | B90: 新疆办事处 | C90: 乌鲁木齐服务中心 | D90: 库尔勒泽玉家电维修服务中心（个体工商户） | E90: 合作 | F90: 王泽玉 | G90: JS000039743 | H90: 46236.463 | I90: 1-EVMJKK9 | J90: FGDG20260802006149 | K90: 报装 | L90: 吸油烟机 | M90: 保内 | N90: 客供防火阀、防烟宝、防雨罩安装费 | O90: 50 | P90: 50 | R90: 其他服务费 | S90: 50 | T90: 50 | U90: 50 | V90: 0 | Y90: 0 | Z90: 0 | AD90: 已确认 | AE90: 46238.457 | AF90: 现金收费 | AG90: 已支付 | AH90: 46234 | AI90: 0 | AK90: JQ系列油烟机
A91: 西北大区部 | B91: 新疆办事处 | C91: 乌鲁木齐服务中心 | D91: 库尔勒泽玉家电维修服务中心（个体工商户） | E91: 合作 | F91: 王泽玉 | G91: JS000039743 | H91: 46237.576 | I91: 1-EVWO1QI | J91: FGDG20260803014516 | K91: 报装 | L91: 吸油烟机 | M91: 保外 | N91: 客供防火阀、防烟宝、防雨罩安装费 | O91: 50 | P91: 50 | R91: 其他服务费 | S91: 50 | T91: 50 | U91: 50 | V91: 0 | Y91: 0 | Z91: 0 | AD91: 已确认 | AE91: 46238.457 | AF91: 现金收费 | AG91: 已支付 | AI91: 0 | AK91: JQ系列油烟机
A92: 西北大区部 | B92: 新疆办事处 | C92: 乌鲁木齐服务中心 | D92: 库尔勒泽玉家电维修服务中心（个体工商户） | E92: 合作 | F92: 王泽玉 | G92: JS000039743 | H92: 46235.86 | I92: 1-EVCGRHZ | J92: FGDG20260801024944 | K92: 报装 | L92: 吸油烟机 | M92: 保内 | N92: 免费拆旧机 | O92: 0 | P92: 0 | R92: 其他服务费 | S92: 180 | T92: 180 | U92: 0 | V92: 0 | Y92: 0 | Z92: 0 | AB92: 已确认 | AC92: 46236.472 | AD92: 已确认 | AE92: 46238.457 | AF92: 现金收费 | AG92: 已支付 | AH92: 46231 | AI92: 0 | AK92: JQ系列油烟机
A93: 西北大区部 | B93: 新疆办事处 | C93: 乌鲁木齐服务中心 | D93: 库尔勒泽玉家电维修服务中心（个体工商户） | E93: 合作 | F93: 王泽玉 | G93: JS000039743 | H93: 46237.696 | I93: 1-EVWO1QI | J93: FGDG20260803014537 | K93: 报装 | L93: 吸油烟机 | M93: 保内 | N93: 客供防火阀、防烟宝、防雨罩安装费 | O93: 50 | P93: 50 | R93: 其他服务费 | S93: 448 | T93: 448 | U93: 50 | V93: 0 | Y93: 0 | Z93: 0 | AB93: 已确认 | AC93: 46239.719 | AD93: 已确认 | AE93: 46238.457 | AF93: 现金收费 | AG93: 已支付 | AH93: 46173 | AI93: 0 | AK93: X系列油烟机
A94: 西北大区部 | B94: 新疆办事处 | C94: 乌鲁木齐服务中心 | D94: 乌鲁木齐市米东区宏誉家电维修服务部 | E94: 合作 | F94: 张宏 | G94: JS000004379 | H94: 46233.573 | J94: FGDG20260729016605 | K94: 报装 | L94: 吸油烟机 | M94: 保内 | N94: 橱柜层板、侧板切割 | O94: 100 | P94: 100 | R94: 改装服务费 | S94: 100 | T94: 100 | U94: 100 | V94: 0 | Y94: 0 | Z94: 0 | AD94: 已确认 | AE94: 46238.49 | AF94: 现金收费 | AG94: 已支付 | AH94: 46229 | AI94: 0 | AK94: JQ系列油烟机
A95: 西北大区部 | B95: 新疆办事处 | C95: 乌鲁木齐服务中心 | D95: 乌鲁木齐市米东区宏誉家电维修服务部 | E95: 合作 | F95: 张宏 | G95: JS000004379 | H95: 46237.544 | I95: 1-EVWO1QM | J95: FGDG20260802027916 | K95: 报修 | L95: 吸油烟机 | M95: 保外 | N95: 上门 | O95: 30 | P95: 30 | R95: 基础服务费 | S95: 30 | T95: 30 | U95: 30 | V95: 0 | Y95: 0 | Z95: 0 | AD95: 已确认 | AE95: 46238.49 | AF95: 现金收费 | AG95: 已支付 | AH95: 43009 | AI95: 0 | AK95: 欧式油烟机
A96: 西北大区部 | B96: 新疆办事处 | C96: 乌鲁木齐服务中心 | D96: 乌鲁木齐市米东区宏誉家电维修服务部 | E96: 合作 | F96: 张宏 | G96: JS000004379 | H96: 46232.726 | I96: 1-EV27AB8 | J96: FGDG20260725014481 | K96: 报装 | L96: 水槽洗碗机 | M96: 保内 | N96: 保修延长套餐（三年） | O96: 458 | P96: 458 | Q96: 延保服务 | R96: 增值产品费 | S96: 578 | T96: 578 | U96: 458 | V96: 0 | Y96: 343.5 | Z96: 343.5 | AB96: 已确认 | AC96: 46236.474 | AD96: 已确认 | AE96: 46238.49 | AF96: 现金收费 | AG96: 已支付 | AH96: 46228 | AI96: 0 | AK96: 水槽洗碗机
A97: 西北大区部 | B97: 新疆办事处 | C97: 乌鲁木齐服务中心 | D97: 乌鲁木齐经济技术开发区（头屯河区）明瑞商务服务工作室 | E97: 合作 | F97: 张朋 | G97: JS000045138 | H97: 46238.459 | I97: 1-EW6RWNL | J97: FGDG20260731021649 | K97: 报装 | L97: 吸油烟机 | M97: 保内 | N97: 客供防火阀、防烟宝、防雨罩安装费 | O97: 50 | P97: 50 | R97: 其他服务费 | S97: 100 | T97: 100 | U97: 50 | V97: 0 | Y97: 0 | Z97: 0 | AD97: 已确认 | AE97: 46238.696 | AF97: 现金收费 | AG97: 已支付 | AH97: 46234 | AI97: 0 | AK97: JQ系列油烟机
A98: 西北大区部 | B98: 新疆办事处 | C98: 乌鲁木齐服务中心 | D98: 乌鲁木齐经济技术开发区（头屯河区）明瑞商务服务工作室 | E98: 合作 | F98: 张朋 | G98: JS000045138 | H98: 46238.459 | I98: 1-EW6RWNL | J98: FGDG20260731021649 | K98: 报装 | L98: 吸油烟机 | M98: 保内 | N98: 公共烟道整改（不切瓷砖） | O98: 50 | P98: 50 | R98: 其他服务费 | S98: 100 | T98: 100 | U98: 50 | V98: 0 | Y98: 0 | Z98: 0 | AD98: 已确认 | AE98: 46238.696 | AF98: 现金收费 | AG98: 已支付 | AH98: 46234 | AI98: 0 | AK98: JQ系列油烟机
A99: 西北大区部 | B99: 新疆办事处 | C99: 乌鲁木齐服务中心 | D99: 水磨沟区华凌市场卓尚良思家用电器经销部 | E99: 合作 | F99: 张海涛 | G99: JS000013760 | H99: 46241.629 | I99: 1-EX0UPZU | J99: FGDG20260804015997 | K99: 报装 | L99: 嵌入式洗碗机 | M99: 保内 | N99: 橱柜层板和隔板开孔 | O99: 30 | P99: 30 | R99: 其他服务费 | S99: 200 | T99: 200 | U99: 30 | V99: 0 | Y99: 0 | Z99: 0 | AD99: 已确认 | AE99: 46242.573 | AF99: 现金收费 | AG99: 已支付 | AH99: 46240 | AI99: 0 | AK99: 嵌入式洗碗机
A100: 西北大区部 | B100: 新疆办事处 | C100: 乌鲁木齐服务中心 | D100: 石河子市有文电器修理部 | E100: 合作 | F100: 周有文 | G100: JS000010466 | H100: 46241.602 | I100: 1-EX0UPZE | J100: FGDG20260807013633 | K100: 报装 | L100: 吸油烟机 | M100: 保内 | N100: 客供防火阀、防烟宝、防雨罩安装费 | O100: 50 | P100: 50 | R100: 其他服务费 | S100: 170 | T100: 170 | U100: 50 | V100: 0 | Y100: 0 | Z100: 0 | AD100: 已确认 | AE100: 46242.672 | AF100: 现金收费 | AG100: 已支付 | AH100: 46238 | AI100: 0 | AK100: J1系列油烟机
A101: 西北大区部 | B101: 新疆办事处 | C101: 乌鲁木齐服务中心 | D101: 石河子市有文电器修理部 | E101: 合作 | F101: 周有文 | G101: JS000010466 | H101: 46241.602 | I101: 1-EX0UPZE | J101: FGDG20260807013633 | K101: 报装 | L101: 吸油烟机 | M101: 保内 | N101: 墙体开扩孔/公共烟道整改（切瓷砖） | O101: 120 | P101: 120 | R101: 改装服务费 | S101: 170 | T101: 170 | U101: 120 | V101: 0 | Y101: 0 | Z101: 0 | AD101: 已确认 | AE101: 46242.672 | AF101: 现金收费 | AG101: 已支付 | AH101: 46238 | AI101: 0 | AK101: J1系列油烟机
...

Sheet CSM配件
A2: 大区 | B2: 服务中心 | C2: 办事处 | D2: 服务网点 | E2: 网点类型 | F2: 服务工程师 | G2: 服务工程师编码 | H2: 工单编号 | I2: 工单类型 | J2: 产品线 | K2: 服务项目 | L2: 保内外 | M2: 配件名称 | N2: 配件编码 | O2: 配件分类 | P2: 配件用途 | Q2: 辅材分类 | R2: 销售分类 | S2: 数量 | T2: 单价 | U2: 工单实收费用 | V2: 工单应收费用 | W2: 配件实收费用 | X2: 折扣费用 | Y2: 折扣原因 | Z2: 其他折扣原因 | AA2: 上缴标准 | AB2: 上缴金额 | AC2: 事业商扣款 | AD2: 网点缴费单状态 | AE2: 网点缴费确认时间 | AF2: 技师缴费单状态 | AG2: 技师缴费单时间 | AH2: 收费方式 | AI2: 支付状态 | AJ2: 开票日期 | AK2: 录入完成时间
A3: 西北大区部 | B3: 呼和浩特服务中心 | C3: 呼和浩特办事处 | D3: 呼和浩特市凯多丰电器服务维修有限公司 | E3: 合作 | F3: 陈国强 | G3: JS000038671 | H3: FGDG20260804005258 | I3: 报修 | J3: 吸油烟机 | K3: 油烟机小保养 | L3: 保外 | M3: 新装清洗包FW-/-大连 | N3: 1508010400574 | O3: A | P3: 清洗 | Q3: 无 | S3: 1 | T3: 0 | U3: 198 | V3: 198 | W3: 0 | X3: 0 | AA3: 0 | AB3: 0 | AD3: 已确认 | AE3: 46238.777 | AH3: 现金收费 | AI3: 已支付 | AJ3: 41847 | AK3: 46238.757
A4: 西北大区部 | B4: 呼和浩特服务中心 | C4: 呼和浩特办事处 | D4: 呼和浩特市凯多丰电器服务维修有限公司 | E4: 合作 | F4: 陈国强 | G4: JS000038671 | H4: FGDG20260801013125 | I4: 报修 | J4: 吸油烟机 | K4: 油烟机小保养 | L4: 保内 | M4: 新装清洗包FW-/-大连 | N4: 1508010400574 | O4: A | P4: 清洗 | Q4: 无 | S4: 1 | T4: 0 | U4: 198 | V4: 198 | W4: 0 | X4: 0 | AA4: 0 | AB4: 0 | AD4: 已确认 | AE4: 46238.777 | AH4: 现金收费 | AI4: 已支付 | AJ4: 44136 | AK4: 46237.744
A5: 西北大区部 | B5: 呼和浩特服务中心 | C5: 呼和浩特办事处 | D5: 呼和浩特市凯多丰电器服务维修有限公司 | E5: 合作 | F5: 刘伟 | G5: JS000003431 | H5: FGDG20260801022861 | I5: 报修 | J5: 灶具 | K5: 维修 | L5: 保外 | M5: 双线圈电磁阀(点胶)(JZT-HL6B-12T)FW | N5: 110200160548R | O5: A | P5: 维修 | Q5: 无 | S5: 1 | T5: 40 | U5: 100 | V5: 130 | W5: 40 | X5: 0 | Y5: 客户端授权减免 | AA5: 28 | AB5: 28 | AD5: 已确认 | AE5: 46238.777 | AH5: 现金收费 | AI5: 已支付 | AJ5: 43050 | AK5: 46237.374
A6: 西北大区部 | B6: 呼和浩特服务中心 | C6: 呼和浩特办事处 | D6: 呼和浩特市凯多丰电器服务维修有限公司 | E6: 合作 | F6: 刘伟 | G6: JS000003431 | H6: FGDG20260802004575 | I6: 报修 | J6: 灶具 | K6: 维修 | L6: 保外 | M6: （老结构）维修热电偶(JZY-HA3G-20Y)FW | N6: 1102001903850 | O6: A | P6: 维修 | Q6: 无 | S6: 1 | T6: 20 | U6: 110 | V6: 110 | W6: 20 | X6: 0 | AA6: 14 | AB6: 14 | AD6: 已确认 | AE6: 46238.777 | AH6: 现金收费 | AI6: 已支付 | AJ6: 41426 | AK6: 46236.632
A7: 西北大区部 | B7: 呼和浩特服务中心 | C7: 呼和浩特办事处 | D7: 土默特左旗占平安装维修部 | E7: 合作 | F7: 杨占平 | G7: JS000008904 | H7: FGDG20260804026315 | I7: 其他 | J7: 吸油烟机 | K7: 工单补录 | L7: 保内 | M7: 出风罩连接圈_V1R1 | N7: 1101002600900 | O7: A | P7: 维修 | Q7: 无 | S7: 1 | T7: 10 | U7: 55 | V7: 55 | W7: 10 | X7: 0 | AA7: 7 | AB7: 7 | AD7: 已确认 | AE7: 46239.258 | AI7: 未支付 | AJ7: 46174 | AK7: 46238.732
A8: 西北大区部 | B8: 呼和浩特服务中心 | C8: 呼和浩特办事处 | D8: 土默特左旗占平安装维修部 | E8: 合作 | F8: 杨占平 | G8: JS000008904 | H8: FGDG20260804026315 | I8: 其他 | J8: 吸油烟机 | K8: 工单补录 | L8: 保内 | M8: 出风罩组件_白色_180_V1R1 | N8: 110100260088A | O8: A | P8: 维修 | Q8: 无 | S8: 1 | T8: 45 | U8: 55 | V8: 55 | W8: 45 | X8: 0 | AA8: 31.5 | AB8: 31.5 | AD8: 已确认 | AE8: 46239.258 | AI8: 未支付 | AJ8: 46174 | AK8: 46238.732
A9: 西北大区部 | B9: 呼和浩特服务中心 | C9: 呼和浩特办事处 | D9: 土默特左旗占平安装维修部 | E9: 合作 | F9: 赵拴钱 | G9: JS000039518 | H9: FGDG20260803017201 | I9: 报装 | J9: 吸油烟机 | K9: 安装 | L9: 保内 | M9: 挂钩组件(Z6T)FW | N9: 1101001508560 | O9: B | P9: 辅材 | Q9: 其他烟机 | R9: 其他产品线专用 | S9: 1 | T9: 50 | U9: 50 | V9: 50 | W9: 50 | X9: 0 | AA9: 35 | AB9: 35 | AD9: 已确认 | AE9: 46239.258 | AH9: 现金收费 | AI9: 已支付 | AJ9: 46237 | AK9: 46238.655
A10: 西北大区部 | B10: 呼和浩特服务中心 | C10: 呼和浩特办事处 | D10: 土默特左旗占平安装维修部 | E10: 合作 | F10: 张旺 | G10: JS000002134 | H10: FGDG20260804004293 | I10: 报装 | J10: 吸油烟机 | K10: 安装 | L10: 保内 | M10: 挂钩组件(Z6T)FW | N10: 1101001508560 | O10: B | P10: 辅材 | Q10: 其他烟机 | R10: 其他产品线专用 | S10: 1 | T10: 50 | U10: 50 | V10: 50 | W10: 50 | X10: 0 | AA10: 35 | AB10: 35 | AD10: 已确认 | AE10: 46239.258 | AH10: 现金收费 | AI10: 已支付 | AJ10: 46235 | AK10: 46238.649
A11: 西北大区部 | B11: 呼和浩特服务中心 | C11: 呼和浩特办事处 | D11: 土默特左旗占平安装维修部 | E11: 合作 | F11: 赵拴钱 | G11: JS000039518 | H11: FGDG20260803024386 | I11: 报装 | J11: 吸油烟机 | K11: 安装 | L11: 保内 | M11: 挂钩组件(Z6T)FW | N11: 1101001508560 | O11: B | P11: 辅材 | Q11: 其他烟机 | R11: 其他产品线专用 | S11: 1 | T11: 50 | U11: 50 | V11: 50 | W11: 50 | X11: 0 | AA11: 35 | AB11: 35 | AD11: 已确认 | AE11: 46239.258 | AH11: 现金收费 | AI11: 已支付 | AJ11: 46169 | AK11: 46238.612
A12: 西北大区部 | B12: 呼和浩特服务中心 | C12: 呼和浩特办事处 | D12: 土默特左旗占平安装维修部 | E12: 合作 | F12: 赵拴钱 | G12: JS000039518 | H12: FGDG20260803022641 | I12: 报装 | J12: 吸油烟机 | K12: 安装 | L12: 保内 | M12: 挂钩组件(Z6T)FW | N12: 1101001508560 | O12: B | P12: 辅材 | Q12: 其他烟机 | R12: 其他产品线专用 | S12: 1 | T12: 50 | U12: 50 | V12: 50 | W12: 50 | X12: 0 | AA12: 35 | AB12: 35 | AD12: 已确认 | AE12: 46239.258 | AH12: 现金收费 | AI12: 已支付 | AJ12: 46237 | AK12: 46238.41
A13: 西北大区部 | B13: 呼和浩特服务中心 | C13: 呼和浩特办事处 | D13: 土默特左旗占平安装维修部 | E13: 合作 | F13: 张旺 | G13: JS000002134 | H13: FGDG20260803007127 | I13: 报装 | J13: 嵌入式洗碗机 | K13: 安装 | L13: 保内 | M13: 泰和三角阀_水路(冷)FW | N13: 1507030100502 | O13: B | P13: 辅材 | Q13: 其他热水器 | R13: 其他水路辅材 | S13: 1 | T13: 60 | U13: 60 | V13: 60 | W13: 60 | X13: 0 | AA13: 42 | AB13: 42 | AD13: 已确认 | AE13: 46239.258 | AH13: 现金收费 | AI13: 已支付 | AJ13: 46235 | AK13: 46237.813
A14: 西北大区部 | B14: 呼和浩特服务中心 | C14: 呼和浩特办事处 | D14: 土默特左旗占平安装维修部 | E14: 合作 | F14: 赵拴钱 | G14: JS000039518 | H14: FGDG20260801020185 | I14: 报装 | J14: 吸油烟机 | K14: 安装 | L14: 保内 | M14: 挂钩组件(Z6T)FW | N14: 1101001508560 | O14: B | P14: 辅材 | Q14: 其他烟机 | R14: 其他产品线专用 | S14: 1 | T14: 50 | U14: 50 | V14: 50 | W14: 50 | X14: 0 | AA14: 35 | AB14: 35 | AD14: 已确认 | AE14: 46239.258 | AH14: 现金收费 | AI14: 已支付 | AJ14: 46169 | AK14: 46237.492
A15: 西北大区部 | B15: 呼和浩特服务中心 | C15: 呼和浩特办事处 | D15: 土默特左旗占平安装维修部 | E15: 合作 | F15: 妥晓勇 | G15: JS000034706 | H15: FGDG20260802017720 | I15: 报装 | J15: 吸油烟机 | K15: 安装 | L15: 保内 | M15: 挂钩组件(Z6T)FW | N15: 1101001508560 | O15: B | P15: 辅材 | Q15: 其他烟机 | R15: 其他产品线专用 | S15: 1 | T15: 50 | U15: 50 | V15: 50 | W15: 50 | X15: 0 | AA15: 35 | AB15: 35 | AD15: 已确认 | AE15: 46239.258 | AI15: 未支付 | AJ15: 46236 | AK15: 46237.45
A16: 西北大区部 | B16: 呼和浩特服务中心 | C16: 呼和浩特办事处 | D16: 土默特左旗占平安装维修部 | E16: 合作 | F16: 刘有义 | G16: JS000026919 | H16: FGDG20260801021480 | I16: 报修 | J16: 吸油烟机 | K16: 维修 | L16: 保外 | M16: 电源板组件(CXW-189-JX05(不带罩)) | N16: 110100030276C | O16: A | P16: 维修 | Q16: 无 | S16: 1 | T16: 170 | U16: 170 | V16: 170 | W16: 170 | X16: 0 | AA16: 119 | AB16: 119 | AD16: 已确认 | AE16: 46239.258 | AH16: 现金收费 | AI16: 已支付 | AJ16: 40879 | AK16: 46236.853
A17: 西北大区部 | B17: 呼和浩特服务中心 | C17: 呼和浩特办事处 | D17: 土默特左旗占平安装维修部 | E17: 合作 | F17: 张旺 | G17: JS000002134 | H17: FGDG20260801004256 | I17: 报修 | J17: 吸油烟机 | K17: 维修 | L17: 保外 | M17: 电源板组件(CXW-200-EH29T) | N17: 110100081259E | O17: A | P17: 维修 | Q17: 无 | S17: 1 | T17: 130 | U17: 210 | V17: 210 | W17: 130 | X17: 0 | AA17: 91 | AB17: 91 | AD17: 已确认 | AE17: 46239.258 | AH17: 现金收费 | AI17: 已支付 | AJ17: 42584 | AK17: 46236.724
A18: 西北大区部 | B18: 呼和浩特服务中心 | C18: 呼和浩特办事处 | D18: 内蒙古洁莱电器安装服务有限公司 | E18: 合作 | F18: 雷锁锁 | G18: JS000020273 | H18: FGDG20260804018404 | I18: 报装 | J18: 吸油烟机 | K18: 改装 | L18: 保内 | M18: 排油烟气防火止回阀组件_S3-B | N18: 112500010076B | O18: B | P18: 辅材 | Q18: 防烟宝 | R18: 止回阀 | S18: 1 | T18: 180 | U18: 280 | V18: 280 | W18: 180 | X18: 0 | AA18: 100 | AB18: 100 | AD18: 已确认 | AE18: 46238.778 | AH18: 现金收费 | AI18: 已支付 | AJ18: 46234 | AK18: 46238.711
A19: 西北大区部 | B19: 呼和浩特服务中心 | C19: 呼和浩特办事处 | D19: 内蒙古洁莱电器安装服务有限公司 | E19: 合作 | F19: 雷锁锁 | G19: JS000020273 | H19: FGDG20260804010367 | I19: 报装 | J19: 灶具 | K19: 调试 | L19: 保内 | M19: 气管接头组件(JZT-HD1G-12T)FW | N19: 1102001701120 | O19: A | P19: 维修 | Q19: 无 | S19: 1 | T19: 20 | U19: 20 | V19: 20 | W19: 20 | X19: 0 | AA19: 14 | AB19: 14 | AD19: 已确认 | AE19: 46238.778 | AH19: 现金收费 | AI19: 已支付 | AJ19: 46237 | AK19: 46238.53
A20: 西北大区部 | B20: 呼和浩特服务中心 | C20: 呼和浩特办事处 | D20: 内蒙古洁莱电器安装服务有限公司 | E20: 合作 | F20: 赵云飞 | G20: JS000025678 | H20: FGDG20260803008788 | I20: 报装 | J20: 吸油烟机 | K20: 安装 | L20: 保内 | M20: 挂钩组件(Z6T)FW | N20: 1101001508560 | O20: B | P20: 辅材 | Q20: 其他烟机 | R20: 其他产品线专用 | S20: 1 | T20: 50 | U20: 50 | V20: 50 | W20: 50 | X20: 0 | AA20: 35 | AB20: 35 | AD20: 已确认 | AE20: 46238.778 | AH20: 现金收费 | AI20: 已支付 | AJ20: 46168 | AK20: 46238.472
A21: 西北大区部 | B21: 呼和浩特服务中心 | C21: 呼和浩特办事处 | D21: 内蒙古洁莱电器安装服务有限公司 | E21: 合作 | F21: 侯小乐 | G21: JS000025735 | H21: FGDG20260803030986 | I21: 报装 | J21: 嵌入式洗碗机 | K21: 安装 | L21: 保内 | M21: 下水三通-PP-T20-灰-FW | N21: 1507020101309 | O21: B | P21: 辅材 | Q21: 其他热水器 | R21: 其他产品线专用 | S21: 1 | T21: 10 | U21: 320 | V21: 320 | W21: 10 | X21: 0 | AA21: 7 | AB21: 7 | AD21: 已确认 | AE21: 46238.778 | AI21: 未支付 | AJ21: 46143 | AK21: 46238.42
A22: 西北大区部 | B22: 呼和浩特服务中心 | C22: 呼和浩特办事处 | D22: 内蒙古洁莱电器安装服务有限公司 | E22: 合作 | F22: 侯小乐 | G22: JS000025735 | H22: FGDG20260803030986 | I22: 报装 | J22: 嵌入式洗碗机 | K22: 安装 | L22: 保内 | M22: 外排水管-PP+TPE-内径Φ21.4长1.85m-/FW | N22: 1507020101230 | O22: B | P22: 辅材 | Q22: 其他热水器 | R22: 其他产品线专用 | S22: 1 | T22: 25 | U22: 320 | V22: 320 | W22: 25 | X22: 0 | AA22: 17.5 | AB22: 17.5 | AD22: 已确认 | AE22: 46238.778 | AI22: 未支付 | AJ22: 46143 | AK22: 46238.42
A23: 西北大区部 | B23: 呼和浩特服务中心 | C23: 呼和浩特办事处 | D23: 内蒙古洁莱电器安装服务有限公司 | E23: 合作 | F23: 侯小乐 | G23: JS000025735 | H23: FGDG20260803030986 | I23: 报装 | J23: 嵌入式洗碗机 | K23: 安装 | L23: 保内 | M23: 排水管延长接头-PP-T20(100个/箱)-/FW | N23: 1507020101310 | O23: B | P23: 辅材 | Q23: 其他热水器 | R23: 其他产品线专用 | S23: 1 | T23: 5 | U23: 320 | V23: 320 | W23: 5 | X23: 0 | AA23: 3.5 | AB23: 3.5 | AD23: 已确认 | AE23: 46238.778 | AI23: 未支付 | AJ23: 46143 | AK23: 46238.42
A24: 西北大区部 | B24: 呼和浩特服务中心 | C24: 呼和浩特办事处 | D24: 内蒙古洁莱电器安装服务有限公司 | E24: 合作 | F24: 雷锁锁 | G24: JS000020273 | H24: FGDG20260802022536 | I24: 报装 | J24: 水槽洗碗机 | K24: 安装 | L24: 保内 | M24: 泰和三角阀_水路(冷)FW | N24: 1507030100502 | O24: B | P24: 辅材 | Q24: 其他热水器 | R24: 其他水路辅材 | S24: 1 | T24: 60 | U24: 160 | V24: 160 | W24: 60 | X24: 0 | AA24: 42 | AB24: 42 | AD24: 已确认 | AE24: 46238.778 | AH24: 现金收费 | AI24: 已支付 | AJ24: 46235 | AK24: 46237.734
A25: 西北大区部 | B25: 呼和浩特服务中心 | C25: 呼和浩特办事处 | D25: 内蒙古洁莱电器安装服务有限公司 | E25: 合作 | F25: 雷锁锁 | G25: JS000020273 | H25: FGDG20260802022536 | I25: 报装 | J25: 水槽洗碗机 | K25: 安装 | L25: 保内 | M25: 泰和三角阀_水路(热)(JSQ19-1101) | N25: 1507030100013 | O25: B | P25: 辅材 | Q25: 其他热水器 | R25: 其他水路辅材 | S25: 1 | T25: 60 | U25: 160 | V25: 160 | W25: 60 | X25: 0 | AA25: 42 | AB25: 42 | AD25: 已确认 | AE25: 46238.778 | AH25: 现金收费 | AI25: 已支付 | AJ25: 46235 | AK25: 46237.734
A26: 西北大区部 | B26: 呼和浩特服务中心 | C26: 呼和浩特办事处 | D26: 内蒙古洁莱电器安装服务有限公司 | E26: 合作 | F26: 雷锁锁 | G26: JS000020273 | H26: FGDG20260802022536 | I26: 报装 | J26: 水槽洗碗机 | K26: 安装 | L26: 保内 | M26: 水龙头三通(JBSD2T-Q1) | N26: 110800010013A | O26: B | P26: 辅材 | Q26: 其他热水器 | R26: 其他水路辅材 | S26: 1 | T26: 40 | U26: 160 | V26: 160 | W26: 40 | X26: 0 | AA26: 28 | AB26: 28 | AD26: 已确认 | AE26: 46238.778 | AH26: 现金收费 | AI26: 已支付 | AJ26: 46235 | AK26: 46237.734
A27: 西北大区部 | B27: 呼和浩特服务中心 | C27: 呼和浩特办事处 | D27: 内蒙古洁莱电器安装服务有限公司 | E27: 合作 | F27: 侯小乐 | G27: JS000025735 | H27: FGDG20260802005513 | I27: 报装 | J27: 吸油烟机 | K27: 安装 | L27: 保内 | M27: 挂钩组件(Z6T)FW | N27: 1101001508560 | O27: B | P27: 辅材 | Q27: 其他烟机 | R27: 其他产品线专用 | S27: 1 | T27: 50 | U27: 50 | V27: 50 | W27: 50 | X27: 0 | AA27: 35 | AB27: 35 | AD27: 已确认 | AE27: 46238.778 | AI27: 未支付 | AJ27: 46023 | AK27: 46237.543
A28: 西北大区部 | B28: 呼和浩特服务中心 | C28: 呼和浩特办事处 | D28: 内蒙古洁莱电器安装服务有限公司 | E28: 合作 | F28: 侯小乐 | G28: JS000025735 | H28: FGDG20260801028402 | I28: 报装 | J28: 吸油烟机 | K28: 改装 | L28: 保内 | M28: 排油烟气防火止回阀组件_S3 | N28: 1125000100640 | O28: B | P28: 辅材 | Q28: 防烟宝 | R28: 止回阀 | S28: 1 | T28: 180 | U28: 350 | V28: 350 | W28: 180 | X28: 0 | Y28: 重要/特殊客户 | AA28: 100 | AB28: 100 | AD28: 已确认 | AE28: 46238.778 | AI28: 未支付 | AJ28: 46023 | AK28: 46237.501
A29: 西北大区部 | B29: 呼和浩特服务中心 | C29: 呼和浩特办事处 | D29: 内蒙古洁莱电器安装服务有限公司 | E29: 合作 | F29: 侯小乐 | G29: JS000025735 | H29: FGDG20260802015889 | I29: 报装 | J29: 吸油烟机 | K29: 安装 | L29: 保内 | M29: 排油烟气防火止回阀组件_S3-B | N29: 112500010076B | O29: B | P29: 辅材 | Q29: 防烟宝 | R29: 止回阀 | S29: 1 | T29: 180 | U29: 180 | V29: 180 | W29: 180 | X29: 0 | AA29: 100 | AB29: 100 | AD29: 已确认 | AE29: 46238.778 | AI29: 未支付 | AJ29: 46023 | AK29: 46237.424
A30: 西北大区部 | B30: 呼和浩特服务中心 | C30: 呼和浩特办事处 | D30: 内蒙古洁莱电器安装服务有限公司 | E30: 合作 | F30: 雷锁锁 | G30: JS000020273 | H30: FGDG20260802024136 | I30: 报装 | J30: 智慧水槽 | K30: 改装 | L30: 保内 | M30: 泰和三角阀_水路(热)(JSQ19-1101) | N30: 1507030100013 | O30: B | P30: 辅材 | Q30: 其他热水器 | R30: 其他水路辅材 | S30: 1 | T30: 60 | U30: 100 | V30: 100 | W30: 60 | X30: 0 | Y30: 其他 | Z30: 其他 | AA30: 42 | AB30: 42 | AD30: 已确认 | AE30: 46238.778 | AH30: 现金收费 | AI30: 已支付 | AJ30: 46228 | AK30: 46236.772
A31: 西北大区部 | B31: 呼和浩特服务中心 | C31: 呼和浩特办事处 | D31: 内蒙古洁莱电器安装服务有限公司 | E31: 合作 | F31: 雷锁锁 | G31: JS000020273 | H31: FGDG20260802024136 | I31: 报装 | J31: 智慧水槽 | K31: 改装 | L31: 保内 | M31: 水龙头三通(JBSD2T-Q1) | N31: 110800010013A | O31: B | P31: 辅材 | Q31: 其他热水器 | R31: 其他水路辅材 | S31: 1 | T31: 40 | U31: 100 | V31: 100 | W31: 40 | X31: 0 | Y31: 其他 | Z31: 其他 | AA31: 28 | AB31: 28 | AD31: 已确认 | AE31: 46238.778 | AH31: 现金收费 | AI31: 已支付 | AJ31: 46228 | AK31: 46236.772
A32: 西北大区部 | B32: 呼和浩特服务中心 | C32: 呼和浩特办事处 | D32: 内蒙古洁莱电器安装服务有限公司 | E32: 合作 | F32: 雷锁锁 | G32: JS000020273 | H32: FGDG20260802018507 | I32: 报装 | J32: 水槽洗碗机 | K32: 安装 | L32: 保内 | M32: LF对丝-铜-4-G1/2-R1/2-LF | N32: 1507020200800 | O32: B | P32: 辅材 | Q32: 其他灶具 | R32: 其他水路辅材 | S32: 1 | T32: 20 | U32: 80 | V32: 80 | W32: 20 | X32: 0 | AA32: 14 | AB32: 14 | AD32: 已确认 | AE32: 46238.778 | AH32: 现金收费 | AI32: 已支付 | AJ32: 46210 | AK32: 46236.632
A33: 西北大区部 | B33: 呼和浩特服务中心 | C33: 呼和浩特办事处 | D33: 内蒙古洁莱电器安装服务有限公司 | E33: 合作 | F33: 雷锁锁 | G33: JS000020273 | H33: FGDG20260802018507 | I33: 报装 | J33: 水槽洗碗机 | K33: 安装 | L33: 保内 | M33: LF对丝-铜-4-G1/2-R1/2-LF | N33: 1507020200800 | O33: B | P33: 辅材 | Q33: 其他灶具 | R33: 其他水路辅材 | S33: 1 | T33: 20 | U33: 80 | V33: 80 | W33: 20 | X33: 0 | AA33: 14 | AB33: 14 | AD33: 已确认 | AE33: 46238.778 | AH33: 现金收费 | AI33: 已支付 | AJ33: 46210 | AK33: 46236.632
A34: 西北大区部 | B34: 呼和浩特服务中心 | C34: 呼和浩特办事处 | D34: 内蒙古洁莱电器安装服务有限公司 | E34: 合作 | F34: 雷锁锁 | G34: JS000020273 | H34: FGDG20260802018507 | I34: 报装 | J34: 水槽洗碗机 | K34: 安装 | L34: 保内 | M34: 水龙头三通(JBSD2T-Q1) | N34: 110800010013A | O34: B | P34: 辅材 | Q34: 其他热水器 | R34: 其他水路辅材 | S34: 1 | T34: 40 | U34: 80 | V34: 80 | W34: 40 | X34: 0 | AA34: 28 | AB34: 28 | AD34: 已确认 | AE34: 46238.778 | AH34: 现金收费 | AI34: 已支付 | AJ34: 46210 | AK34: 46236.632
A35: 西北大区部 | B35: 呼和浩特服务中心 | C35: 呼和浩特办事处 | D35: 内蒙古洁莱电器安装服务有限公司 | E35: 合作 | F35: 赵云飞 | G35: JS000025678 | H35: FGDG20260802003296 | I35: 报修 | J35: 水槽洗碗机 | K35: 维修 | L35: 保外 | M35: 加热盘密封圈(JBSD2T-Q1) | N35: 1108000102230 | O35: A | P35: 维修 | Q35: 无 | S35: 1 | T35: 15 | U35: 180 | V35: 180 | W35: 15 | X35: 0 | AA35: 10.5 | AB35: 10.5 | AD35: 已确认 | AE35: 46238.778 | AH35: 现金收费 | AI35: 已支付 | AJ35: 43800 | AK35: 46236.395
A36: 西北大区部 | B36: 呼和浩特服务中心 | C36: 呼和浩特办事处 | D36: 内蒙古洁莱电器安装服务有限公司 | E36: 合作 | F36: 赵云飞 | G36: JS000025678 | H36: FGDG20260802003296 | I36: 报修 | J36: 水槽洗碗机 | K36: 维修 | L36: 保外 | M36: 加热盘组件(JBSD2T-Q3) | N36: 110800020181C | O36: A | P36: 维修 | Q36: 无 | S36: 1 | T36: 75 | U36: 180 | V36: 180 | W36: 75 | X36: 0 | AA36: 52.5 | AB36: 52.5 | AD36: 已确认 | AE36: 46238.778 | AH36: 现金收费 | AI36: 已支付 | AJ36: 43800 | AK36: 46236.395
A37: 西北大区部 | B37: 呼和浩特服务中心 | C37: 呼和浩特办事处 | D37: 内蒙古萱圆居民日常生活服务有限公司 | E37: 合作 | F37: 李超 | G37: JS000041943 | H37: FGDG20260802021984 | I37: 报修 | J37: 吸油烟机 | K37: 油烟机小保养 | L37: 保外 | M37: 新装清洗包FW-/-象山 | N37: 1508010400577 | O37: A | P37: 清洗 | Q37: 无 | S37: 1 | T37: 0 | U37: 198 | V37: 198 | W37: 0 | X37: 0 | AA37: 0 | AB37: 0 | AD37: 已确认 | AE37: 46238.779 | AH37: 现金收费 | AI37: 已支付 | AJ37: 43315 | AK37: 46237.484
A38: 西北大区部 | B38: 呼和浩特服务中心 | C38: 呼和浩特办事处 | D38: 内蒙古萱圆居民日常生活服务有限公司 | E38: 合作 | F38: 李永强 | G38: JS000042742 | H38: FGDG20260801008657 | I38: 报装 | J38: 吸油烟机 | K38: 安装 | L38: 保内 | M38: 排油烟气防火止回阀组件_S3-B | N38: 112500010076B | O38: B | P38: 辅材 | Q38: 防烟宝 | R38: 止回阀 | S38: 1 | T38: 180 | U38: 180 | V38: 180 | W38: 180 | X38: 0 | AA38: 100 | AB38: 100 | AD38: 已确认 | AE38: 46238.779 | AH38: 现金收费 | AI38: 已支付 | AJ38: 46235 | AK38: 46236.792
A39: 西北大区部 | B39: 呼和浩特服务中心 | C39: 呼和浩特办事处 | D39: 内蒙古萱圆居民日常生活服务有限公司 | E39: 合作 | F39: 李超 | G39: JS000041943 | H39: FGDG20260802001586 | I39: 报修 | J39: 吸油烟机 | K39: 油烟机小保养 | L39: 保外 | M39: 新装清洗包FW-/-象山 | N39: 1508010400577 | O39: A | P39: 清洗 | Q39: 无 | S39: 1 | T39: 0 | U39: 198 | V39: 198 | W39: 0 | X39: 0 | AA39: 0 | AB39: 0 | AD39: 已确认 | AE39: 46238.779 | AH39: 现金收费 | AI39: 已支付 | AJ39: 43314 | AK39: 46236.439
A40: 西北大区部 | B40: 呼和浩特服务中心 | C40: 呼和浩特办事处 | D40: 土默特左旗金誉良电气安装服务部 | E40: 合作 | F40: 张加良 | G40: JS000024561 | H40: FGDG20260804025768 | I40: 其他 | J40: 微波炉 | K40: 样机维修 | L40: 保外 | M40: 玻璃接油盘(W25800P-C2A) | N40: 1106000301110 | O40: A | P40: 维修 | Q40: 无 | S40: 1 | T40: 50 | U40: 50 | V40: 50 | W40: 50 | X40: 0 | AA40: 35 | AB40: 35 | AD40: 已确认 | AE40: 46238.78 | AH40: 现金收费 | AI40: 已支付 | AJ40: 42008 | AK40: 46238.766
A41: 西北大区部 | B41: 呼和浩特服务中心 | C41: 呼和浩特办事处 | D41: 土默特左旗金誉良电气安装服务部 | E41: 合作 | F41: 张加良 | G41: JS000024561 | H41: FGDG20260804025767 | I41: 其他 | J41: 吸油烟机 | K41: 样机维修 | L41: 保外 | M41: 灯连接线(CXW-200-EM01T) | N41: 1101000901760 | O41: A | P41: 维修 | Q41: 无 | S41: 1 | T41: 15 | U41: 85 | V41: 85 | W41: 15 | X41: 0 | AA41: 10.5 | AB41: 10.5 | AD41: 已确认 | AE41: 46238.78 | AH41: 现金收费 | AI41: 已支付 | AJ41: 41855 | AK41: 46238.765
A42: 西北大区部 | B42: 呼和浩特服务中心 | C42: 呼和浩特办事处 | D42: 土默特左旗金誉良电气安装服务部 | E42: 合作 | F42: 张加良 | G42: JS000024561 | H42: FGDG20260804025767 | I42: 其他 | J42: 吸油烟机 | K42: 样机维修 | L42: 保外 | M42: 电容器(CXW-152-Q2XL) | N42: 110100010132C | O42: A | P42: 维修 | Q42: 无 | S42: 1 | T42: 20 | U42: 85 | V42: 85 | W42: 20 | X42: 0 | AA42: 14 | AB42: 14 | AD42: 已确认 | AE42: 46238.78 | AH42: 现金收费 | AI42: 已支付 | AJ42: 41855 | AK42: 46238.765
A43: 西北大区部 | B43: 呼和浩特服务中心 | C43: 呼和浩特办事处 | D43: 土默特左旗金誉良电气安装服务部 | E43: 合作 | F43: 张加良 | G43: JS000024561 | H43: FGDG20260804025767 | I43: 其他 | J43: 吸油烟机 | K43: 样机维修 | L43: 保外 | M43: 左侧板_03-Z7T | N43: 1101001516820 | O43: A | P43: 维修 | Q43: 无 | S43: 1 | T43: 50 | U43: 85 | V43: 85 | W43: 50 | X43: 0 | AA43: 35 | AB43: 35 | AD43: 已确认 | AE43: 46238.78 | AH43: 现金收费 | AI43: 已支付 | AJ43: 41855 | AK43: 46238.765
A44: 西北大区部 | B44: 呼和浩特服务中心 | C44: 呼和浩特办事处 | D44: 土默特左旗金誉良电气安装服务部 | E44: 合作 | F44: 张磊 | G44: JS000026353 | H44: FGDG20260731027848 | I44: 报修 | J44: 吸油烟机 | K44: 维修 | L44: 保外 | M44: 集烟罩组件(CXW-200-EM10T)FW | N44: 1101000906010 | O44: A | P44: 维修 | Q44: 无 | S44: 1 | T44: 695 | U44: 785 | V44: 785 | W44: 695 | X44: 0 | AA44: 486.5 | AB44: 486.5 | AD44: 已确认 | AE44: 46238.78 | AH44: 现金收费 | AI44: 已支付 | AJ44: 42979 | AK44: 46238.507
A45: 西北大区部 | B45: 呼和浩特服务中心 | C45: 呼和浩特办事处 | D45: 土默特左旗金誉良电气安装服务部 | E45: 合作 | F45: 刘晓丰 | G45: JS000029708 | H45: FGDG20260802017763 | I45: 报装 | J45: 吸油烟机 | K45: 安装 | L45: 保内 | M45: 挂钩组件(Z6T)FW | N45: 1101001508560 | O45: B | P45: 辅材 | Q45: 其他烟机 | R45: 其他产品线专用 | S45: 1 | T45: 50 | U45: 50 | V45: 50 | W45: 50 | X45: 0 | AA45: 35 | AB45: 35 | AD45: 已确认 | AE45: 46238.78 | AH45: 现金收费 | AI45: 已支付 | AJ45: 46168 | AK45: 46237.711
A46: 西北大区部 | B46: 呼和浩特服务中心 | C46: 呼和浩特办事处 | D46: 土默特左旗金誉良电气安装服务部 | E46: 合作 | F46: 刘晓丰 | G46: JS000029708 | H46: FGDG20260803022447 | I46: 报修 | J46: 水槽洗碗机 | K46: 维修 | L46: 保外 | M46: 手动门锁_JPSD2T-C3A | N46: 1108000507120 | O46: A | P46: 维修 | Q46: 无 | S46: 1 | T46: 80 | U46: 170 | V46: 170 | W46: 80 | X46: 0 | AA46: 56 | AB46: 56 | AD46: 已确认 | AE46: 46238.78 | AH46: 现金收费 | AI46: 已支付 | AJ46: 44258 | AK46: 46237.672
A47: 西北大区部 | B47: 呼和浩特服务中心 | C47: 呼和浩特办事处 | D47: 土默特左旗金誉良电气安装服务部 | E47: 合作 | F47: 张加良 | G47: JS000024561 | H47: FGDG20260801028872 | I47: 报装 | J47: 吸油烟机 | K47: 安装 | L47: 保内 | M47: 挂钩组件(Z6T)FW | N47: 1101001508560 | O47: B | P47: 辅材 | Q47: 其他烟机 | R47: 其他产品线专用 | S47: 1 | T47: 50 | U47: 50 | V47: 50 | W47: 50 | X47: 0 | AA47: 35 | AB47: 35 | AD47: 已确认 | AE47: 46238.78 | AH47: 现金收费 | AI47: 已支付 | AJ47: 46235 | AK47: 46237.654
A48: 西北大区部 | B48: 呼和浩特服务中心 | C48: 呼和浩特办事处 | D48: 土默特左旗金誉良电气安装服务部 | E48: 合作 | F48: 张磊 | G48: JS000026353 | H48: FGDG20260802009918 | I48: 报装 | J48: 吸油烟机 | K48: 安装 | L48: 保内 | M48: 挂钩组件(Z6T)FW | N48: 1101001508560 | O48: B | P48: 辅材 | Q48: 其他烟机 | R48: 其他产品线专用 | S48: 1 | T48: 50 | U48: 50 | V48: 50 | W48: 50 | X48: 0 | AA48: 35 | AB48: 35 | AD48: 已确认 | AE48: 46238.78 | AH48: 现金收费 | AI48: 已支付 | AJ48: 46236 | AK48: 46237.468
A49: 西北大区部 | B49: 呼和浩特服务中心 | C49: 呼和浩特办事处 | D49: 土默特左旗金誉良电气安装服务部 | E49: 合作 | F49: 张加良 | G49: JS000024561 | H49: FGDG20260731020201 | I49: 报装 | J49: 吸油烟机 | K49: 安装 | L49: 保内 | M49: 装饰罩组件_JR01T-G | N49: 1101002404280 | O49: B | P49: 辅材 | Q49: 装饰罩 | R49: 装饰罩 | S49: 1 | T49: 280 | U49: 560 | V49: 560 | W49: 280 | X49: 0 | AA49: 196 | AB49: 196 | AD49: 已确认 | AE49: 46238.78 | AH49: 现金收费 | AI49: 已支付 | AJ49: 46235 | AK49: 46237.417
A50: 西北大区部 | B50: 呼和浩特服务中心 | C50: 呼和浩特办事处 | D50: 土默特左旗金誉良电气安装服务部 | E50: 合作 | F50: 张加良 | G50: JS000024561 | H50: FGDG20260731020201 | I50: 报装 | J50: 吸油烟机 | K50: 安装 | L50: 保内 | M50: 装饰罩组件_JR01T-G | N50: 1101002404280 | O50: B | P50: 辅材 | Q50: 装饰罩 | R50: 装饰罩 | S50: 1 | T50: 280 | U50: 560 | V50: 560 | W50: 280 | X50: 0 | AA50: 196 | AB50: 196 | AD50: 已确认 | AE50: 46238.78 | AH50: 现金收费 | AI50: 已支付 | AJ50: 46235 | AK50: 46237.417
A51: 西北大区部 | B51: 呼和浩特服务中心 | C51: 呼和浩特办事处 | D51: 土默特左旗金誉良电气安装服务部 | E51: 合作 | F51: 刘晓丰 | G51: JS000029708 | H51: FGDG20260801007550 | I51: 报装 | J51: 吸油烟机 | K51: 安装 | L51: 保内 | M51: 排油烟气防火止回阀组件_S3-A | N51: 112500010069C | O51: B | P51: 辅材 | Q51: 防烟宝 | R51: 止回阀 | S51: 1 | T51: 180 | U51: 180 | V51: 180 | W51: 180 | X51: 0 | AA51: 100 | AB51: 100 | AD51: 已确认 | AE51: 46238.78 | AH51: 现金收费 | AI51: 已支付 | AJ51: 46235 | AK51: 46236.486
A52: 西北大区部 | B52: 呼和浩特服务中心 | C52: 呼和浩特办事处 | D52: 土默特左旗金誉良电气安装服务部 | E52: 合作 | F52: 张磊 | G52: JS000026353 | H52: FGDG20260801025060 | I52: 报装 | J52: 灶具 | K52: 调试 | L52: 保内 | M52: 气管接头组件(JZT-HD1G-12T)FW | N52: 1102001701120 | O52: A | P52: 维修 | Q52: 无 | S52: 1 | T52: 20 | U52: 110 | V52: 110 | W52: 20 | X52: 0 | AA52: 14 | AB52: 14 | AD52: 已确认 | AE52: 46238.78 | AH52: 现金收费 | AI52: 已支付 | AJ52: 46235 | AK52: 46236.45
A53: 西北大区部 | B53: 呼和浩特服务中心 | C53: 呼和浩特办事处 | D53: 土默特左旗金誉良电气安装服务部 | E53: 合作 | F53: 刘晓丰 | G53: JS000029708 | H53: FGDG20260730004233 | I53: 报装 | J53: 吸油烟机 | K53: 安装 | L53: 保内 | M53: 挂钩组件(Z6T)FW | N53: 1101001508560 | O53: B | P53: 辅材 | Q53: 其他烟机 | R53: 其他产品线专用 | S53: 1 | T53: 50 | U53: 50 | V53: 50 | W53: 50 | X53: 0 | AA53: 35 | AB53: 35 | AD53: 已确认 | AE53: 46238.78 | AH53: 现金收费 | AI53: 已支付 | AJ53: 46235 | AK53: 46236.426
A54: 西北大区部 | B54: 呼和浩特服务中心 | C54: 呼和浩特办事处 | D54: 呼和浩特市回民区彦辰家电维修经营部 | E54: 合作 | F54: 王鹏 | G54: JS000043198 | H54: FGDG20260804013568 | I54: 报装 | J54: 吸油烟机 | K54: 安装 | L54: 保内 | M54: 挂钩组件(Z6T)FW | N54: 1101001508560 | O54: B | P54: 辅材 | Q54: 其他烟机 | R54: 其他产品线专用 | S54: 1 | T54: 50 | U54: 50 | V54: 50 | W54: 50 | X54: 0 | AA54: 35 | AB54: 35 | AD54: 已确认 | AE54: 46238.776 | AH54: 现金收费 | AI54: 已支付 | AJ54: 46237 | AK54: 46238.771
A55: 西北大区部 | B55: 呼和浩特服务中心 | C55: 呼和浩特办事处 | D55: 呼和浩特市回民区彦辰家电维修经营部 | E55: 合作 | F55: 侯慧忠 | G55: JS000015636 | H55: FGDG20260802021492 | I55: 报修 | J55: 灶具 | K55: 维修 | L55: 保外 | M55: 内环火盖组件Y/T(JZY-HC1G-20Y) | N55: 110200200050D | O55: A | P55: 维修 | Q55: 无 | S55: 1 | T55: 25 | U55: 200 | V55: 200 | W55: 25 | X55: 0 | AA55: 17.5 | AB55: 17.5 | AD55: 已确认 | AE55: 46238.776 | AH55: 现金收费 | AI55: 已支付 | AJ55: 42408 | AK55: 46238.522
A56: 西北大区部 | B56: 呼和浩特服务中心 | C56: 呼和浩特办事处 | D56: 呼和浩特市回民区彦辰家电维修经营部 | E56: 合作 | F56: 侯慧忠 | G56: JS000015636 | H56: FGDG20260802021492 | I56: 报修 | J56: 灶具 | K56: 维修 | L56: 保外 | M56: 内环火盖组件Y/T(JZY-HC1G-20Y) | N56: 110200200050D | O56: A | P56: 维修 | Q56: 无 | S56: 1 | T56: 25 | U56: 200 | V56: 200 | W56: 25 | X56: 0 | AA56: 17.5 | AB56: 17.5 | AD56: 已确认 | AE56: 46238.776 | AH56: 现金收费 | AI56: 已支付 | AJ56: 42408 | AK56: 46238.522
A57: 西北大区部 | B57: 呼和浩特服务中心 | C57: 呼和浩特办事处 | D57: 呼和浩特市回民区彦辰家电维修经营部 | E57: 合作 | F57: 侯慧忠 | G57: JS000015636 | H57: FGDG20260802021492 | I57: 报修 | J57: 灶具 | K57: 维修 | L57: 保外 | M57: 热电偶(JZY-HC1G-20Y) | N57: 110200200055H | O57: A | P57: 维修 | Q57: 无 | S57: 1 | T57: 20 | U57: 200 | V57: 200 | W57: 20 | X57: 0 | AA57: 14 | AB57: 14 | AD57: 已确认 | AE57: 46238.776 | AH57: 现金收费 | AI57: 已支付 | AJ57: 42408 | AK57: 46238.522
A58: 西北大区部 | B58: 呼和浩特服务中心 | C58: 呼和浩特办事处 | D58: 呼和浩特市回民区彦辰家电维修经营部 | E58: 合作 | F58: 侯慧忠 | G58: JS000015636 | H58: FGDG20260802021492 | I58: 报修 | J58: 灶具 | K58: 维修 | L58: 保外 | M58: 双线圈电磁阀(点胶)(JZT-HL6B-12T)FW | N58: 110200160548R | O58: A | P58: 维修 | Q58: 无 | S58: 1 | T58: 40 | U58: 200 | V58: 200 | W58: 40 | X58: 0 | AA58: 28 | AB58: 28 | AD58: 已确认 | AE58: 46238.776 | AH58: 现金收费 | AI58: 已支付 | AJ58: 42408 | AK58: 46238.522
A59: 西北大区部 | B59: 呼和浩特服务中心 | C59: 呼和浩特办事处 | D59: 呼和浩特市回民区彦辰家电维修经营部 | E59: 合作 | F59: 王鹏 | G59: JS000043198 | H59: FGDG20260802027943 | I59: 报装 | J59: 吸油烟机 | K59: 安装 | L59: 保内 | M59: 挂钩组件(Z6T)FW | N59: 1101001508560 | O59: B | P59: 辅材 | Q59: 其他烟机 | R59: 其他产品线专用 | S59: 1 | T59: 50 | U59: 50 | V59: 50 | W59: 50 | X59: 0 | AA59: 35 | AB59: 35 | AD59: 已确认 | AE59: 46238.776 | AH59: 现金收费 | AI59: 已支付 | AJ59: 46236 | AK59: 46237.793
A60: 西北大区部 | B60: 呼和浩特服务中心 | C60: 呼和浩特办事处 | D60: 呼和浩特市回民区彦辰家电维修经营部 | E60: 合作 | F60: 王鹏 | G60: JS000043198 | H60: FGDG20260803004131 | I60: 报装 | J60: 吸油烟机 | K60: 安装 | L60: 保内 | M60: 挂钩组件(Z6T)FW | N60: 1101001508560 | O60: B | P60: 辅材 | Q60: 其他烟机 | R60: 其他产品线专用 | S60: 1 | T60: 50 | U60: 50 | V60: 50 | W60: 50 | X60: 0 | AA60: 35 | AB60: 35 | AD60: 已确认 | AE60: 46238.776 | AH60: 现金收费 | AI60: 已支付 | AJ60: 46236 | AK60: 46237.717
A61: 西北大区部 | B61: 呼和浩特服务中心 | C61: 呼和浩特办事处 | D61: 呼和浩特市回民区彦辰家电维修经营部 | E61: 合作 | F61: 侯慧忠 | G61: JS000015636 | H61: FGDG20260801023157 | I61: 报装 | J61: 吸油烟机 | K61: 安装 | L61: 保内 | M61: 排油烟气防火止回阀组件_S3-A | N61: 112500010069D | O61: B | P61: 辅材 | Q61: 防烟宝 | R61: 止回阀 | S61: 1 | T61: 180 | U61: 230 | V61: 230 | W61: 180 | X61: 0 | AA61: 100 | AB61: 100 | AD61: 已确认 | AE61: 46238.776 | AH61: 现金收费 | AI61: 已支付 | AJ61: 46196 | AK61: 46237.545
A62: 西北大区部 | B62: 呼和浩特服务中心 | C62: 呼和浩特办事处 | D62: 呼和浩特市回民区彦辰家电维修经营部 | E62: 合作 | F62: 侯慧忠 | G62: JS000015636 | H62: FGDG20260801023157 | I62: 报装 | J62: 吸油烟机 | K62: 安装 | L62: 保内 | M62: 挂钩组件(Z6T)FW | N62: 1101001508560 | O62: B | P62: 辅材 | Q62: 其他烟机 | R62: 其他产品线专用 | S62: 1 | T62: 50 | U62: 230 | V62: 230 | W62: 50 | X62: 0 | AA62: 35 | AB62: 35 | AD62: 已确认 | AE62: 46238.776 | AH62: 现金收费 | AI62: 已支付 | AJ62: 46196 | AK62: 46237.545
A63: 西北大区部 | B63: 呼和浩特服务中心 | C63: 呼和浩特办事处 | D63: 呼和浩特市回民区彦辰家电维修经营部 | E63: 合作 | F63: 王鹏 | G63: JS000043198 | H63: FGDG20260730026905 | I63: 报装 | J63: 吸油烟机 | K63: 安装 | L63: 保内 | M63: 挂钩组件(Z6T)FW | N63: 1101001508560 | O63: B | P63: 辅材 | Q63: 其他烟机 | R63: 其他产品线专用 | S63: 1 | T63: 50 | U63: 50 | V63: 50 | W63: 50 | X63: 0 | AA63: 35 | AB63: 35 | AD63: 已确认 | AE63: 46238.776 | AH63: 现金收费 | AI63: 已支付 | AJ63: 46236 | AK63: 46237.508
A64: 西北大区部 | B64: 呼和浩特服务中心 | C64: 呼和浩特办事处 | D64: 呼和浩特市回民区彦辰家电维修经营部 | E64: 合作 | F64: 王鹏 | G64: JS000043198 | H64: FGDG20260802011048 | I64: 报装 | J64: 吸油烟机 | K64: 多次安装 | L64: 保外 | M64: 铝箔出风管（标贴）(EM01T)FW | N64: 110100091899D | O64: B | P64: 辅材 | Q64: 出风管 | R64: 排烟出风管 | S64: 1 | T64: 50 | U64: 150 | V64: 150 | W64: 50 | X64: 0 | AA64: 35 | AB64: 35 | AD64: 已确认 | AE64: 46238.776 | AH64: 现金收费 | AI64: 已支付 | AJ64: 41967 | AK64: 46236.772
A65: 西北大区部 | B65: 呼和浩特服务中心 | C65: 呼和浩特办事处 | D65: 呼和浩特市回民区彦辰家电维修经营部 | E65: 合作 | F65: 王鹏 | G65: JS000043198 | H65: FGDG20260802011048 | I65: 报装 | J65: 吸油烟机 | K65: 多次安装 | L65: 保外 | M65: 挂钩组件(Z6T)FW | N65: 1101001508560 | O65: B | P65: 辅材 | Q65: 其他烟机 | R65: 其他产品线专用 | S65: 1 | T65: 50 | U65: 150 | V65: 150 | W65: 50 | X65: 0 | AA65: 35 | AB65: 35 | AD65: 已确认 | AE65: 46238.776 | AH65: 现金收费 | AI65: 已支付 | AJ65: 41967 | AK65: 46236.772
A66: 西北大区部 | B66: 呼和浩特服务中心 | C66: 呼和浩特办事处 | D66: 呼和浩特市回民区彦辰家电维修经营部 | E66: 合作 | F66: 侯慧忠 | G66: JS000015636 | H66: FGDG20260802023326 | I66: 报装 | J66: 吸油烟机 | K66: 油烟机预埋烟管 | L66: 保外 | M66: 铝箔出风管_φ189_1.6m_S1Pro | N66: 1101003500000 | O66: B | P66: 辅材 | Q66: 出风管 | R66: 排烟出风管 | S66: 1 | T66: 50 | U66: 50 | V66: 50 | W66: 50 | X66: 0 | AA66: 35 | AB66: 35 | AD66: 已确认 | AE66: 46238.776 | AH66: 现金收费 | AI66: 已支付 | AK66: 46236.744
A67: 西北大区部 | B67: 呼和浩特服务中心 | C67: 呼和浩特办事处 | D67: 呼和浩特市回民区彦辰家电维修经营部 | E67: 合作 | F67: 王鹏 | G67: JS000043198 | H67: FGDG20260802003355 | I67: 报装 | J67: 智慧水槽 | K67: 安装 | L67: 保内 | M67: 水龙头三通(JBSD2T-Q1) | N67: 110800010013A | O67: B | P67: 辅材 | Q67: 其他热水器 | R67: 其他水路辅材 | S67: 1 | T67: 40 | U67: 40 | V67: 40 | W67: 40 | X67: 0 | AA67: 28 | AB67: 28 | AD67: 已确认 | AE67: 46238.776 | AH67: 现金收费 | AI67: 已支付 | AJ67: 46196 | AK67: 46236.523
A68: 西北大区部 | B68: 呼和浩特服务中心 | C68: 呼和浩特办事处 | D68: 呼和浩特市回民区彦辰家电维修经营部 | E68: 合作 | F68: 侯慧忠 | G68: JS000015636 | H68: FGDG20260806018282 | I68: 报装 | J68: 灶具 | K68: 调试 | L68: 保内 | M68: 气管接头组件(JZT-HD1G-12T)FW | N68: 1102001701120 | O68: A | P68: 维修 | Q68: 无 | S68: 1 | T68: 20 | U68: 110 | V68: 110 | W68: 20 | X68: 0 | AA68: 14 | AB68: 14 | AD68: 已确认 | AE68: 46243.337 | AH68: 现金收费 | AI68: 已支付 | AJ68: 46229 | AK68: 46240.819
A69: 西北大区部 | B69: 呼和浩特服务中心 | C69: 呼和浩特办事处 | D69: 呼和浩特市回民区彦辰家电维修经营部 | E69: 合作 | F69: 侯慧忠 | G69: JS000015636 | H69: FGDG20260806023268 | I69: 报装 | J69: 灶具 | K69: 调试 | L69: 保内 | M69: 换装底盘扩展支架_TF21B | N69: 1102004309130 | O69: B | P69: 辅材 | Q69: 其他灶具 | R69: 其他产品线专用 | S69: 1 | T69: 20 | U69: 20 | V69: 20 | W69: 20 | X69: 0 | AA69: 14 | AB69: 14 | AD69: 已确认 | AE69: 46243.337 | AH69: 现金收费 | AI69: 已支付 | AJ69: 46233 | AK69: 46240.74
A70: 西北大区部 | B70: 呼和浩特服务中心 | C70: 呼和浩特办事处 | D70: 呼和浩特市回民区彦辰家电维修经营部 | E70: 合作 | F70: 侯慧忠 | G70: JS000015636 | H70: FGDG20260803003002 | I70: 报修 | J70: 灶具 | K70: 维修 | L70: 保外 | M70: 点火针组件（加聚能环）(JZY-FC1G-20Y) | N70: 1102001401140 | O70: A | P70: 维修 | Q70: 无 | S70: 1 | T70: 10 | U70: 140 | V70: 140 | W70: 10 | X70: 0 | AA70: 7 | AB70: 7 | AD70: 已确认 | AE70: 46243.337 | AH70: 现金收费 | AI70: 已支付 | AJ70: 41857 | AK70: 46240.491
A71: 西北大区部 | B71: 呼和浩特服务中心 | C71: 呼和浩特办事处 | D71: 呼和浩特市回民区彦辰家电维修经营部 | E71: 合作 | F71: 侯慧忠 | G71: JS000015636 | H71: FGDG20260803003002 | I71: 报修 | J71: 灶具 | K71: 维修 | L71: 保外 | M71: 点火器组件(JZY-FC1G-20Y) | N71: 110200140119D | O71: A | P71: 维修 | Q71: 无 | S71: 1 | T71: 40 | U71: 140 | V71: 140 | W71: 40 | X71: 0 | AA71: 28 | AB71: 28 | AD71: 已确认 | AE71: 46243.337 | AH71: 现金收费 | AI71: 已支付 | AJ71: 41857 | AK71: 46240.491
A72: 西北大区部 | B72: 呼和浩特服务中心 | C72: 呼和浩特办事处 | D72: 呼和浩特市回民区彦辰家电维修经营部 | E72: 合作 | F72: 王鹏 | G72: JS000043198 | H72: FGDG20260806005159 | I72: 其他 | J72: 吸油烟机 | K72: 安装装饰罩 | L72: 保内 | M72: 装饰罩组件_03-Z5TA | N72: 1101001518540 | O72: B | P72: 辅材 | Q72: 装饰罩 | R72: 装饰罩 | S72: 1 | T72: 350 | U72: 350 | V72: 350 | W72: 350 | X72: 0 | AA72: 245 | AB72: 245 | AD72: 已确认 | AE72: 46243.337 | AH72: 现金收费 | AI72: 已支付 | AJ72: 46237 | AK72: 46240.413
A73: 西北大区部 | B73: 呼和浩特服务中心 | C73: 呼和浩特办事处 | D73: 呼和浩特市回民区彦辰家电维修经营部 | E73: 合作 | F73: 侯慧忠 | G73: JS000015636 | H73: FGDG20260805020405 | I73: 其他 | J73: 吸油烟机 | K73: 安装装饰罩 | L73: 保内 | M73: 装饰罩组件_T31 | N73: 1101003401170 | O73: B | P73: 辅材 | Q73: 装饰罩 | R73: 装饰罩 | S73: 1 | T73: 350 | U73: 350 | V73: 350 | W73: 350 | X73: 0 | AA73: 245 | AB73: 245 | AD73: 已确认 | AE73: 46243.337 | AI73: 未支付 | AJ73: 46232 | AK73: 46239.867
A74: 西北大区部 | B74: 呼和浩特服务中心 | C74: 呼和浩特办事处 | D74: 呼和浩特市回民区彦辰家电维修经营部 | E74: 合作 | F74: 王鹏 | G74: JS000043198 | H74: FGDG20260803009623 | I74: 报装 | J74: 嵌入式洗碗机 | K74: 安装 | L74: 保内 | M74: 泰和三角阀_水路(冷)FW | N74: 1507030100502 | O74: B | P74: 辅材 | Q74: 其他热水器 | R74: 其他水路辅材 | S74: 1 | T74: 60 | U74: 185 | V74: 185 | W74: 60 | X74: 0 | AA74: 42 | AB74: 42 | AD74: 已确认 | AE74: 46243.337 | AH74: 现金收费 | AI74: 已支付 | AJ74: 46238 | AK74: 46239.515
A75: 西北大区部 | B75: 呼和浩特服务中心 | C75: 呼和浩特办事处 | D75: 呼和浩特市回民区彦辰家电维修经营部 | E75: 合作 | F75: 王鹏 | G75: JS000043198 | H75: FGDG20260803009623 | I75: 报装 | J75: 嵌入式洗碗机 | K75: 安装 | L75: 保内 | M75: 进水管组件-加长管2m-/FW | N75: 1507020400357 | O75: B | P75: 辅材 | Q75: 其他热水器 | R75: 其他产品线专用 | S75: 1 | T75: 105 | U75: 185 | V75: 185 | W75: 105 | X75: 0 | AA75: 73.5 | AB75: 73.5 | AD75: 已确认 | AE75: 46243.337 | AH75: 现金收费 | AI75: 已支付 | AJ75: 46238 | AK75: 46239.515
A76: 西北大区部 | B76: 呼和浩特服务中心 | C76: 呼和浩特办事处 | D76: 呼和浩特市回民区彦辰家电维修经营部 | E76: 合作 | F76: 王鹏 | G76: JS000043198 | H76: FGDG20260803009623 | I76: 报装 | J76: 嵌入式洗碗机 | K76: 安装 | L76: 保内 | M76: LF对丝-铜-4-G1/2-R1/2-LF | N76: 1507020200800 | O76: B | P76: 辅材 | Q76: 其他灶具 | R76: 其他水路辅材 | S76: 1 | T76: 20 | U76: 185 | V76: 185 | W76: 20 | X76: 0 | AA76: 14 | AB76: 14 | AD76: 已确认 | AE76: 46243.337 | AH76: 现金收费 | AI76: 已支付 | AJ76: 46238 | AK76: 46239.515
A77: 西北大区部 | B77: 呼和浩特服务中心 | C77: 呼和浩特办事处 | D77: 土默特左旗占平安装维修部 | E77: 合作 | F77: 妥晓勇 | G77: JS000034706 | H77: FGDG20260806011959 | I77: 报装 | J77: 吸油烟机 | K77: 安装 | L77: 保内 | M77: 铝箔出风管_φ189_1.6m_S1Pro | N77: 1101003500000 | O77: B | P77: 辅材 | Q77: 出风管 | R77: 排烟出风管 | S77: 1 | T77: 50 | U77: 100 | V77: 100 | W77: 50 | X77: 0 | AA77: 35 | AB77: 35 | AD77: 支付中 | AE77: 46243.351 | AI77: 未支付 | AJ77: 46241 | AK77: 46242.675
A78: 西北大区部 | B78: 呼和浩特服务中心 | C78: 呼和浩特办事处 | D78: 土默特左旗占平安装维修部 | E78: 合作 | F78: 妥晓勇 | G78: JS000034706 | H78: FGDG20260806011959 | I78: 报装 | J78: 吸油烟机 | K78: 安装 | L78: 保内 | M78: 挂钩组件(Z6T)FW | N78: 1101001508560 | O78: B | P78: 辅材 | Q78: 其他烟机 | R78: 其他产品线专用 | S78: 1 | T78: 50 | U78: 100 | V78: 100 | W78: 50 | X78: 0 | AA78: 35 | AB78: 35 | AD78: 支付中 | AE78: 46243.351 | AI78: 未支付 | AJ78: 46241 | AK78: 46242.675
A79: 西北大区部 | B79: 呼和浩特服务中心 | C79: 呼和浩特办事处 | D79: 土默特左旗占平安装维修部 | E79: 合作 | F79: 赵拴钱 | G79: JS000039518 | H79: FGDG20260806007686 | I79: 报装 | J79: 吸油烟机 | K79: 安装 | L79: 保内 | M79: 挂钩组件(Z6T)FW | N79: 1101001508560 | O79: B | P79: 辅材 | Q79: 其他烟机 | R79: 其他产品线专用 | S79: 1 | T79: 50 | U79: 50 | V79: 50 | W79: 50 | X79: 0 | AA79: 35 | AB79: 35 | AD79: 支付中 | AE79: 46243.351 | AI79: 未支付 | AJ79: 46169 | AK79: 46242.424
A80: 西北大区部 | B80: 呼和浩特服务中心 | C80: 呼和浩特办事处 | D80: 土默特左旗占平安装维修部 | E80: 合作 | F80: 妥晓勇 | G80: JS000034706 | H80: FGDG20260803028369 | I80: 报修 | J80: 水槽洗碗机 | K80: 维修 | L80: 保内 | M80: 门体组件(JBSD2T-K3B) | N80: 110800030951A | O80: A | P80: 维修 | Q80: 无 | S80: 1 | T80: 505 | U80: 505 | V80: 505 | W80: 505 | X80: 0 | AA80: 353.5 | AB80: 353.5 | AD80: 支付中 | AE80: 46243.351 | AI80: 未支付 | AJ80: 45160 | AK80: 46241.71
A81: 西北大区部 | B81: 呼和浩特服务中心 | C81: 呼和浩特办事处 | D81: 土默特左旗占平安装维修部 | E81: 合作 | F81: 赵拴钱 | G81: JS000039518 | H81: FGDG20260806030535 | I81: 报装 | J81: 吸油烟机 | K81: 安装 | L81: 保内 | M81: 挂钩组件(Z6T)FW | N81: 1101001508560 | O81: B | P81: 辅材 | Q81: 其他烟机 | R81: 其他产品线专用 | S81: 1 | T81: 50 | U81: 50 | V81: 50 | W81: 50 | X81: 0 | AA81: 35 | AB81: 35 | AD81: 支付中 | AE81: 46243.351 | AH81: 现金收费 | AI81: 已支付 | AJ81: 46240 | AK81: 46241.469
A82: 西北大区部 | B82: 呼和浩特服务中心 | C82: 呼和浩特办事处 | D82: 土默特左旗占平安装维修部 | E82: 合作 | F82: 张旺 | G82: JS000002134 | H82: FGDG20260806022001 | I82: 报装 | J82: 吸油烟机 | K82: 安装 | L82: 保内 | M82: 挂钩组件(Z6T)FW | N82: 1101001508560 | O82: B | P82: 辅材 | Q82: 其他烟机 | R82: 其他产品线专用 | S82: 1 | T82: 50 | U82: 50 | V82: 50 | W82: 50 | X82: 0 | AA82: 35 | AB82: 35 | AD82: 支付中 | AE82: 46243.351 | AH82: 现金收费 | AI82: 已支付 | AJ82: 46235 | AK82: 46240.797
A83: 西北大区部 | B83: 呼和浩特服务中心 | C83: 呼和浩特办事处 | D83: 土默特左旗占平安装维修部 | E83: 合作 | F83: 杨占平 | G83: JS000008904 | H83: FGDG20260806021531 | I83: 其他 | J83: 吸油烟机 | K83: 工单补录 | L83: 保内 | M83: 出风罩连接圈_V1R1 | N83: 1101002600900 | O83: A | P83: 维修 | Q83: 无 | S83: 1 | T83: 10 | U83: 10 | V83: 10 | W83: 10 | X83: 0 | AA83: 7 | AB83: 7 | AD83: 支付中 | AE83: 46243.351 | AI83: 未支付 | AJ83: 46237 | AK83: 46240.653
A84: 西北大区部 | B84: 呼和浩特服务中心 | C84: 呼和浩特办事处 | D84: 土默特左旗占平安装维修部 | E84: 合作 | F84: 杨占平 | G84: JS000008904 | H84: FGDG20260803030125 | I84: 报装 | J84: 吸油烟机 | K84: 安装 | L84: 保外 | M84: 挂钩组件(Z6T)FW | N84: 1101001508560 | O84: B | P84: 辅材 | Q84: 其他烟机 | R84: 其他产品线专用 | S84: 1 | T84: 50 | U84: 50 | V84: 50 | W84: 50 | X84: 0 | AA84: 35 | AB84: 35 | AD84: 支付中 | AE84: 46243.351 | AI84: 未支付 | AJ84: 46237 | AK84: 46240.645
A85: 西北大区部 | B85: 呼和浩特服务中心 | C85: 呼和浩特办事处 | D85: 土默特左旗占平安装维修部 | E85: 合作 | F85: 杨占平 | G85: JS000008904 | H85: FGDG20260805009329 | I85: 报装 | J85: 吸油烟机 | K85: 安装 | L85: 保内 | M85: 排油烟气防火止回阀组件_S3-A | N85: 112500010069C | O85: B | P85: 辅材 | Q85: 防烟宝 | R85: 止回阀 | S85: 1 | T85: 180 | U85: 230 | V85: 230 | W85: 180 | X85: 0 | AA85: 100 | AB85: 100 | AD85: 支付中 | AE85: 46243.351 | AH85: 现金收费 | AI85: 已支付 | AJ85: 46235 | AK85: 46240.522
A86: 西北大区部 | B86: 呼和浩特服务中心 | C86: 呼和浩特办事处 | D86: 土默特左旗占平安装维修部 | E86: 合作 | F86: 杨占平 | G86: JS000008904 | H86: FGDG20260805009329 | I86: 报装 | J86: 吸油烟机 | K86: 安装 | L86: 保内 | M86: 挂钩组件(Z6T)FW | N86: 1101001508560 | O86: B | P86: 辅材 | Q86: 其他烟机 | R86: 其他产品线专用 | S86: 1 | T86: 50 | U86: 230 | V86: 230 | W86: 50 | X86: 0 | AA86: 35 | AB86: 35 | AD86: 支付中 | AE86: 46243.351 | AH86: 现金收费 | AI86: 已支付 | AJ86: 46235 | AK86: 46240.522
A87: 西北大区部 | B87: 呼和浩特服务中心 | C87: 呼和浩特办事处 | D87: 土默特左旗占平安装维修部 | E87: 合作 | F87: 张旺 | G87: JS000002134 | H87: FGDG20260806007810 | I87: 其他 | J87: 灶具 | K87: 工单补录 | L87: 保内 | M87: 换装底盘扩展支架_02-TD7B_FW | N87: 1102004303200 | O87: B | P87: 辅材 | Q87: 其他灶具 | R87: 橱柜类辅材 | S87: 1 | T87: 25 | U87: 25 | V87: 25 | W87: 25 | X87: 0 | AA87: 17.5 | AB87: 17.5 | AD87: 支付中 | AE87: 46243.351 | AH87: 现金收费 | AI87: 已支付 | AJ87: 46204 | AK87: 46240.445
A88: 西北大区部 | B88: 呼和浩特服务中心 | C88: 呼和浩特办事处 | D88: 土默特左旗占平安装维修部 | E88: 合作 | F88: 赵拴钱 | G88: JS000039518 | H88: FGDG20260804029785 | I88: 报装 | J88: 吸油烟机 | K88: 安装 | L88: 保内 | M88: 挂钩组件(Z6T)FW | N88: 1101001508560 | O88: B | P88: 辅材 | Q88: 其他烟机 | R88: 其他产品线专用 | S88: 1 | T88: 50 | U88: 50 | V88: 50 | W88: 50 | X88: 0 | AA88: 35 | AB88: 35 | AD88: 支付中 | AE88: 46243.351 | AH88: 现金收费 | AI88: 已支付 | AJ88: 46238 | AK88: 46239.749
A89: 西北大区部 | B89: 呼和浩特服务中心 | C89: 呼和浩特办事处 | D89: 土默特左旗占平安装维修部 | E89: 合作 | F89: 妥晓勇 | G89: JS000034706 | H89: FGDG20260804007351 | I89: 报装 | J89: 吸油烟机 | K89: 安装 | L89: 保内 | M89: 挂钩组件(Z6T)FW | N89: 1101001508560 | O89: B | P89: 辅材 | Q89: 其他烟机 | R89: 其他产品线专用 | S89: 1 | T89: 50 | U89: 50 | V89: 50 | W89: 50 | X89: 0 | AA89: 35 | AB89: 35 | AD89: 支付中 | AE89: 46243.351 | AI89: 未支付 | AJ89: 46168 | AK89: 46239.453
A90: 西北大区部 | B90: 呼和浩特服务中心 | C90: 呼和浩特办事处 | D90: 内蒙古洁莱电器安装服务有限公司 | E90: 合作 | F90: 雷锁锁 | G90: JS000020273 | H90: FGDG20260731022521 | I90: 报修 | J90: 水槽洗碗机 | K90: 维修 | L90: 保外 | M90: 双槽强排泵排水组件(JPSD2T-G3)FW | N90: 1108000403420 | O90: B | P90: 辅材 | Q90: 其他热水器 | R90: 其他产品线专用 | S90: 1 | T90: 200 | U90: 260 | V90: 260 | W90: 200 | X90: 0 | AA90: 140 | AB90: 140 | AD90: 已确认 | AE90: 46236.406 | AH90: 现金收费 | AI90: 已支付 | AJ90: 42799 | AK90: 46235.822
A91: 西北大区部 | B91: 呼和浩特服务中心 | C91: 呼和浩特办事处 | D91: 内蒙古洁莱电器安装服务有限公司 | E91: 合作 | F91: 雷锁锁 | G91: JS000020273 | H91: FGDG20260730007475 | I91: 报装 | J91: 水槽洗碗机 | K91: 安装 | L91: 保内 | M91: 泰和三角阀_水路(冷)FW | N91: 1507030100502 | O91: B | P91: 辅材 | Q91: 其他热水器 | R91: 其他水路辅材 | S91: 1 | T91: 60 | U91: 180 | V91: 180 | W91: 60 | X91: 0 | AA91: 42 | AB91: 42 | AD91: 已确认 | AE91: 46236.406 | AH91: 现金收费 | AI91: 已支付 | AJ91: 46210 | AK91: 46235.7
A92: 西北大区部 | B92: 呼和浩特服务中心 | C92: 呼和浩特办事处 | D92: 内蒙古洁莱电器安装服务有限公司 | E92: 合作 | F92: 雷锁锁 | G92: JS000020273 | H92: FGDG20260730007475 | I92: 报装 | J92: 水槽洗碗机 | K92: 安装 | L92: 保内 | M92: 泰和三角阀_水路(热)(JSQ19-1101) | N92: 1507030100013 | O92: B | P92: 辅材 | Q92: 其他热水器 | R92: 其他水路辅材 | S92: 1 | T92: 60 | U92: 180 | V92: 180 | W92: 60 | X92: 0 | AA92: 42 | AB92: 42 | AD92: 已确认 | AE92: 46236.406 | AH92: 现金收费 | AI92: 已支付 | AJ92: 46210 | AK92: 46235.7
A93: 西北大区部 | B93: 呼和浩特服务中心 | C93: 呼和浩特办事处 | D93: 内蒙古洁莱电器安装服务有限公司 | E93: 合作 | F93: 雷锁锁 | G93: JS000020273 | H93: FGDG20260730007475 | I93: 报装 | J93: 水槽洗碗机 | K93: 安装 | L93: 保内 | M93: 泰和三角阀_水路(热)(JSQ19-1101) | N93: 1507030100013 | O93: B | P93: 辅材 | Q93: 其他热水器 | R93: 其他水路辅材 | S93: 1 | T93: 60 | U93: 180 | V93: 180 | W93: 60 | X93: 0 | AA93: 42 | AB93: 42 | AD93: 已确认 | AE93: 46236.406 | AH93: 现金收费 | AI93: 已支付 | AJ93: 46210 | AK93: 46235.7
A94: 西北大区部 | B94: 呼和浩特服务中心 | C94: 呼和浩特办事处 | D94: 内蒙古洁莱电器安装服务有限公司 | E94: 合作 | F94: 雷锁锁 | G94: JS000020273 | H94: FGDG20260731020037 | I94: 报装 | J94: 吸油烟机 | K94: 安装 | L94: 保内 | M94: 排油烟气防火止回阀组件_S3-B | N94: 112500010076B | O94: B | P94: 辅材 | Q94: 防烟宝 | R94: 止回阀 | S94: 1 | T94: 180 | U94: 180 | V94: 180 | W94: 180 | X94: 0 | AA94: 100 | AB94: 100 | AD94: 已确认 | AE94: 46236.406 | AH94: 现金收费 | AI94: 已支付 | AJ94: 46226 | AK94: 46235.607
A95: 西北大区部 | B95: 呼和浩特服务中心 | C95: 呼和浩特办事处 | D95: 内蒙古洁莱电器安装服务有限公司 | E95: 合作 | F95: 赵云飞 | G95: JS000025678 | H95: FGDG20260731028416 | I95: 其他 | J95: 水槽洗碗机 | K95: 样机维修 | L95: 保外 | M95: 进气管(JBSD2F-E5) | N95: 110800050115A | O95: A | P95: 维修 | Q95: 无 | S95: 1 | T95: 5 | U95: 175 | V95: 175 | W95: 5 | X95: 0 | AA95: 3.5 | AB95: 3.5 | AD95: 已确认 | AE95: 46236.406 | AH95: 现金收费 | AI95: 已支付 | AJ95: 43308 | AK95: 46234.856
A96: 西北大区部 | B96: 呼和浩特服务中心 | C96: 呼和浩特办事处 | D96: 内蒙古洁莱电器安装服务有限公司 | E96: 合作 | F96: 赵云飞 | G96: JS000025678 | H96: FGDG20260731028416 | I96: 其他 | J96: 水槽洗碗机 | K96: 样机维修 | L96: 保外 | M96: 排水管组件_JBSD2T-K3A | N96: 110800031359A | O96: A | P96: 维修 | Q96: 无 | S96: 1 | T96: 80 | U96: 175 | V96: 175 | W96: 80 | X96: 0 | AA96: 56 | AB96: 56 | AD96: 已确认 | AE96: 46236.406 | AH96: 现金收费 | AI96: 已支付 | AJ96: 43308 | AK96: 46234.856
A97: 西北大区部 | B97: 呼和浩特服务中心 | C97: 呼和浩特办事处 | D97: 内蒙古洁莱电器安装服务有限公司 | E97: 合作 | F97: 赵云飞 | G97: JS000025678 | H97: FGDG20260731028416 | I97: 其他 | J97: 水槽洗碗机 | K97: 样机维修 | L97: 保外 | M97: 大槽下水器组件(SD2F-P1X-MYFT) | N97: 110800030657A | O97: A | P97: 维修 | Q97: 无 | S97: 1 | T97: 90 | U97: 175 | V97: 175 | W97: 90 | X97: 0 | AA97: 63 | AB97: 63 | AD97: 已确认 | AE97: 46236.406 | AH97: 现金收费 | AI97: 已支付 | AJ97: 43308 | AK97: 46234.856
A98: 西北大区部 | B98: 呼和浩特服务中心 | C98: 呼和浩特办事处 | D98: 内蒙古洁莱电器安装服务有限公司 | E98: 合作 | F98: 赵云飞 | G98: JS000025678 | H98: FGDG20260731028415 | I98: 其他 | J98: 吸油烟机 | K98: 样机维修 | L98: 保外 | M98: 出风罩连接圈_V1R1 | N98: 1101002600900 | O98: A | P98: 维修 | Q98: 无 | S98: 1 | T98: 10 | U98: 185 | V98: 185 | W98: 10 | X98: 0 | AA98: 7 | AB98: 7 | AD98: 已确认 | AE98: 46236.406 | AH98: 现金收费 | AI98: 已支付 | AJ98: 43309 | AK98: 46234.855
A99: 西北大区部 | B99: 呼和浩特服务中心 | C99: 呼和浩特办事处 | D99: 内蒙古洁莱电器安装服务有限公司 | E99: 合作 | F99: 赵云飞 | G99: JS000025678 | H99: FGDG20260731028415 | I99: 其他 | J99: 吸油烟机 | K99: 样机维修 | L99: 保外 | M99: 油杯组件(EH11D) | N99: 110100080543L | O99: A | P99: 维修 | Q99: 无 | S99: 1 | T99: 15 | U99: 185 | V99: 185 | W99: 15 | X99: 0 | AA99: 10.5 | AB99: 10.5 | AD99: 已确认 | AE99: 46236.406 | AH99: 现金收费 | AI99: 已支付 | AJ99: 43309 | AK99: 46234.855
A100: 西北大区部 | B100: 呼和浩特服务中心 | C100: 呼和浩特办事处 | D100: 内蒙古洁莱电器安装服务有限公司 | E100: 合作 | F100: 赵云飞 | G100: JS000025678 | H100: FGDG20260731028415 | I100: 其他 | J100: 吸油烟机 | K100: 样机维修 | L100: 保外 | M100: 油杯组件(EH11D) | N100: 110100080543L | O100: A | P100: 维修 | Q100: 无 | S100: 1 | T100: 15 | U100: 185 | V100: 185 | W100: 15 | X100: 0 | AA100: 10.5 | AB100: 10.5 | AD100: 已确认 | AE100: 46236.406 | AH100: 现金收费 | AI100: 已支付 | AJ100: 43309 | AK100: 46234.855
A101: 西北大区部 | B101: 呼和浩特服务中心 | C101: 呼和浩特办事处 | D101: 内蒙古洁莱电器安装服务有限公司 | E101: 合作 | F101: 赵云飞 | G101: JS000025678 | H101: FGDG20260731028415 | I101: 其他 | J101: 吸油烟机 | K101: 样机维修 | L101: 保外 | M101: 出风罩组件_本色_180_长琴V1R1 | N101: 110100260107A | O101: A | P101: 维修 | Q101: 无 | S101: 1 | T101: 45 | U101: 185 | V101: 185 | W101: 45 | X101: 0 | AA101: 31.5 | AB101: 31.5 | AD101: 已确认 | AE101: 46236.406 | AH101: 现金收费 | AI101: 已支付 | AJ101: 43309 | AK101: 46234.855
...

Sheet 服务产品收入统计
A2: 大区 | B2: 服务中心 | C2: 办事处 | D2: 服务网点 | E2: 中心机构 | F2: 网点类型 | G2: 服务工程师 | H2: 服务工程师编码 | I2: 数据来源 | J2: 清洗保养 | K2: 延保服务 | L2: 清洁耗材 | M2: 止回阀 | N2: 装饰罩 | O2: 水/气路金属软管 | P2: 排烟出风管 | Q2: 水气路通用辅材 | R2: 其他产品线专用 | S2: 其他水路辅材 | T2: 其他气路辅材 | U2: 橱柜类辅材 | V2: 燃气管快速接头 | W2: 工具 | X2: 电路辅材 | Y2: 合计
A3: 西北大区部 | B3: 兰州服务中心 | C3: 兰州办事处 | D3: 兰州服务中心零售网点 | E3: 分支机构 | F3: 自营 | G3: 郭延峰 | H3: JS000004278 | I3: 工单消耗 | J3: 2237 | K3: 0 | L3: 0 | M3: 0 | N3: 0 | O3: 0 | P3: 50 | Q3: 0 | R3: 0 | S3: 0 | T3: 0 | U3: 0 | V3: 0 | W3: 0 | X3: 0 | Y3: 2287
A4: 西北大区部 | B4: 乌鲁木齐服务中心 | C4: 新疆办事处 | D4: 乌鲁木齐市米东区宏誉家电维修服务部 | E4: 分支机构 | F4: 合作 | G4: 闫玉洁 | H4: JS000027179 | I4: 工单消耗 | J4: 140 | K4: 0 | L4: 0 | M4: 0 | N4: 0 | O4: 0 | P4: 0 | Q4: 0 | R4: 0 | S4: 0 | T4: 0 | U4: 0 | V4: 0 | W4: 0 | X4: 0 | Y4: 140
A5: 西北大区部 | B5: 兰州服务中心 | C5: 兰州办事处 | D5: 兰州百洁立家政服务有限公司 | E5: 分支机构 | F5: 合作 | G5: 李成建 | H5: JS000002967 | I5: 工单消耗 | J5: 225 | K5: 0 | L5: 0 | M5: 100 | N5: 0 | O5: 0 | P5: 0 | Q5: 0 | R5: 60 | S5: 0 | T5: 0 | U5: 0 | V5: 0 | W5: 0 | X5: 0 | Y5: 385
A6: 西北大区部 | B6: 乌鲁木齐服务中心 | C6: 新疆办事处 | D6: 乌鲁木齐经济技术开发区（头屯河区）明瑞商务服务工作室 | E6: 分支机构 | F6: 合作 | G6: 闫玉洁 | H6: JS000027179 | I6: 工单消耗 | J6: 1320 | K6: 0 | L6: 0 | M6: 0 | N6: 0 | O6: 0 | P6: 0 | Q6: 0 | R6: 0 | S6: 0 | T6: 0 | U6: 0 | V6: 0 | W6: 0 | X6: 0 | Y6: 1320
A7: 西北大区部 | B7: 乌鲁木齐服务中心 | C7: 新疆办事处 | D7: 乌鲁木齐市米东区宏誉家电维修服务部 | E7: 分支机构 | F7: 合作 | G7: 张宏 | H7: JS000004379 | I7: 工单消耗 | J7: 0 | K7: 343.5 | L7: 0 | M7: 0 | N7: 0 | O7: 0 | P7: 0 | Q7: 0 | R7: 0 | S7: 0 | T7: 0 | U7: 0 | V7: 0 | W7: 0 | X7: 0 | Y7: 343.5
A8: 西北大区部 | B8: 兰州服务中心 | C8: 兰州办事处 | D8: 西峰区二牛电器维修服务中心 | E8: 分支机构 | F8: 合作 | G8: 郭海军 | H8: JS000023509 | I8: 工单消耗 | J8: 0 | K8: 732.8 | L8: 0 | M8: 0 | N8: 0 | O8: 0 | P8: 0 | Q8: 0 | R8: 98 | S8: 0 | T8: 0 | U8: 0 | V8: 0 | W8: 0 | X8: 0 | Y8: 830.8
A9: 西北大区部 | B9: 兰州服务中心 | C9: 西宁办事处 | D9: 西宁代表处 | E9: 分支机构 | F9: 自营 | G9: 本国平 | H9: JS000002036 | I9: 工单消耗 | J9: 0 | K9: 916 | L9: 0 | M9: 0 | N9: 0 | O9: 0 | P9: 252 | Q9: 0 | R9: 100 | S9: 0 | T9: 0 | U9: 0 | V9: 0 | W9: 0 | X9: 0 | Y9: 1268
A10: 西北大区部 | B10: 宁夏服务中心 | C10: 宁夏办事处 | D10: 海原县宏志家电维修中心（个体工商户） | E10: 分支机构 | F10: 合作 | G10: 田志龙 | H10: JS000031047 | I10: 工单消耗 | J10: 0 | K10: 0 | L10: 0 | M10: 500 | N10: 0 | O10: 0 | P10: 476 | Q10: 0 | R10: 35 | S10: 0 | T10: 0 | U10: 0 | V10: 0 | W10: 0 | X10: 0 | Y10: 1011
A11: 西北大区部 | B11: 兰州服务中心 | C11: 兰州办事处 | D11: 会宁县伍龙家政服务店 | E11: 分支机构 | F11: 合作 | G11: 朱武龙 | H11: JS000009567 | I11: 工单消耗 | J11: 0 | K11: 0 | L11: 0 | M11: 1200 | N11: 0 | O11: 0 | P11: 0 | Q11: 0 | R11: 105 | S11: 0 | T11: 0 | U11: 0 | V11: 0 | W11: 0 | X11: 0 | Y11: 1305
A12: 西北大区部 | B12: 宁夏服务中心 | C12: 宁夏办事处 | D12: 固原市原州区凯鑫电器经销部 | E12: 分支机构 | F12: 合作 | G12: 贾龙龙 | H12: JS000014319 | I12: 工单消耗 | J12: 0 | K12: 0 | L12: 0 | M12: 1000 | N12: 0 | O12: 0 | P12: 0 | Q12: 0 | R12: 185.5 | S12: 28 | T12: 0 | U12: 0 | V12: 0 | W12: 0 | X12: 0 | Y12: 1213.5
A13: 西北大区部 | B13: 包头服务中心 | C13: 包头办事处 | D13: 包头服务中心零售网点 | E13: 分支机构 | F13: 自营 | G13: 王学飞 | H13: JS000004197 | I13: 工单消耗 | J13: 0 | K13: 0 | L13: 86 | M13: 0 | N13: 0 | O13: 0 | P13: 0 | Q13: 0 | R13: 110 | S13: 0 | T13: 0 | U13: 0 | V13: 0 | W13: 0 | X13: 0 | Y13: 196
A14: 西北大区部 | B14: 乌鲁木齐服务中心 | C14: 新疆办事处 | D14: 北屯市王金女家电维修店 | E14: 分支机构 | F14: 合作 | G14: 谢彦飞 | H14: JS000023745 | I14: 工单消耗 | J14: 0 | K14: 0 | L14: 0 | M14: 500 | N14: 0 | O14: 0 | P14: 105 | Q14: 0 | R14: 185.5 | S14: 84 | T14: 0 | U14: 0 | V14: 0 | W14: 0 | X14: 0 | Y14: 874.5
... A26: 西北大区部 | B26: 兰州服务中心 | C26: 兰州办事处 | D26: 西和县北源电器店 | E26: 分支机构 | F26: 合作 | G26: 叶西元 | H26: JS000006089 | I26: 工单消耗 | J26: 0 | K26: 0 | L26: 0 | M26: 0 | N26: 0 | O26: 0 | P26: 0 | Q26: 0 | R26: 0 | S26: 0 | T26: 0 | U26: 0 | V26: 0 | W26: 0 | X26: 0 | Y26: 0
A27: 西北大区部 | B27: 呼和浩特服务中心 | C27: 呼和浩特办事处 | D27: 呼和浩特市回民区彦辰家电维修经营部 | E27: 分支机构 | F27: 合作 | I27: 网点买断 | J27: 0 | K27: 0 | L27: 0 | M27: 0 | N27: 0 | O27: 484.97 | P27: 0 | Q27: 0 | R27: 0 | S27: 0 | T27: 0 | U27: 0 | V27: 0 | W27: 0 | X27: 0 | Y27: 484.97
A28: 西北大区部 | B28: 宁夏服务中心 | C28: 宁夏办事处 | D28: 灵武市灵梅军家电快修店 | E28: 分支机构 | F28: 合作 | I28: 网点买断 | J28: 0 | K28: 0 | L28: 312 | M28: 0 | N28: 0 | O28: 139.52 | P28: 0 | Q28: 0 | R28: 0 | S28: 0 | T28: 0 | U28: 0 | V28: 0 | W28: 0 | X28: 0 | Y28: 451.52
A29: 西北大区部 | B29: 宁夏服务中心 | C29: 宁夏办事处 | D29: 固原市原州区凯鑫电器经销部 | E29: 分支机构 | F29: 合作 | I29: 网点买断 | J29: 0 | K29: 0 | L29: 532 | M29: 0 | N29: 0 | O29: 0 | P29: 0 | Q29: 0 | R29: 0 | S29: 0 | T29: 0 | U29: 0 | V29: 0 | W29: 0 | X29: 0 | Y29: 532
A30: 西北大区部 | B30: 乌鲁木齐服务中心 | C30: 新疆办事处 | D30: 阿克苏市零壹家电维修部 | E30: 分支机构 | F30: 合作 | I30: 网点买断 | J30: 0 | K30: 0 | L30: 0 | M30: 0 | N30: 0 | O30: 816.42 | P30: 0 | Q30: 0 | R30: 0 | S30: 0 | T30: 0 | U30: 0 | V30: 222 | W30: 0 | X30: 0 | Y30: 1038.42
A31: 西北大区部 | B31: 兰州服务中心 | C31: 兰州办事处 | D31: 武都百佳润电器维修服务中心 | E31: 分支机构 | F31: 合作 | I31: 网点买断 | J31: 0 | K31: 0 | L31: 0 | M31: 0 | N31: 0 | O31: 462.78 | P31: 0 | Q31: 0 | R31: 0 | S31: 0 | T31: 0 | U31: 0 | V31: 0 | W31: 0 | X31: 0 | Y31: 462.78
A32: 西北大区部 | B32: 兰州服务中心 | C32: 兰州办事处 | D32: 永登鑫元家电维修部（个体工商户） | E32: 分支机构 | F32: 合作 | I32: 网点买断 | J32: 0 | K32: 0 | L32: 0 | M32: 0 | N32: 0 | O32: 2041.05 | P32: 0 | Q32: 0 | R32: 0 | S32: 0 | T32: 0 | U32: 0 | V32: 0 | W32: 0 | X32: 0 | Y32: 2041.05
A33: 西北大区部 | B33: 宁夏服务中心 | C33: 宁夏办事处 | D33: 永宁县杨和镇易玖利家电服务部 | E33: 分支机构 | F33: 合作 | G33: 曹晓凡 | H33: JS000021162 | I33: 工单消耗 | J33: 975 | K33: 0 | L33: 0 | M33: 0 | N33: 0 | O33: 0 | P33: 0 | Q33: 0 | R33: 0 | S33: 0 | T33: 0 | U33: 0 | V33: 0 | W33: 0 | X33: 0 | Y33: 975
A34: 西北大区部 | B34: 宁夏服务中心 | C34: 宁夏办事处 | D34: 宁夏中卫服务站 | E34: 分支机构 | F34: 自营 | G34: 张学文 | H34: JS000006273 | I34: 工单消耗 | J34: 238 | K34: 0 | L34: 256 | M34: 0 | N34: 0 | O34: 60 | P34: 140 | Q34: 0 | R34: 125 | S34: 400 | T34: 0 | U34: 0 | V34: 0 | W34: 0 | X34: 0 | Y34: 1219
A35: 西北大区部 | B35: 宁夏服务中心 | C35: 宁夏办事处 | D35: 贺兰县家玺家电维修部 | E35: 分支机构 | F35: 合作 | G35: 王琪珑 | H35: JS000042601 | I35: 工单消耗 | J35: 300 | K35: 0 | L35: 0 | M35: 700 | N35: 0 | O35: 0 | P35: 0 | Q35: 0 | R35: 210 | S35: 0 | T35: 0 | U35: 0 | V35: 0 | W35: 0 | X35: 0 | Y35: 1210
A36: 西北大区部 | B36: 兰州服务中心 | C36: 西宁办事处 | D36: 青海心自由呼吸环保科技有限公司 | E36: 分支机构 | F36: 合作 | G36: 韩占祥 | H36: JS000033978 | I36: 工单消耗 | J36: 150 | K36: 0 | L36: 0 | M36: 0 | N36: 0 | O36: 0 | P36: 0 | Q36: 0 | R36: 0 | S36: 0 | T36: 0 | U36: 0 | V36: 0 | W36: 0 | X36: 0 | Y36: 150
A37: 西北大区部 | B37: 呼和浩特服务中心 | C37: 呼和浩特办事处 | D37: 内蒙古萱圆居民日常生活服务有限公司 | E37: 分支机构 | F37: 合作 | G37: 李超 | H37: JS000041943 | I37: 工单消耗 | J37: 544 | K37: 0 | L37: 0 | M37: 0 | N37: 0 | O37: 0 | P37: 0 | Q37: 0 | R37: 0 | S37: 0 | T37: 0 | U37: 0 | V37: 0 | W37: 0 | X37: 0 | Y37: 544
A38: 西北大区部 | B38: 宁夏服务中心 | C38: 宁夏办事处 | D38: 永宁县杨和镇中天家电维修部 | E38: 分支机构 | F38: 合作 | G38: 刘佳辉 | H38: JS000029340 | I38: 工单消耗 | J38: 0 | K38: 1076.3 | L38: 0 | M38: 500 | N38: 0 | O38: 0 | P38: 136.5 | Q38: 0 | R38: 140 | S38: 0 | T38: 0 | U38: 0 | V38: 0 | W38: 0 | X38: 0 | Y38: 1852.8
A39: 西北大区部 | B39: 宁夏服务中心 | C39: 宁夏办事处 | D39: 银川服务站 | E39: 分支机构 | F39: 自营 | G39: 刘永坤 | H39: JS000004375 | I39: 工单消耗 | J39: 0 | K39: 656 | L39: 56 | M39: 0 | N39: 0 | O39: 0 | P39: 0 | Q39: 0 | R39: 0 | S39: 0 | T39: 0 | U39: 0 | V39: 0 | W39: 0 | X39: 0 | Y39: 712
A40: 西北大区部 | B40: 兰州服务中心 | C40: 西宁办事处 | D40: 青海心自由呼吸环保科技有限公司 | E40: 分支机构 | F40: 合作 | G40: 张培范 | H40: JS000041020 | I40: 工单消耗 | J40: 0 | K40: 343.5 | L40: 0 | M40: 0 | N40: 0 | O40: 0 | P40: 0 | Q40: 0 | R40: 0 | S40: 0 | T40: 0 | U40: 0 | V40: 0 | W40: 0 | X40: 0 | Y40: 343.5
A41: 西北大区部 | B41: 包头服务中心 | C41: 包头办事处 | D41: 临河区范慧明家电维修中心 | E41: 分支机构 | F41: 合作 | G41: 范慧明 | H41: JS000019833 | I41: 工单消耗 | J41: 75 | K41: 0 | L41: 0 | M41: 100 | N41: 0 | O41: 0 | P41: 129.5 | Q41: 0 | R41: 175 | S41: 0 | T41: 0 | U41: 0 | V41: 0 | W41: 0 | X41: 0 | Y41: 479.5
A42: 西北大区部 | B42: 兰州服务中心 | C42: 兰州办事处 | D42: 庆阳加美电器服务有限公司 | E42: 分支机构 | F42: 合作 | G42: 钱琪超 | H42: JS000037603 | I42: 工单消耗 | J42: 0 | K42: 0 | L42: 0 | M42: 400 | N42: 0 | O42: 0 | P42: 42 | Q42: 0 | R42: 175 | S42: 0 | T42: 0 | U42: 0 | V42: 0 | W42: 0 | X42: 0 | Y42: 617
A43: 西北大区部 | B43: 呼和浩特服务中心 | C43: 呼和浩特办事处 | D43: 呼和浩特市回民区彦辰家电维修经营部 | E43: 分支机构 | F43: 合作 | G43: 侯慧忠 | H43: JS000015636 | I43: 工单消耗 | J43: 0 | K43: 0 | L43: 0 | M43: 300 | N43: 245 | O43: 0 | P43: 35 | Q43: 0 | R43: 231 | S43: 42 | T43: 0 | U43: 0 | V43: 0 | W43: 0 | X43: 0 | Y43: 853
A44: 西北大区部 | B44: 兰州服务中心 | C44: 兰州办事处 | D44: 康县乐享劳务服务有限公司 | E44: 分支机构 | F44: 合作 | G44: 石礼勇 | H44: JS000021926 | I44: 工单消耗 | J44: 0 | K44: 0 | L44: 0 | M44: 0 | N44: 0 | O44: 0 | P44: 0 | Q44: 0 | R44: 0 | S44: 0 | T44: 0 | U44: 0 | V44: 0 | W44: 0 | X44: 0 | Y44: 0
... A51: 西北大区部 | B51: 兰州服务中心 | C51: 兰州办事处 | D51: 甘谷县磐安建元厨卫商行 | E51: 分支机构 | F51: 合作 | G51: 石建元 | H51: JS000027823 | I51: 工单消耗 | J51: 0 | K51: 0 | L51: 0 | M51: 0 | N51: 0 | O51: 0 | P51: 42 | Q51: 0 | R51: 0 | S51: 0 | T51: 0 | U51: 0 | V51: 0 | W51: 0 | X51: 0 | Y51: 42
A52: 西北大区部 | B52: 兰州服务中心 | C52: 兰州办事处 | D52: 天水晨旺家电服务有限公司 | E52: 分支机构 | F52: 合作 | I52: 网点买断 | J52: 0 | K52: 0 | L52: 0 | M52: 0 | N52: 0 | O52: 3702.24 | P52: 0 | Q52: 0 | R52: 0 | S52: 0 | T52: 0 | U52: 0 | V52: 1004 | W52: 0 | X52: 0 | Y52: 4706.24
A53: 西北大区部 | B53: 乌鲁木齐服务中心 | C53: 新疆办事处 | D53: 昌吉市井清家电维修服务部 | E53: 分支机构 | F53: 合作 | I53: 网点买断 | J53: 0 | K53: 0 | L53: 0 | M53: 0 | N53: 0 | O53: 6123.15 | P53: 0 | Q53: 0 | R53: 0 | S53: 0 | T53: 0 | U53: 0 | V53: 1795 | W53: 0 | X53: 0 | Y53: 7918.15
A54: 西北大区部 | B54: 宁夏服务中心 | C54: 宁夏办事处 | D54: 贺兰县家玺家电维修部 | E54: 分支机构 | F54: 合作 | G54: 蒋波 | H54: JS000041197 | I54: 工单消耗 | J54: 1560 | K54: 0 | L54: 0 | M54: 0 | N54: 0 | O54: 0 | P54: 0 | Q54: 0 | R54: 0 | S54: 0 | T54: 0 | U54: 0 | V54: 0 | W54: 0 | X54: 0 | Y54: 1560
A55: 西北大区部 | B55: 乌鲁木齐服务中心 | C55: 新疆办事处 | D55: 昌吉市井清家电维修服务部 | E55: 分支机构 | F55: 合作 | G55: 王忠义 | H55: JS000008869 | I55: 工单消耗 | J55: 0 | K55: 343.5 | L55: 46 | M55: 800 | N55: 245 | O55: 0 | P55: 35 | Q55: 0 | R55: 175 | S55: 28 | T55: 0 | U55: 0 | V55: 0 | W55: 0 | X55: 0 | Y55: 1672.5
A56: 西北大区部 | B56: 乌鲁木齐服务中心 | C56: 新疆办事处 | D56: 新疆服务中心零售网点 | E56: 分支机构 | F56: 自营 | G56: 贺江新 | H56: JS000005536 | I56: 工单消耗 | J56: 1782 | K56: 0 | L56: 0 | M56: 0 | N56: 0 | O56: 0 | P56: 0 | Q56: 0 | R56: 0 | S56: 0 | T56: 0 | U56: 0 | V56: 0 | W56: 0 | X56: 0 | Y56: 1782
A57: 西北大区部 | B57: 兰州服务中心 | C57: 西宁办事处 | D57: 西宁广仁技术服务有限公司 | E57: 分支机构 | F57: 合作 | G57: 孙延国 | H57: JS000023906 | I57: 工单消耗 | J57: 0 | K57: 1030.5 | L57: 0 | M57: 200 | N57: 0 | O57: 0 | P57: 94.5 | Q57: 0 | R57: 304.5 | S57: 0 | T57: 0 | U57: 0 | V57: 0 | W57: 0 | X57: 0 | Y57: 1629.5
A58: 西北大区部 | B58: 宁夏服务中心 | C58: 宁夏办事处 | D58: 银川服务站 | E58: 分支机构 | F58: 自营 | G58: 尹海军 | H58: JS000002894 | I58: 工单消耗 | J58: 319 | K58: 0 | L58: 256 | M58: 1080 | N58: 0 | O58: 160 | P58: 0 | Q58: 0 | R58: 275 | S58: 40 | T58: 0 | U58: 0 | V58: 0 | W58: 0 | X58: 0 | Y58: 2130
A59: 西北大区部 | B59: 包头服务中心 | C59: 包头办事处 | D59: 海勃湾区福心圆家电维修服务部（个体工商户） | E59: 分支机构 | F59: 合作 | G59: 蔺猛 | H59: JS000026834 | I59: 工单消耗 | J59: 0 | K59: 0 | L59: 95 | M59: 500 | N59: 0 | O59: 0 | P59: 0 | Q59: 0 | R59: 322 | S59: 0 | T59: 0 | U59: 0 | V59: 0 | W59: 0 | X59: 0 | Y59: 917
A60: 西北大区部 | B60: 包头服务中心 | C60: 包头办事处 | D60: 包头服务中心零售网点 | E60: 分支机构 | F60: 自营 | G60: 连勇峰 | H60: JS000005657 | I60: 工单消耗 | J60: 0 | K60: 0 | L60: 159 | M60: 180 | N60: 0 | O60: 0 | P60: 0 | Q60: 0 | R60: 700 | S60: 0 | T60: 0 | U60: 50 | V60: 0 | W60: 0 | X60: 0 | Y60: 1089
A61: 西北大区部 | B61: 乌鲁木齐服务中心 | C61: 新疆办事处 | D61: 库尔勒远祥家电维修部 | E61: 分支机构 | F61: 合作 | G61: 郭明中 | H61: JS000004986 | I61: 工单消耗 | J61: 0 | K61: 0 | L61: 255 | M61: 1200 | N61: 0 | O61: 0 | P61: 35 | Q61: 0 | R61: 437.5 | S61: 196 | T61: 0 | U61: 0 | V61: 0 | W61: 0 | X61: 0 | Y61: 2123.5
A62: 西北大区部 | B62: 包头服务中心 | C62: 包头办事处 | D62: 青山区厨小帮家电维修门店 | E62: 分支机构 | F62: 合作 | G62: 马玲 | H62: JS000014739 | I62: 工单消耗 | J62: 0 | K62: 0 | L62: 76 | M62: 0 | N62: 0 | O62: 0 | P62: 0 | Q62: 0 | R62: 140 | S62: 0 | T62: 0 | U62: 0 | V62: 0 | W62: 0 | X62: 0 | Y62: 216
A63: 西北大区部 | B63: 乌鲁木齐服务中心 | C63: 新疆办事处 | D63: 北屯市王金女家电维修店 | E63: 分支机构 | F63: 合作 | G63: 车攀宁 | H63: JS000039122 | I63: 工单消耗 | J63: 0 | K63: 0 | L63: 0 | M63: 700 | N63: 0 | O63: 0 | P63: 0 | Q63: 0 | R63: 245 | S63: 56 | T63: 0 | U63: 59.5 | V63: 0 | W63: 0 | X63: 0 | Y63: 1060.5
A64: 西北大区部 | B64: 乌鲁木齐服务中心 | C64: 新疆办事处 | D64: 阿克苏市零壹家电维修部 | E64: 分支机构 | F64: 合作 | G64: 张蒙光 | H64: JS000005116 | I64: 工单消耗 | J64: 0 | K64: 0 | L64: 0 | M64: 800 | N64: 0 | O64: 0 | P64: 28 | Q64: 0 | R64: 98 | S64: 0 | T64: 0 | U64: 0 | V64: 0 | W64: 0 | X64: 0 | Y64: 926
A65: 西北大区部 | B65: 包头服务中心 | C65: 包头办事处 | D65: 康巴什区中福家电维修服务部 | E65: 分支机构 | F65: 合作 | G65: 韩键 | H65: JS000019140 | I65: 工单消耗 | J65: 0 | K65: 0 | L65: 228 | M65: 1100 | N65: 0 | O65: 0 | P65: 105 | Q65: 0 | R65: 567 | S65: 0 | T65: 0 | U65: 0 | V65: 0 | W65: 0 | X65: 0 | Y65: 2000
... A79: 西北大区部 | B79: 宁夏服务中心 | C79: 宁夏办事处 | D79: 中宁县成城家政服务中心 | E79: 分支机构 | F79: 合作 | G79: 李亚成 | H79: JS000006439 | I79: 工单消耗 | J79: 0 | K79: 0 | L79: 0 | M79: 0 | N79: 0 | O79: 0 | P79: 0 | Q79: 0 | R79: 0 | S79: 0 | T79: 0 | U79: 0 | V79: 0 | W79: 0 | X79: 0 | Y79: 0
A80: 西北大区部 | B80: 包头服务中心 | C80: 包头办事处 | D80: 青山区厨小帮家电维修门店 | E80: 分支机构 | F80: 合作 | I80: 网点买断 | J80: 0 | K80: 0 | L80: 444 | M80: 0 | N80: 0 | O80: 408.21 | P80: 0 | Q80: 0 | R80: 0 | S80: 0 | T80: 0 | U80: 0 | V80: 44.4 | W80: 0 | X80: 0 | Y80: 896.61
A81: 西北大区部 | B81: 兰州服务中心 | C81: 西宁办事处 | D81: 西宁广仁技术服务有限公司 | E81: 分支机构 | F81: 合作 | I81: 网点买断 | J81: 0 | K81: 0 | L81: 40 | M81: 0 | N81: 0 | O81: 0 | P81: 0 | Q81: 0 | R81: 0 | S81: 0 | T81: 0 | U81: 0 | V81: 0 | W81: 0 | X81: 0 | Y81: 40
A82: 西北大区部 | B82: 宁夏服务中心 | C82: 宁夏办事处 | D82: 贺兰县家玺家电维修部 | E82: 分支机构 | F82: 合作 | I82: 网点买断 | J82: 0 | K82: 0 | L82: 436 | M82: 0 | N82: 0 | O82: 1846.82 | P82: 0 | Q82: 0 | R82: 0 | S82: 0 | T82: 0 | U82: 0 | V82: 133.2 | W82: 0 | X82: 0 | Y82: 2416.02
A83: 西北大区部 | B83: 乌鲁木齐服务中心 | C83: 新疆办事处 | D83: 库尔勒远祥家电维修部 | E83: 分支机构 | F83: 合作 | I83: 网点买断 | J83: 0 | K83: 0 | L83: 0 | M83: 0 | N83: 0 | O83: 408.21 | P83: 0 | Q83: 0 | R83: 0 | S83: 0 | T83: 0 | U83: 0 | V83: 222 | W83: 0 | X83: 0 | Y83: 630.21
A84: 西北大区部 | B84: 兰州服务中心 | C84: 兰州办事处 | D84: 西峰区二牛电器维修服务中心 | E84: 分支机构 | F84: 合作 | I84: 网点买断 | J84: 0 | K84: 0 | L84: 0 | M84: 0 | N84: 0 | O84: 1224.63 | P84: 0 | Q84: 0 | R84: 0 | S84: 0 | T84: 0 | U84: 0 | V84: 0 | W84: 0 | X84: 0 | Y84: 1224.63
A85: 西北大区部 | B85: 宁夏服务中心 | C85: 宁夏办事处 | D85: 贺兰县家玺家电维修部 | E85: 分支机构 | F85: 合作 | G85: 梁金堂 | H85: JS000020276 | I85: 工单消耗 | J85: 0 | K85: 2061 | L85: 0 | M85: 900 | N85: 0 | O85: 0 | P85: 0 | Q85: 0 | R85: 350 | S85: 10.5 | T85: 0 | U85: 0 | V85: 0 | W85: 0 | X85: 0 | Y85: 3321.5
A86: 西北大区部 | B86: 宁夏服务中心 | C86: 宁夏办事处 | D86: 永宁县杨和镇鑫界家电配送维修中心 | E86: 分支机构 | F86: 合作 | G86: 马宁 | H86: JS000046562 | I86: 工单消耗 | J86: 1350 | K86: 0 | L86: 0 | M86: 0 | N86: 0 | O86: 0 | P86: 0 | Q86: 0 | R86: 0 | S86: 0 | T86: 0 | U86: 0 | V86: 0 | W86: 0 | X86: 0 | Y86: 1350
A87: 西北大区部 | B87: 兰州服务中心 | C87: 兰州办事处 | D87: 七里河兴旺电器维修服务经营部 | E87: 分支机构 | F87: 合作 | G87: 周永红 | H87: JS000029057 | I87: 工单消耗 | J87: 225 | K87: 389.3 | L87: 16 | M87: 500 | N87: 0 | O87: 0 | P87: 84 | Q87: 0 | R87: 140 | S87: 0 | T87: 0 | U87: 0 | V87: 0 | W87: 0 | X87: 0 | Y87: 1354.3
A88: 西北大区部 | B88: 乌鲁木齐服务中心 | C88: 新疆办事处 | D88: 乌鲁木齐经济技术开发区（头屯河区）明瑞商务服务工作室 | E88: 分支机构 | F88: 合作 | G88: 苏勇强 | H88: JS000010906 | I88: 工单消耗 | J88: 0 | K88: 732.8 | L88: 76 | M88: 700 | N88: 0 | O88: 0 | P88: 255.5 | Q88: 0 | R88: 182 | S88: 84 | T88: 0 | U88: 0 | V88: 0 | W88: 0 | X88: 0 | Y88: 2030.3
A89: 西北大区部 | B89: 乌鲁木齐服务中心 | C89: 新疆办事处 | D89: 额敏县异兄家电维修店 | E89: 分支机构 | F89: 合作 | G89: 刘红民 | H89: JS000030841 | I89: 工单消耗 | J89: 0 | K89: 1465.6 | L89: 152 | M89: 700 | N89: 0 | O89: 0 | P89: 87.5 | Q89: 0 | R89: 245 | S89: 28 | T89: 0 | U89: 0 | V89: 0 | W89: 0 | X89: 0 | Y89: 2678.1
A90: 西北大区部 | B90: 乌鲁木齐服务中心 | C90: 新疆办事处 | D90: 乌鲁木齐经济技术开发区（头屯河区）明瑞商务服务工作室 | E90: 分支机构 | F90: 合作 | G90: 许东亚 | H90: JS000040323 | I90: 工单消耗 | J90: 0 | K90: 343.5 | L90: 1140 | M90: 900 | N90: 0 | O90: 0 | P90: 35 | Q90: 0 | R90: 210 | S90: 182 | T90: 0 | U90: 77 | V90: 0 | W90: 0 | X90: 0 | Y90: 2887.5
A91: 西北大区部 | B91: 呼和浩特服务中心 | C91: 呼和浩特办事处 | D91: 呼和浩特服务中心零售网点 | E91: 分支机构 | F91: 自营 | G91: 贾义 | H91: JS000005164 | I91: 工单消耗 | J91: 0 | K91: 0 | L91: 128 | M91: 180 | N91: 0 | O91: 0 | P91: 170 | Q91: 0 | R91: 250 | S91: 60 | T91: 0 | U91: 0 | V91: 0 | W91: 0 | X91: 0 | Y91: 788
A92: 西北大区部 | B92: 包头服务中心 | C92: 包头办事处 | D92: 伊金霍洛旗刘庆春电器店 | E92: 分支机构 | F92: 合作 | G92: 李勇 | H92: JS000028758 | I92: 工单消耗 | J92: 0 | K92: 0 | L92: 0 | M92: 100 | N92: 0 | O92: 0 | P92: 35 | Q92: 0 | R92: 280 | S92: 0 | T92: 0 | U92: 0 | V92: 0 | W92: 0 | X92: 0 | Y92: 415
A93: 西北大区部 | B93: 呼和浩特服务中心 | C93: 呼和浩特办事处 | D93: 土默特左旗金誉良电气安装服务部 | E93: 分支机构 | F93: 合作 | G93: 刘晓丰 | H93: JS000029708 | I93: 工单消耗 | J93: 0 | K93: 0 | L93: 0 | M93: 500 | N93: 0 | O93: 0 | P93: 24.5 | Q93: 0 | R93: 399 | S93: 84 | T93: 0 | U93: 0 | V93: 0 | W93: 0 | X93: 0 | Y93: 1007.5
A94: 西北大区部 | B94: 宁夏服务中心 | C94: 宁夏办事处 | D94: 永宁县杨和镇易玖利家电服务部 | E94: 分支机构 | F94: 合作 | G94: 张凯祥 | H94: JS000013384 | I94: 工单消耗 | J94: 0 | K94: 0 | L94: 0 | M94: 900 | N94: 0 | O94: 0 | P94: 0 | Q94: 0 | R94: 425.6 | S94: 0 | T94: 0 | U94: 0 | V94: 0 | W94: 0 | X94: 0 | Y94: 1325.6
A95: 西北大区部 | B95: 呼和浩特服务中心 | C95: 呼和浩特办事处 | D95: 呼和浩特市回民区彦辰家电维修经营部 | E95: 分支机构 | F95: 合作 | G95: 王鹏 | H95: JS000043198 | I95: 工单消耗 | J95: 0 | K95: 0 | L95: 0 | M95: 300 | N95: 245 | O95: 0 | P95: 35 | Q95: 0 | R95: 322 | S95: 84 | T95: 0 | U95: 0 | V95: 0 | W95: 0 | X95: 0 | Y95: 986
A96: 西北大区部 | B96: 兰州服务中心 | C96: 兰州办事处 | D96: 永登鑫元家电维修部（个体工商户） | E96: 分支机构 | F96: 合作 | G96: 张天珍 | H96: JS000019822 | I96: 工单消耗 | J96: 0 | K96: 0 | L96: 199 | M96: 400 | N96: 0 | O96: 0 | P96: 0 | Q96: 0 | R96: 74 | S96: 56 | T96: 0 | U96: 0 | V96: 0 | W96: 0 | X96: 0 | Y96: 729
... A161: 西北大区部 | B161: 兰州服务中心 | C161: 兰州办事处 | D161: 正宁县贵博厨具店 | E161: 分支机构 | F161: 合作 | G161: 赵贵博 | H161: JS000000431 | I161: 工单消耗 | J161: 0 | K161: 0 | L161: 0 | M161: 0 | N161: 0 | O161: 0 | P161: 0 | Q161: 0 | R161: 0 | S161: 0 | T161: 0 | U161: 0 | V161: 0 | W161: 0 | X161: 0 | Y161: 0
A162: 西北大区部 | B162: 宁夏服务中心 | C162: 宁夏办事处 | D162: 海原县宏志家电维修中心（个体工商户） | E162: 分支机构 | F162: 合作 | I162: 网点买断 | J162: 0 | K162: 0 | L162: 76 | M162: 0 | N162: 0 | O162: 0 | P162: 0 | Q162: 0 | R162: 136 | S162: 0 | T162: 0 | U162: 0 | V162: 0 | W162: 0 | X162: 0 | Y162: 212
A163: 西北大区部 | B163: 乌鲁木齐服务中心 | C163: 新疆办事处 | D163: 额敏县异兄家电维修店 | E163: 分支机构 | F163: 合作 | G163: 张奇 | H163: JS000013528 | I163: 工单消耗 | J163: 1350 | K163: 0 | L163: 0 | M163: 0 | N163: 0 | O163: 0 | P163: 0 | Q163: 0 | R163: 0 | S163: 0 | T163: 0 | U163: 0 | V163: 0 | W163: 0 | X163: 0 | Y163: 1350
A164: 西北大区部 | B164: 宁夏服务中心 | C164: 宁夏办事处 | D164: 永宁县杨和镇中天家电维修部 | E164: 分支机构 | F164: 合作 | G164: 薛雷 | H164: JS000020413 | I164: 工单消耗 | J164: 0 | K164: 647.8 | L164: 0 | M164: 700 | N164: 196 | O164: 0 | P164: 108.5 | Q164: 0 | R164: 187.6 | S164: 3.5 | T164: 0 | U164: 0 | V164: 0 | W164: 0 | X164: 0 | Y164: 1843.4
A165: 西北大区部 | B165: 呼和浩特服务中心 | C165: 呼和浩特办事处 | D165: 呼和浩特市凯多丰电器服务维修有限公司 | E165: 分支机构 | F165: 合作 | G165: 陈国强 | H165: JS000038671 | I165: 工单消耗 | J165: 750 | K165: 0 | L165: 0 | M165: 0 | N165: 0 | O165: 0 | P165: 105 | Q165: 0 | R165: 0 | S165: 0 | T165: 0 | U165: 0 | V165: 0 | W165: 0 | X165: 0 | Y165: 855
A166: 西北大区部 | B166: 包头服务中心 | C166: 包头办事处 | D166: 包头服务中心零售网点 | E166: 分支机构 | F166: 自营 | G166: 张红峰 | H166: JS000001125 | I166: 工单消耗 | J166: 928 | K166: 0 | L166: 0 | M166: 0 | N166: 0 | O166: 0 | P166: 50 | Q166: 0 | R166: 0 | S166: 0 | T166: 0 | U166: 0 | V166: 0 | W166: 0 | X166: 0 | Y166: 978
A167: 西北大区部 | B167: 兰州服务中心 | C167: 兰州办事处 | D167: 七里河兴旺电器维修服务经营部 | E167: 分支机构 | F167: 合作 | G167: 王立杰 | H167: JS000035630 | I167: 工单消耗 | J167: 750 | K167: 343.5 | L167: 0 | M167: 500 | N167: 0 | O167: 0 | P167: 0 | Q167: 0 | R167: 126 | S167: 0 | T167: 0 | U167: 0 | V167: 0 | W167: 0 | X167: 0 | Y167: 1719.5
A168: 西北大区部 | B168: 乌鲁木齐服务中心 | C168: 新疆办事处 | D168: 昌吉市井清家电维修服务部 | E168: 分支机构 | F168: 合作 | G168: 张历辉 | H168: JS000013589 | I168: 工单消耗 | J168: 0 | K168: 343.5 | L168: 0 | M168: 400 | N168: 0 | O168: 0 | P168: 28 | Q168: 0 | R168: 70 | S168: 0 | T168: 0 | U168: 0 | V168: 0 | W168: 0 | X168: 0 | Y168: 841.5
A169: 西北大区部 | B169: 乌鲁木齐服务中心 | C169: 新疆办事处 | D169: 库车金润电器商行 | E169: 分支机构 | F169: 合作 | G169: 贾晓璐 | H169: JS000018570 | I169: 工单消耗 | J169: 0 | K169: 389.3 | L169: 0 | M169: 0 | N169: 0 | O169: 0 | P169: 0 | Q169: 0 | R169: 0 | S169: 0 | T169: 0 | U169: 0 | V169: 0 | W169: 0 | X169: 0 | Y169: 389.3
A170: 西北大区部 | B170: 宁夏服务中心 | C170: 宁夏办事处 | D170: 永宁县杨和镇鑫界家电配送维修中心 | E170: 分支机构 | F170: 合作 | G170: 仇祥 | H170: JS000011598 | I170: 工单消耗 | J170: 0 | K170: 343.5 | L170: 0 | M170: 600 | N170: 0 | O170: 0 | P170: 38.5 | Q170: 0 | R170: 196 | S170: 17.5 | T170: 0 | U170: 17.5 | V170: 0 | W170: 0 | X170: 0 | Y170: 1213
A171: 西北大区部 | B171: 宁夏服务中心 | C171: 宁夏办事处 | D171: 银川服务站 | E171: 分支机构 | F171: 自营 | G171: 马少宁 | H171: JS000000047 | I171: 工单消耗 | J171: 0 | K171: 916 | L171: 1710 | M171: 360 | N171: 0 | O171: 0 | P171: 225 | Q171: 0 | R171: 400 | S171: 620 | T171: 0 | U171: 0 | V171: 0 | W171: 0 | X171: 0 | Y171: 4231
A172: 西北大区部 | B172: 乌鲁木齐服务中心 | C172: 新疆办事处 | D172: 水磨沟区华凌市场卓尚良思家用电器经销部 | E172: 分支机构 | F172: 合作 | G172: 赵维碧 | H172: JS000039098 | I172: 工单消耗 | J172: 0 | K172: 343.5 | L172: 0 | M172: 300 | N172: 0 | O172: 0 | P172: 325.5 | Q172: 0 | R172: 140 | S172: 28 | T172: 0 | U172: 0 | V172: 0 | W172: 0 | X172: 0 | Y172: 1137
A173: 西北大区部 | B173: 乌鲁木齐服务中心 | C173: 新疆办事处 | D173: 乌鲁木齐经济技术开发区（头屯河区）明瑞商务服务工作室 | E173: 分支机构 | F173: 合作 | G173: 项光普 | H173: JS000016577 | I173: 工单消耗 | J173: 0 | K173: 389.3 | L173: 68 | M173: 700 | N173: 0 | O173: 0 | P173: 255.5 | Q173: 0 | R173: 280 | S173: 140 | T173: 0 | U173: 0 | V173: 0 | W173: 0 | X173: 0 | Y173: 1832.8
A174: 西北大区部 | B174: 兰州服务中心 | C174: 兰州办事处 | D174: 西峰区二牛电器维修服务中心 | E174: 分支机构 | F174: 合作 | G174: 胡鹏飞 | H174: JS000040929 | I174: 工单消耗 | J174: 0 | K174: 0 | L174: 0 | M174: 200 | N174: 0 | O174: 0 | P174: 0 | Q174: 0 | R174: 70 | S174: 0 | T174: 0 | U174: 0 | V174: 0 | W174: 0 | X174: 0 | Y174: 270
... A195: 西北大区部 | B195: 乌鲁木齐服务中心 | C195: 新疆办事处 | D195: 莎车县雅姿装饰生活馆 | E195: 分支机构 | F195: 合作 | G195: 阿布力孜·吐尔逊 | H195: JS000035440 | I195: 工单消耗 | J195: 0 | K195: 0 | L195: 0 | M195: 0 | N195: 0 | O195: 0 | P195: 35 | Q195: 0 | R195: 35 | S195: 0 | T195: 0 | U195: 0 | V195: 0 | W195: 0 | X195: 0 | Y195: 70
A196: 西北大区部 | B196: 宁夏服务中心 | C196: 宁夏办事处 | D196: 永宁县杨和镇鑫界家电配送维修中心 | E196: 分支机构 | F196: 合作 | I196: 网点买断 | J196: 0 | K196: 0 | L196: 764 | M196: 0 | N196: 0 | O196: 100.16 | P196: 0 | Q196: 0 | R196: 0 | S196: 0 | T196: 0 | U196: 0 | V196: 0 | W196: 0 | X196: 0 | Y196: 864.16
A197: 西北大区部 | B197: 乌鲁木齐服务中心 | C197: 新疆办事处 | D197: 库尔勒泽玉家电维修服务中心（个体工商户） | E197: 分支机构 | F197: 合作 | I197: 网点买断 | J197: 0 | K197: 0 | L197: 0 | M197: 0 | N197: 0 | O197: 408.21 | P197: 0 | Q197: 0 | R197: 0 | S197: 0 | T197: 0 | U197: 0 | V197: 222 | W197: 0 | X197: 0 | Y197: 630.21
A198: 西北大区部 | B198: 乌鲁木齐服务中心 | C198: 新疆办事处 | D198: 乌鲁木齐经济技术开发区（头屯河区）明瑞商务服务工作室 | E198: 分支机构 | F198: 合作 | G198: 张小强 | H198: JS000026680 | I198: 工单消耗 | J198: 1275 | K198: 0 | L198: 0 | M198: 0 | N198: 0 | O198: 0 | P198: 35 | Q198: 0 | R198: 0 | S198: 0 | T198: 0 | U198: 0 | V198: 0 | W198: 0 | X198: 0 | Y198: 1310
A199: 西北大区部 | B199: 宁夏服务中心 | C199: 宁夏办事处 | D199: 永宁县杨和镇鑫界家电配送维修中心 | E199: 分支机构 | F199: 合作 | G199: 郭瑞 | H199: JS000047787 | I199: 工单消耗 | J199: 1200 | K199: 0 | L199: 0 | M199: 0 | N199: 0 | O199: 0 | P199: 0 | Q199: 0 | R199: 0 | S199: 0 | T199: 0 | U199: 0 | V199: 0 | W199: 0 | X199: 0 | Y199: 1200
A200: 西北大区部 | B200: 乌鲁木齐服务中心 | C200: 新疆办事处 | D200: 伊宁边境经济合作区谢振升家电维修服务部 | E200: 分支机构 | F200: 合作 | G200: 刘军伍 | H200: JS000047221 | I200: 工单消耗 | J200: 150 | K200: 0 | L200: 0 | M200: 0 | N200: 0 | O200: 0 | P200: 0 | Q200: 0 | R200: 0 | S200: 0 | T200: 0 | U200: 0 | V200: 0 | W200: 0 | X200: 0 | Y200: 150
A201: 西北大区部 | B201: 乌鲁木齐服务中心 | C201: 新疆办事处 | D201: 北屯市王金女家电维修店 | E201: 分支机构 | F201: 合作 | G201: 王伟俊 | H201: JS000035718 | I201: 工单消耗 | J201: 0 | K201: 389.3 | L201: 0 | M201: 900 | N201: 0 | O201: 0 | P201: 203 | Q201: 0 | R201: 280 | S201: 56 | T201: 0 | U201: 0 | V201: 0 | W201: 0 | X201: 0 | Y201: 1828.3
A202: 西北大区部 | B202: 兰州服务中心 | C202: 西宁办事处 | D202: 青海心自由呼吸环保科技有限公司 | E202: 分支机构 | F202: 合作 | G202: 贲红康 | H202: JS000038808 | I202: 工单消耗 | J202: 0 | K202: 343.5 | L202: 0 | M202: 0 | N202: 0 | O202: 0 | P202: 0 | Q202: 0 | R202: 0 | S202: 0 | T202: 0 | U202: 0 | V202: 0 | W202: 0 | X202: 0 | Y202: 343.5
A203: 西北大区部 | B203: 乌鲁木齐服务中心 | C203: 新疆办事处 | D203: 额敏县异兄家电维修店 | E203: 分支机构 | F203: 合作 | G203: 张雷杰 | H203: JS000002691 | I203: 工单消耗 | J203: 0 | K203: 0 | L203: 0 | M203: 400 | N203: 0 | O203: 0 | P203: 122.5 | Q203: 0 | R203: 70 | S203: 0 | T203: 0 | U203: 0 | V203: 0 | W203: 0 | X203: 0 | Y203: 592.5
A204: 西北大区部 | B204: 包头服务中心 | C204: 包头办事处 | D204: 昆都仑区王宏明家电安装部 | E204: 分支机构 | F204: 合作 | G204: 王宏明 | H204: JS000019832 | I204: 工单消耗 | J204: 0 | K204: 0 | L204: 40 | M204: 100 | N204: 0 | O204: 0 | P204: 0 | Q204: 0 | R204: 280 | S204: 0 | T204: 0 | U204: 52.5 | V204: 0 | W204: 0 | X204: 0 | Y204: 472.5
A205: 西北大区部 | B205: 包头服务中心 | C205: 包头办事处 | D205: 东胜区赵全笑家电维修服务部 | E205: 分支机构 | F205: 合作 | G205: 赵全笑 | H205: JS000003330 | I205: 工单消耗 | J205: 0 | K205: 0 | L205: 1220 | M205: 1100 | N205: 0 | O205: 0 | P205: 52.5 | Q205: 0 | R205: 840 | S205: 196 | T205: 0 | U205: 17.5 | V205: 0 | W205: 0 | X205: 0 | Y205: 3426
A206: 西北大区部 | B206: 宁夏服务中心 | C206: 宁夏办事处 | D206: 永宁县杨和镇易玖利家电服务部 | E206: 分支机构 | F206: 合作 | G206: 周龙 | H206: JS000008377 | I206: 工单消耗 | J206: 0 | K206: 0 | L206: 0 | M206: 1000 | N206: 0 | O206: 0 | P206: 14 | Q206: 0 | R206: 77 | S206: 0 | T206: 0 | U206: 0 | V206: 0 | W206: 0 | X206: 0 | Y206: 1091
A207: 西北大区部 | B207: 兰州服务中心 | C207: 兰州办事处 | D207: 七里河兴旺电器维修服务经营部 | E207: 分支机构 | F207: 合作 | G207: 王龙龙 | H207: JS000038761 | I207: 工单消耗 | J207: 0 | K207: 0 | L207: 0 | M207: 100 | N207: 0 | O207: 0 | P207: 0 | Q207: 0 | R207: 0 | S207: 0 | T207: 0 | U207: 0 | V207: 0 | W207: 0 | X207: 0 | Y207: 100
A208: 西北大区部 | B208: 乌鲁木齐服务中心 | C208: 新疆办事处 | D208: 北屯市王金女家电维修店 | E208: 分支机构 | F208: 合作 | G208: 赵飞飞 | H208: JS000030840 | I208: 工单消耗 | J208: 0 | K208: 0 | L208: 160 | M208: 600 | N208: 0 | O208: 0 | P208: 28 | Q208: 0 | R208: 343 | S208: 112 | T208: 0 | U208: 0 | V208: 0 | W208: 0 | X208: 0 | Y208: 1243
A209: 西北大区部 | B209: 乌鲁木齐服务中心 | C209: 新疆办事处 | D209: 水磨沟区华凌市场卓尚良思家用电器经销部 | E209: 分支机构 | F209: 合作 | G209: 谷鹏 | H209: JS000024046 | I209: 工单消耗 | J209: 0 | K209: 0 | L209: 202 | M209: 500 | N209: 49 | O209: 0 | P209: 388.5 | Q209: 0 | R209: 210 | S209: 14 | T209: 0 | U209: 35 | V209: 0 | W209: 0 | X209: 0 | Y209: 1398.5
... A229: 西北大区部 | B229: 兰州服务中心 | C229: 西宁办事处 | D229: 敦煌市慧科电子科技服务部 | E229: 分支机构 | F229: 合作 | G229: 融成德 | H229: JS000004426 | I229: 工单消耗 | J229: 0 | K229: 0 | L229: 0 | M229: 0 | N229: 0 | O229: 0 | P229: 0 | Q229: 0 | R229: 0 | S229: 0 | T229: 0 | U229: 0 | V229: 0 | W229: 0 | X229: 0 | Y229: 0
A230: 西北大区部 | B230: 宁夏服务中心 | C230: 宁夏办事处 | D230: 永宁县杨和镇易玖利家电服务部 | E230: 分支机构 | F230: 合作 | I230: 网点买断 | J230: 0 | K230: 0 | L230: 1088 | M230: 0 | N230: 0 | O230: 63.36 | P230: 0 | Q230: 0 | R230: 0 | S230: 0 | T230: 0 | U230: 0 | V230: 0 | W230: 0 | X230: 0 | Y230: 1151.36
A231: 西北大区部 | B231: 宁夏服务中心 | C231: 宁夏办事处 | D231: 永宁县杨和镇中天家电维修部 | E231: 分支机构 | F231: 合作 | I231: 网点买断 | J231: 0 | K231: 0 | L231: 387 | M231: 0 | N231: 0 | O231: 179.36 | P231: 0 | Q231: 0 | R231: 0 | S231: 0 | T231: 0 | U231: 0 | V231: 0 | W231: 0 | X231: 0 | Y231: 566.36

Sheet 年度服务产品
A1: 大区部 | B1: 办事处 | C1: 46023 | H1: 46054 | M1: 46082 | R1: 46113 | W1: 46143 | AB1: 46174 | AG1: 46204 | AL1: 2026年全年
C2: 当月目标 | D2: 当月实绩 | E2: 当月完成率 | F2: 25年实绩 | G2: 同比 | H2: 当月目标 | I2: 当月实绩 | J2: 当月完成率 | K2: 25年实绩 | L2: 同比 | M2: 当月目标 | N2: 当月实绩 | O2: 当月完成率 | P2: 25年实绩 | Q2: 同比 | R2: 当月目标 | S2: 当月实绩 | T2: 当月完成率 | U2: 25年实绩 | V2: 同比 | W2: 当月目标 | X2: 当月实绩 | Y2: 当月完成率 | Z2: 25年实绩 | AA2: 同比 | AB2: 当月目标 | AC2: 当月实绩 | AD2: 当月完成率 | AE2: 25年实绩 | AF2: 同比 | AG2: 当月目标 | AH2: 当月实绩 | AI2: 当月完成率 | AJ2: 25年实绩 | AK2: 同比 | AL2: 累计实绩 | AM2: 累计目标 | AN2: 累计完成率 | AO2: 全年目标 | AP2: 年度完成进度 | AQ2: 25年实绩 | AR2: 同比
A3: 西北大区部 | B3: 包头 | C3: 3.9 | D3: 5.757736 | E3: =D3/C3 -> 1.4763426 | F3: 4.671894 | G3: =(D3-F3)/F3 -> 0.23242008 | H3: 1.17 | I3: 2.7852 | J3: =I3/H3 -> 2.3805128 | K3: 1.46945 | L3: =(I3-K3)/K3 -> 0.89540304 | M3: 2.34 | N3: 1.53389 | O3: =N3/M3 -> 0.65550855 | P3: 2.64943 | Q3: =(N3-P3)/P3 -> -0.42104906 | R3: 2.73 | S3: 3.045961 | T3: =S3/R3 -> 1.1157366 | U3: 2.97402 | V3: =(S3-U3)/U3 -> 0.024189817 | W3: 2.73 | X3: 3.050349 | Y3: =X3/W3 -> 1.117344 | Z3: 2.987746 | AA3: =(X3-Z3)/Z3 -> 0.020953254 | AB3: 2.73 | AC3: 3.391281 | AD3: =AC3/AB3 -> 1.2422275 | AE3: 2.980144 | AF3: =(AC3-AE3)/AE3 -> 0.13795877 | AG3: 3.51 | AH3: 3.235077 | AI3: =AH3/AG3 -> 0.92167436 | AL3: =D3+I3+N3+S3+X3+AC3+AH3 -> 22.799494 | AM3: =C3+H3+M3+R3+W3+AB3+AG3 -> 19.11 | AN3: =AL3/AM3 -> 1.1930661 | AO3: 39 | AP3: =AL3/AO3 -> 0.58460241 | AQ3: =F3+K3+P3+U3+Z3+AE3 -> 17.732684 | AR3: =(AL3-AQ3)/AQ3 -> 0.28573283
A4: 西北大区部 | B4: 呼和浩特 | C4: 3.6 | D4: 4.635312 | E4: =D4/C4 -> 1.2875867 | F4: 5.579199 | G4: =(D4-F4)/F4 -> -0.16917966 | H4: 1.08 | I4: 2.74716 | J4: =I4/H4 -> 2.5436667 | K4: 1.81487 | L4: =(I4-K4)/K4 -> 0.5136952 | M4: 2.16 | N4: 1.904714 | O4: =N4/M4 -> 0.88181204 | P4: 1.82954 | Q4: =(N4-P4)/P4 -> 0.041089017 | R4: 2.52 | S4: 2.701961 | T4: =S4/R4 -> 1.0722067 | U4: 3.002846 | V4: =(S4-U4)/U4 -> -0.10019994 | W4: 2.52 | X4: 2.845045 | Y4: =X4/W4 -> 1.1289861 | Z4: 2.573815 | AA4: =(X4-Z4)/Z4 -> 0.10538053 | AB4: 2.52 | AC4: 3.688113 | AD4: =AC4/AB4 -> 1.4635369 | AE4: 3.05464 | AF4: =(AC4-AE4)/AE4 -> 0.20738058 | AG4: 3.24 | AH4: 3.704106 | AI4: =AH4/AG4 -> 1.1432426 | AL4: =D4+I4+N4+S4+X4+AC4+AH4 -> 22.226411 | AM4: =C4+H4+M4+R4+W4+AB4+AG4 -> 17.64 | AN4: =AL4/AM4 -> 1.2600006 | AO4: 36 | AP4: =AL4/AO4 -> 0.61740031 | AQ4: =F4+K4+P4+U4+Z4+AE4 -> 17.85491 | AR4: =(AL4-AQ4)/AQ4 -> 0.24483467
A5: 西北大区部 | B5: 兰州 | C5: 9.3 | D5: 8.900277 | E5: =D5/C5 -> 0.95701903 | F5: 10.708775 | G5: =(D5-F5)/F5 -> -0.16888001 | H5: 2.79 | I5: 4.416661 | J5: =I5/H5 -> 1.5830326 | K5: 2.49787 | L5: =(I5-K5)/K5 -> 0.76817088 | M5: 5.58 | N5: 3.39736 | O5: =N5/M5 -> 0.60884588 | P5: 8.064191 | Q5: =(N5-P5)/P5 -> -0.57871038 | R5: 6.51 | S5: 8.06882 | T5: =S5/R5 -> 1.2394501 | U5: 7.010676 | V5: =(S5-U5)/U5 -> 0.15093323 | W5: 6.51 | X5: 6.310425 | Y5: =X5/W5 -> 0.96934332 | Z5: 8.470535 | AA5: =(X5-Z5)/Z5 -> -0.25501459 | AB5: 6.51 | AC5: 8.198339 | AD5: =AC5/AB5 -> 1.2593455 | AE5: 9.095664 | AF5: =(AC5-AE5)/AE5 -> -0.09865415 | AG5: 8.37 | AH5: 6.801145 | AI5: =AH5/AG5 -> 0.81256213 | AL5: =D5+I5+N5+S5+X5+AC5+AH5 -> 46.093027 | AM5: =C5+H5+M5+R5+W5+AB5+AG5 -> 45.57 | AN5: =AL5/AM5 -> 1.0114774 | AO5: 93 | AP5: =AL5/AO5 -> 0.49562395 | AQ5: =F5+K5+P5+U5+Z5+AE5 -> 45.847711 | AR5: =(AL5-AQ5)/AQ5 -> 0.0053506706
A6: 西北大区部 | B6: 宁夏 | C6: 12.4 | D6: 17.746097 | E6: =D6/C6 -> 1.4311369 | F6: 8.856446 | G6: =(D6-F6)/F6 -> 1.0037492 | H6: 3.72 | I6: 6.454476 | J6: =I6/H6 -> 1.7350742 | K6: 7.101315 | L6: =(I6-K6)/K6 -> -0.091087214 | M6: 7.44 | N6: 8.23321 | O6: =N6/M6 -> 1.1066142 | P6: 9.561202 | Q6: =(N6-P6)/P6 -> -0.13889383 | R6: 8.68 | S6: 10.479549 | T6: =S6/R6 -> 1.2073213 | U6: 10.996595 | V6: =(S6-U6)/U6 -> -0.047018736 | W6: 8.68 | X6: 10.122982 | Y6: =X6/W6 -> 1.1662422 | Z6: 8.498806 | AA6: =(X6-Z6)/Z6 -> 0.19110637 | AB6: 8.68 | AC6: 11.695068 | AD6: =AC6/AB6 -> 1.3473581 | AE6: 8.282046 | AF6: =(AC6-AE6)/AE6 -> 0.41209889 | AG6: 11.16 | AH6: 10.771978 | AI6: =AH6/AG6 -> 0.965231 | AL6: =D6+I6+N6+S6+X6+AC6+AH6 -> 75.50336 | AM6: =C6+H6+M6+R6+W6+AB6+AG6 -> 60.76 | AN6: =AL6/AM6 -> 1.2426491 | AO6: 124 | AP6: =AL6/AO6 -> 0.60889806 | AQ6: =F6+K6+P6+U6+Z6+AE6 -> 53.29641 | AR6: =(AL6-AQ6)/AQ6 -> 0.41666878
A7: 西北大区部 | B7: 西宁 | C7: 1.6 | D7: 1.419026 | E7: =D7/C7 -> 0.88689125 | F7: 1.72054 | G7: =(D7-F7)/F7 -> -0.17524382 | H7: 0.48 | I7: 0.702906 | J7: =I7/H7 -> 1.4643875 | K7: 0.32261 | L7: =(I7-K7)/K7 -> 1.1788103 | M7: 0.96 | N7: 0.64391 | O7: =N7/M7 -> 0.67073958 | P7: 1.414816 | Q7: =(N7-P7)/P7 -> -0.54488075 | R7: 1.12 | S7: 1.231352 | T7: =S7/R7 -> 1.0994214 | U7: 1.094898 | V7: =(S7-U7)/U7 -> 0.12462713 | W7: 1.12 | X7: 1.008142 | Y7: =X7/W7 -> 0.90012679 | Z7: 0.91028 | AA7: =(X7-Z7)/Z7 -> 0.10750758 | AB7: 1.12 | AC7: 1.546508 | AD7: =AC7/AB7 -> 1.3808107 | AE7: 1.663517 | AF7: =(AC7-AE7)/AE7 -> -0.070338325 | AG7: 1.44 | AH7: 1.596426 | AI7: =AH7/AG7 -> 1.1086292 | AL7: =D7+I7+N7+S7+X7+AC7+AH7 -> 8.14827 | AM7: =C7+H7+M7+R7+W7+AB7+AG7 -> 7.84 | AN7: =AL7/AM7 -> 1.0393202 | AO7: 16 | AP7: =AL7/AO7 -> 0.50926688 | AQ7: =F7+K7+P7+U7+Z7+AE7 -> 7.126661 | AR7: =(AL7-AQ7)/AQ7 -> 0.1433503
A8: 西北大区部 | B8: 新疆 | C8: 18.7 | D8: 20.451412 | E8: =D8/C8 -> 1.0936584 | F8: 14.125654 | G8: =(D8-F8)/F8 -> 0.44782054 | H8: 5.61 | I8: 9.642696 | J8: =I8/H8 -> 1.7188406 | K8: 5.648997 | L8: =(I8-K8)/K8 -> 0.70697488 | M8: 11.22 | N8: 11.972986 | O8: =N8/M8 -> 1.0671111 | P8: 9.643096 | Q8: =(N8-P8)/P8 -> 0.24161224 | R8: 13.09 | S8: 12.45751 | T8: =S8/R8 -> 0.95168144 | U8: 15.05046 | V8: =(S8-U8)/U8 -> -0.17228377 | W8: 13.09 | X8: 14.324145 | Y8: =X8/W8 -> 1.0942815 | Z8: 14.522604 | AA8: =(X8-Z8)/Z8 -> -0.013665524 | AB8: 13.09 | AC8: 15.763418 | AD8: =AC8/AB8 -> 1.2042336 | AE8: 16.170911 | AF8: =(AC8-AE8)/AE8 -> -0.025199137 | AG8: 16.83 | AH8: 17.218253 | AI8: =AH8/AG8 -> 1.0230691 | AL8: =D8+I8+N8+S8+X8+AC8+AH8 -> 101.83042 | AM8: =C8+H8+M8+R8+W8+AB8+AG8 -> 91.63 | AN8: =AL8/AM8 -> 1.1113218 | AO8: 187 | AP8: =AL8/AO8 -> 0.5445477 | AQ8: =F8+K8+P8+U8+Z8+AE8 -> 75.161722 | AR8: =(AL8-AQ8)/AQ8 -> 0.35481755
A9: 西北大区部 | B9: 小计 | C9: 49.5 | D9: 58.90986 | E9: =D9/C9 -> 1.1900982 | F9: 45.662508 | G9: =(D9-F9)/F9 -> 0.29011442 | H9: 14.85 | I9: 26.749099 | J9: =I9/H9 -> 1.8012861 | K9: 18.855112 | L9: =(I9-K9)/K9 -> 0.41866561 | M9: =M3+M4+M5+M6+M7+M8 -> 29.7 | N9: 27.68607 | O9: =N9/M9 -> 0.93219091 | P9: 33.162275 | Q9: =(N9-P9)/P9 -> -0.16513357 | R9: 34.65 | S9: 37.985153 | T9: =S9/R9 -> 1.0962526 | U9: 40.129495 | V9: =(S9-U9)/U9 -> -0.053435559 | W9: 34.65 | X9: 37.661088 | Y9: =X9/W9 -> 1.0869001 | Z9: 37.963786 | AA9: =(X9-Z9)/Z9 -> -0.0079733354 | AB9: 34.65 | AC9: 44.282727 | AD9: =AC9/AB9 -> 1.2780008 | AE9: 41.246922 | AF9: =(AC9-AE9)/AE9 -> 0.073600765 | AG9: =SUM(AG3:AG8) -> 44.55 | AH9: =SUM(AH3:AH8) -> 43.326985 | AI9: =AH9/AG9 -> 0.97254736 | AL9: =D9+I9+N9+S9+X9+AC9+AH9 -> 276.60098 | AM9: =C9+H9+M9+R9+W9+AB9+AG9 -> 242.55 | AN9: =AL9/AM9 -> 1.1403875 | AO9: 495 | AP9: =AL9/AO9 -> 0.55878986 | AQ9: =F9+K9+P9+U9+Z9+AE9 -> 217.0201 | AR9: =(AL9-AQ9)/AQ9 -> 0.27454086

Sheet 年度三大爆品
A1: 大区部 | B1: 办事处 | C1: 46023 | F1: 46054 | I1: 46082 | L1: 46113 | O1: 46143 | R1: 46174 | U1: 46204 | X1: 2026全年
C2: 当月目标 | D2: 当月实绩 | E2: 当月完成率 | F2: 当月目标 | G2: 当月实绩 | H2: 当月完成率 | I2: 当月目标 | J2: 当月实绩 | K2: 当月完成率 | L2: 当月目标 | M2: 当月实绩 | N2: 当月完成率 | O2: 当月目标 | P2: 当月实绩 | Q2: 当月完成率 | R2: 当月目标 | S2: 当月实绩 | T2: 当月完成率 | U2: 当月目标 | V2: 当月实绩 | W2: 当月完成率 | X2: 累计实际 | Y2: 累计目标 | Z2: 累计完成率 | AA2: 全年目标 | AB2: 年度完成进度
A3: 西北大区部 | B3: 包头 | C3: 1.4 | D3: 2.8448 | E3: =D3/C3 -> 2.032 | F3: 0.42 | G3: 1.9418 | H3: =G3/F3 -> 4.6233333 | I3: 0.84 | J3: 0.4405 | K3: =J3/I3 -> 0.52440476 | L3: 0.98 | M3: 0.9808 | N3: =M3/L3 -> 1.0008163 | O3: 0.98 | P3: 0.8872 | Q3: =P3/O3 -> 0.90530612 | R3: 0.98 | S3: 1.0613 | T3: =S3/R3 -> 1.0829592 | U3: 1.26 | V3: 0.9251 | W3: =V3/U3 -> 0.73420635 | X3: =D3+G3+J3+M3+P3+S3+V3 -> 9.0815 | Y3: =C3+F3+I3+L3+O3+R3+U3 -> 6.86 | Z3: =X3/Y3 -> 1.3238338 | AA3: 14 | AB3: =X3/AA3 -> 0.64867857
A4: 西北大区部 | B4: 呼和浩特 | C4: 1.3 | D4: 2.1779 | E4: =D4/C4 -> 1.6753077 | F4: 0.39 | G4: 1.5858 | H4: =G4/F4 -> 4.0661538 | I4: 0.78 | J4: 0.5453 | K4: =J4/I4 -> 0.69910256 | L4: 0.91 | M4: 0.625 | N4: =M4/L4 -> 0.68681319 | O4: 0.91 | P4: 0.59425 | Q4: =P4/O4 -> 0.65302198 | R4: 0.91 | S4: 0.99673 | T4: =S4/R4 -> 1.0953077 | U4: 1.17 | V4: 0.71624 | W4: =V4/U4 -> 0.61217094 | X4: =D4+G4+J4+M4+P4+S4+V4 -> 7.24122 | Y4: =C4+F4+I4+L4+O4+R4+U4 -> 6.37 | Z4: =X4/Y4 -> 1.1367692 | AA4: 13 | AB4: =X4/AA4 -> 0.55701692
A5: 西北大区部 | B5: 兰州 | C5: 2.6 | D5: 3.70684 | E5: =D5/C5 -> 1.4257077 | F5: 0.78 | G5: 2.03603 | H5: =G5/F5 -> 2.6102949 | I5: 1.56 | J5: 1.34464 | K5: =J5/I5 -> 0.86194872 | L5: 1.82 | M5: 1.81131 | N5: =M5/L5 -> 0.99522527 | O5: 1.82 | P5: 1.76603 | Q5: =P5/O5 -> 0.97034615 | R5: 1.82 | S5: 2.22672 | T5: =S5/R5 -> 1.2234725 | U5: 2.34 | V5: 1.66925 | W5: =V5/U5 -> 0.7133547 | X5: =D5+G5+J5+M5+P5+S5+V5 -> 14.56082 | Y5: =C5+F5+I5+L5+O5+R5+U5 -> 12.74 | Z5: =X5/Y5 -> 1.1429215 | AA5: 26 | AB5: =X5/AA5 -> 0.56003154
A6: 西北大区部 | B6: 宁夏 | C6: 3.9 | D6: 8.38619 | E6: =D6/C6 -> 2.1503051 | F6: 1.17 | G6: 3.64579 | H6: =G6/F6 -> 3.1160598 | I6: 2.34 | J6: 3.85349 | K6: =J6/I6 -> 1.6467906 | L6: 2.73 | M6: 3.44269 | N6: =M6/L6 -> 1.2610586 | O6: 2.73 | P6: 3.77583 | Q6: =P6/O6 -> 1.3830879 | R6: 2.73 | S6: 4.68681 | T6: =S6/R6 -> 1.7167802 | U6: 3.51 | V6: 4.71917 | W6: =V6/U6 -> 1.3444929 | X6: =D6+G6+J6+M6+P6+S6+V6 -> 32.50997 | Y6: =C6+F6+I6+L6+O6+R6+U6 -> 19.11 | Z6: =X6/Y6 -> 1.701202 | AA6: 39 | AB6: =X6/AA6 -> 0.83358897
A7: 西北大区部 | B7: 西宁 | C7: 0.5 | D7: 0.41163 | E7: =D7/C7 -> 0.82326 | F7: 0.15 | G7: 0.20175 | H7: =G7/F7 -> 1.345 | I7: 0.3 | J7: 0.19111 | K7: =J7/I7 -> 0.63703333 | L7: 0.35 | M7: 0.31228 | N7: =M7/L7 -> 0.89222857 | O7: 0.35 | P7: 0.32253 | Q7: =P7/O7 -> 0.92151429 | R7: 0.35 | S7: 0.4209 | T7: =S7/R7 -> 1.2025714 | U7: 0.45 | V7: 0.49436 | W7: =V7/U7 -> 1.0985778 | X7: =D7+G7+J7+M7+P7+S7+V7 -> 2.35456 | Y7: =C7+F7+I7+L7+O7+R7+U7 -> 2.45 | Z7: =X7/Y7 -> 0.9610449 | AA7: 5 | AB7: =X7/AA7 -> 0.470912
A8: 西北大区部 | B8: 新疆 | C8: 5.4 | D8: 5.9093 | E8: =D8/C8 -> 1.0943148 | F8: 1.62 | G8: 5.70766 | H8: =G8/F8 -> 3.5232469 | I8: 3.24 | J8: 3.42184 | K8: =J8/I8 -> 1.0561235 | L8: 3.78 | M8: 3.59159 | N8: =M8/L8 -> 0.95015608 | O8: 3.78 | P8: 4.59376 | Q8: =P8/O8 -> 1.2152804 | R8: 3.78 | S8: 4.16714 | T8: =S8/R8 -> 1.102418 | U8: 4.86 | V8: 5.16552 | W8: =V8/U8 -> 1.0628642 | X8: =D8+G8+J8+M8+P8+S8+V8 -> 32.55681 | Y8: =C8+F8+I8+L8+O8+R8+U8 -> 26.46 | Z8: =X8/Y8 -> 1.2304161 | AA8: 54 | AB8: =X8/AA8 -> 0.60290389
A9: 西北大区部 | B9: 小计 | C9: =SUM(C3:C8) -> 15.1 | D9: 23.43666 | E9: =D9/C9 -> 1.5520967 | F9: 4.53 | G9: 15.11883 | H9: =G9/F9 -> 3.3374901 | I9: 9.06 | J9: 9.79688 | K9: =J9/I9 -> 1.0813333 | L9: 10.57 | M9: 10.76367 | N9: =M9/L9 -> 1.0183226 | O9: 10.57 | P9: 11.9396 | Q9: =P9/O9 -> 1.1295743 | R9: 10.57 | S9: =SUM(S3:S8) -> 13.5596 | T9: =S9/R9 -> 1.2828382 | U9: =SUM(U3:U8) -> 13.59 | V9: =SUM(V3:V8) -> 13.68964 | W9: =V9/U9 -> 1.0073319 | X9: =D9+G9+J9+M9+P9+S9+V9 -> 98.30488 | Y9: =C9+F9+I9+L9+O9+R9+U9 -> 73.99 | Z9: =X9/Y9 -> 1.3286239 | AA9: =SUM(AA3:AA8) -> 151 | AB9: =X9/AA9 -> 0.6510257

Sheet 大保养占比
A1: 西北大区7.28-8.4大保养占比
A2: 办事处 | B2: 油烟机清洗数 | C2: 大保养清洗数 | D2: 大保养占比
A3: 新疆办事处 | B3: 101 | C3: 1 | D3: =C3/B3 -> 0.0099009901
A4: 宁夏办事处 | B4: 54 | C4: 4 | D4: =C4/B4 -> 0.074074074
A5: 兰州办事处 | B5: 22 | C5: 0 | D5: =C5/B5 -> 0
A6: 呼和浩特办事处 | B6: 19 | C6: 0 | D6: =C6/B6 -> 0
A7: 包头办事处 | B7: 8 | C7: 0 | D7: =C7/B7 -> 0
A8: 西宁办事处 | B8: 2 | C8: 0 | D8: =C8/B8 -> 0
A9: 小计 | B9: =SUM(B3:B8) -> 206 | C9: =SUM(C3:C8) -> 5 | D9: =C9/B9 -> 0.024271845

Sheet 工单自购配件明细
A1: 自购配件收费金额 | B1: 折扣金额 | C1: 预约上门时间 | D1: 工单折扣费用 | E1: 工单折扣原因 | F1: 服务网点 | G1: 产品组 | H1: 工单应收费用总计 | I1: 工单实收费用 | J1: 诉求编号 | K1: 录入完成时间 | L1: 服务项目 | M1: 服务中心 | N1: 配件名称 | O1: 工单编号 | P1: 大区部 | Q1: 客户期望时间 | R1: 服务工程师 | S1: 工单状态 | T1: 配件数量 | U1: 配件备注 | V1: 核销码状态 | W1: 电商订单行GUID | X1: 物料编码 | Y1: 滤芯机身码 | Z1: 平台渠道 | AA1: 配件条码 | AB1: 物料名称 | AC1: 工程师编号
A2: 90 | C2: 46231.417 | F2: 呼和浩特市凯多丰电器服务维修有限公司 | G2: 灶具 | H2: 90 | I2: 90 | J2: 20260727-01-11189 | K2: 46231.45 | L2: 调试 | M2: 呼和浩特服务中心 | N2: 网点买断 | O2: FGDG20260727010215 | P2: 西北大区部 | Q2: 46231 | R2: 刘伟 | S2: 已完工 | T2: 1 | X2: 1507020201523 | AA2: 1507020201523-260428014705 | AB2: 气路不锈钢波纹软管-螺纹+插口-1000-套塑-WJ(CCC) | AC2: JS000003431
A3: 40 | C3: 46231.417 | D3: 0 | E3: 客户端授权减免 | F3: 土默特左旗金誉良电气安装服务部 | G3: 水槽洗碗机 | H3: 40 | I3: 40 | J3: 20260726-01-22131 | K3: 46231.461 | L3: 洗碗机改装(水槽用户) | M3: 呼和浩特服务中心 | N3: 铜活接三通 | O3: FGDG20260726019417 | P3: 西北大区部 | Q3: 46231 | R3: 张磊 | S3: 已完工 | T3: 1 | AC3: JS000026353
A4: 60 | C4: 46231.583 | F4: 土默特左旗金誉良电气安装服务部 | G4: 水槽洗碗机 | H4: 100 | I4: 100 | J4: 20260727-01-11218 | K4: 46231.52 | L4: 安装 | M4: 呼和浩特服务中心 | N4: 铜角阀（水） | O4: FGDG20260727010241 | P4: 西北大区部 | Q4: 46231 | R4: 张磊 | S4: 已完工 | T4: 1 | AC4: JS000026353
A5: 40 | C5: 46231.583 | F5: 土默特左旗金誉良电气安装服务部 | G5: 水槽洗碗机 | H5: 100 | I5: 100 | J5: 20260727-01-11218 | K5: 46231.52 | L5: 安装 | M5: 呼和浩特服务中心 | N5: 铜活接三通 | O5: FGDG20260727010241 | P5: 西北大区部 | Q5: 46231 | R5: 张磊 | S5: 已完工 | T5: 1 | AC5: JS000026353
A6: 120 | C6: 46231.458 | F6: 土默特左旗金誉良电气安装服务部 | G6: 水槽洗碗机 | H6: 205 | I6: 205 | J6: 20260727-01-35035 | K6: 46231.546 | L6: 安装 | M6: 呼和浩特服务中心 | N6: 铜角阀（水） | O6: FGDG20260727030258 | P6: 西北大区部 | Q6: 46231 | R6: 刘晓丰 | S6: 已完工 | T6: 2 | AC6: JS000029708
A7: 45 | C7: 46231.458 | F7: 土默特左旗金誉良电气安装服务部 | G7: 水槽洗碗机 | H7: 205 | I7: 205 | J7: 20260727-01-35035 | K7: 46231.546 | L7: 安装 | M7: 呼和浩特服务中心 | N7: 编织软管 | O7: FGDG20260727030258 | P7: 西北大区部 | Q7: 46231 | R7: 刘晓丰 | S7: 已完工 | T7: 1 | AC7: JS000029708
A8: 90 | C8: 46231.625 | F8: 呼和浩特市回民区彦辰家电维修经营部 | G8: 灶具 | H8: 90 | I8: 90 | J8: 20260727-01-01553 | K8: 46231.561 | L8: 调试 | M8: 呼和浩特服务中心 | N8: 网点买断 | O8: FGDG20260727001432 | P8: 西北大区部 | Q8: 46231 | R8: 王鹏 | S8: 已完工 | T8: 1 | X8: 1507020201523 | AA8: 1507020201523-260608019484 | AB8: 气路不锈钢波纹软管-螺纹+插口-1000-套塑-WJ(CCC) | AC8: JS000043198
A9: 0 | C9: 46231.646 | D9: 0 | E9: 客户端授权减免 | F9: 土默特左旗金誉良电气安装服务部 | G9: 水槽洗碗机 | H9: 0 | I9: 0 | J9: 20260727-01-12757 | K9: 46231.696 | L9: 安装 | M9: 呼和浩特服务中心 | N9: 铜角阀（水） | O9: FGDG20260727011633 | P9: 西北大区部 | Q9: 46231 | R9: 张磊 | S9: 已完工 | T9: 2 | AC9: JS000026353
A10: 0 | C10: 46231.646 | D10: 0 | E10: 客户端授权减免 | F10: 土默特左旗金誉良电气安装服务部 | G10: 水槽洗碗机 | H10: 0 | I10: 0 | J10: 20260727-01-12757 | K10: 46231.696 | L10: 安装 | M10: 呼和浩特服务中心 | N10: 铜活接三通 | O10: FGDG20260727011633 | P10: 西北大区部 | Q10: 46231 | R10: 张磊 | S10: 已完工 | T10: 1 | AC10: JS000026353
A11: 90 | C11: 46231.583 | F11: 土默特左旗金誉良电气安装服务部 | G11: 灶具 | H11: 90 | I11: 90 | J11: 20260727-01-22479 | K11: 46231.71 | L11: 灶具放置 | M11: 呼和浩特服务中心 | N11: 网点买断 | O11: FGDG20260727019634 | P11: 西北大区部 | Q11: 46231 | R11: 刘晓丰 | S11: 已完工 | T11: 1 | X11: 1507020201523 | AA11: 1507020201523-260622017970 | AB11: 气路不锈钢波纹软管-螺纹+插口-1000-套塑-WJ(CCC) | AC11: JS000029708
A12: 90 | C12: 46231 | F12: 土默特左旗金誉良电气安装服务部 | G12: 灶具 | H12: 90 | I12: 90 | J12: 20260726-01-12701 | K12: 46231.756 | L12: 调试 | M12: 呼和浩特服务中心 | N12: 网点买断 | O12: FGDG20260726011521 | P12: 西北大区部 | Q12: 46229 | R12: 刘晓丰 | S12: 已完工 | T12: 1 | X12: 1507020201523 | AA12: 1507020201523-260622017950 | AB12: 气路不锈钢波纹软管-螺纹+插口-1000-套塑-WJ(CCC) | AC12: JS000029708
A13: 90 | C13: 46232.417 | F13: 呼和浩特市凯多丰电器服务维修有限公司 | G13: 灶具 | H13: 90 | I13: 90 | J13: 20260728-01-00089 | K13: 46232.404 | L13: 灶具放置 | M13: 呼和浩特服务中心 | N13: 网点买断 | O13: FGDG20260728000079 | P13: 西北大区部 | Q13: 46232.417 | R13: 刘伟 | S13: 已完工 | T13: 1 | X13: 1507020201523 | AA13: 1507020201523-260622017951 | AB13: 气路不锈钢波纹软管-螺纹+插口-1000-套塑-WJ(CCC) | AC13: JS000003431
A14: 28 | C14: 46232.417 | D14: 0 | E14: 其他 | F14: 内蒙古洁莱电器安装服务有限公司 | G14: 水槽洗碗机 | H14: 248 | I14: 248 | J14: 20260727-01-30120 | K14: 46232.513 | L14: 洗碗机改装(水槽用户) | M14: 呼和浩特服务中心 | N14: 纯PPR管材 | O14: FGDG20260727025997 | P14: 西北大区部 | Q14: 46232 | R14: 侯小乐 | S14: 已完工 | T14: 1 | AC14: JS000025735
A15: 70 | C15: 46232.417 | D15: 0 | E15: 其他 | F15: 内蒙古洁莱电器安装服务有限公司 | G15: 水槽洗碗机 | H15: 248 | I15: 248 | J15: 20260727-01-30120 | K15: 46232.513 | L15: 洗碗机改装(水槽用户) | M15: 呼和浩特服务中心 | N15: 外丝弯头 | O15: FGDG20260727025997 | P15: 西北大区部 | Q15: 46232 | R15: 侯小乐 | S15: 已完工 | T15: 1 | AC15: JS000025735
A16: 30 | C16: 46232.417 | D16: 0 | E16: 其他 | F16: 内蒙古洁莱电器安装服务有限公司 | G16: 水槽洗碗机 | H16: 248 | I16: 248 | J16: 20260727-01-30120 | K16: 46232.513 | L16: 洗碗机改装(水槽用户) | M16: 呼和浩特服务中心 | N16: PPR接头（不带丝） | O16: FGDG20260727025997 | P16: 西北大区部 | Q16: 46232 | R16: 侯小乐 | S16: 已完工 | T16: 3 | AC16: JS000025735
A17: 120 | C17: 46232.417 | D17: 0 | E17: 其他 | F17: 内蒙古洁莱电器安装服务有限公司 | G17: 水槽洗碗机 | H17: 248 | I17: 248 | J17: 20260727-01-30120 | K17: 46232.513 | L17: 洗碗机改装(水槽用户) | M17: 呼和浩特服务中心 | N17: 内丝三通 | O17: FGDG20260727025997 | P17: 西北大区部 | Q17: 46232 | R17: 侯小乐 | S17: 已完工 | T17: 2 | AC17: JS000025735
A18: 120 | C18: 46232.417 | F18: 土默特左旗金誉良电气安装服务部 | G18: 水槽洗碗机 | H18: 160 | I18: 160 | J18: 20260728-01-28471 | K18: 46232.52 | L18: 安装 | M18: 呼和浩特服务中心 | N18: 铜角阀（水） | O18: FGDG20260728024583 | P18: 西北大区部 | Q18: 46232 | R18: 刘晓丰 | S18: 已完工 | T18: 2 | AC18: JS000029708
A19: 90 | C19: 46232.417 | F19: 土默特左旗金誉良电气安装服务部 | G19: 灶具 | H19: 90 | I19: 90 | J19: 20260727-01-07521 | K19: 46232.525 | L19: 调试 | M19: 呼和浩特服务中心 | N19: 网点买断 | O19: FGDG20260727006926 | P19: 西北大区部 | Q19: 46232 | R19: 张磊 | S19: 已完工 | T19: 1 | X19: 1507020201530 | AA19: 1507020201530-260608014803 | AB19: 气路不锈钢波纹软管-螺纹+插口-1500-套塑-WJ(CCC) | AC19: JS000026353
A20: 90 | C20: 46232.625 | F20: 土默特左旗金誉良电气安装服务部 | G20: 灶具 | H20: 90 | I20: 90 | J20: 20260728-01-06074 | K20: 46232.645 | L20: 调试 | M20: 呼和浩特服务中心 | N20: 网点买断 | O20: FGDG20260728005572 | P20: 西北大区部 | Q20: 46232.625 | R20: 刘晓丰 | S20: 已完工 | T20: 1 | X20: 1507020201523 | AA20: 1507020201523-260622018148 | AB20: 气路不锈钢波纹软管-螺纹+插口-1000-套塑-WJ(CCC) | AC20: JS000029708
A21: 40 | C21: 46232.625 | F21: 土默特左旗占平安装维修部 | G21: 水槽洗碗机 | H21: 160 | I21: 160 | J21: 20260728-01-31889 | K21: 46232.728 | L21: 安装 | M21: 呼和浩特服务中心 | N21: 铜活接三通 | O21: FGDG20260728027649 | P21: 西北大区部 | Q21: 46232.625 | R21: 赵拴钱 | S21: 已完工 | T21: 1 | AC21: JS000039518
A22: 120 | C22: 46232.625 | F22: 土默特左旗占平安装维修部 | G22: 水槽洗碗机 | H22: 160 | I22: 160 | J22: 20260728-01-31889 | K22: 46232.728 | L22: 安装 | M22: 呼和浩特服务中心 | N22: 铜角阀（水） | O22: FGDG20260728027649 | P22: 西北大区部 | Q22: 46232.625 | R22: 赵拴钱 | S22: 已完工 | T22: 2 | AC22: JS000039518
A23: 180 | C23: 46232.417 | F23: 土默特左旗占平安装维修部 | G23: 水槽洗碗机 | H23: 280 | I23: 280 | J23: 20260726-01-14169 | K23: 46232.765 | L23: 安装 | M23: 呼和浩特服务中心 | N23: 铜角阀（水） | O23: FGDG20260726012745 | P23: 西北大区部 | Q23: 46230.542 | R23: 妥晓勇 | S23: 已完工 | T23: 3 | AC23: JS000034706
A24: 90 | C24: 46232.417 | F24: 土默特左旗占平安装维修部 | G24: 水槽洗碗机 | H24: 280 | I24: 280 | J24: 20260726-01-14169 | K24: 46232.765 | L24: 安装 | M24: 呼和浩特服务中心 | N24: 编织软管 | O24: FGDG20260726012745 | P24: 西北大区部 | Q24: 46230.542 | R24: 妥晓勇 | S24: 已完工 | T24: 2 | AC24: JS000034706
A25: 10 | C25: 46232.417 | F25: 土默特左旗占平安装维修部 | G25: 水槽洗碗机 | H25: 280 | I25: 280 | J25: 20260726-01-14169 | K25: 46232.765 | L25: 安装 | M25: 呼和浩特服务中心 | N25: 水路对丝 | O25: FGDG20260726012745 | P25: 西北大区部 | Q25: 46230.542 | R25: 妥晓勇 | S25: 已完工 | T25: 1 | AC25: JS000034706
A26: 120 | C26: 46233.417 | F26: 土默特左旗金誉良电气安装服务部 | G26: 热水器 | H26: 175 | I26: 175 | J26: 20260728-01-26577 | K26: 46233.478 | L26: 安装 | M26: 呼和浩特服务中心 | N26: 铜角阀（水） | O26: FGDG20260728022946 | P26: 西北大区部 | Q26: 46233.417 | R26: 张加良 | S26: 已完工 | T26: 2 | AC26: JS000024561
A27: 90 | C27: 46233.417 | F27: 土默特左旗金誉良电气安装服务部 | G27: 灶具 | H27: 90 | I27: 90 | J27: 20260729-01-01879 | K27: 46233.492 | L27: 调试 | M27: 呼和浩特服务中心 | N27: 网点买断 | O27: FGDG20260729001782 | P27: 西北大区部 | Q27: 46233 | R27: 张磊 | S27: 已完工 | T27: 1 | X27: 1507020201523 | AA27: 1507020201523-260608019480 | AB27: 气路不锈钢波纹软管-螺纹+插口-1000-套塑-WJ(CCC) | AC27: JS000026353
A28: 120 | C28: 46233.625 | F28: 呼和浩特市凯多丰电器服务维修有限公司 | G28: 灶具 | H28: 120 | I28: 120 | J28: 20260730-01-09698 | K28: 46233.588 | L28: 调试 | M28: 呼和浩特服务中心 | N28: 网点买断 | O28: FGDG20260730009122 | P28: 西北大区部 | Q28: 46233.625 | R28: 刘伟 | S28: 已完工 | T28: 1 | X28: 1507020201530 | AA28: 1507020201530-260617000188 | AB28: 气路不锈钢波纹软管-螺纹+插口-1500-套塑-WJ(CCC) | AC28: JS000003431
A29: 58 | C29: 46234.145 | F29: 内蒙古洁莱电器安装服务有限公司 | G29: 水槽洗碗机 | H29: 98 | I29: 98 | J29: 20260728-01-15572 | K29: 46234.368 | L29: 安装 | M29: 呼和浩特服务中心 | N29: 网点买断 | O29: FGDG20260728013772 | P29: 西北大区部 | Q29: 46233 | R29: 雷锁锁 | S29: 已完工 | T29: 1 | X29: 1506040100621 | AA29: 1506040100621-260521005580 | AB29: 洗碗机专用洗涤粉-1KG/瓶(含包装盒)-/FW | AC29: JS000020273
A30: 90 | C30: 46234.458 | F30: 内蒙古洁莱电器安装服务有限公司 | G30: 灶具 | H30: 90 | I30: 90 | J30: 20260730-01-33350 | K30: 46234.438 | L30: 调试 | M30: 呼和浩特服务中心 | N30: 网点买断 | O30: FGDG20260730029529 | P30: 西北大区部 | Q30: 46234 | R30: 雷锁锁 | S30: 已完工 | T30: 1 | X30: 1507020201523 | AA30: 1507020201523-260622017942 | AB30: 气路不锈钢波纹软管-螺纹+插口-1000-套塑-WJ(CCC) | AC30: JS000020273
A31: 90 | C31: 46234.438 | F31: 土默特左旗金誉良电气安装服务部 | G31: 灶具 | H31: 90 | I31: 90 | J31: 20260731-01-07284 | K31: 46234.446 | L31: 灶具放置 | M31: 呼和浩特服务中心 | N31: 网点买断 | O31: FGDG20260731006820 | P31: 西北大区部 | Q31: 46234 | R31: 刘晓丰 | S31: 已完工 | T31: 1 | X31: 1507020201523 | AA31: 1507020201523-260622018076 | AB31: 气路不锈钢波纹软管-螺纹+插口-1000-套塑-WJ(CCC) | AC31: JS000029708
A32: 90 | C32: 46234.417 | F32: 土默特左旗金誉良电气安装服务部 | G32: 水槽洗碗机 | H32: 130 | I32: 130 | J32: 20260730-01-22062 | K32: 46234.481 | L32: 安装 | M32: 呼和浩特服务中心 | N32: 编织软管 | O32: FGDG20260730019727 | P32: 西北大区部 | Q32: 46234 | R32: 张加良 | S32: 已完工 | T32: 2 | AC32: JS000024561
A33: 90 | C33: 46234.417 | F33: 呼和浩特市回民区彦辰家电维修经营部 | G33: 灶具 | H33: 110 | I33: 110 | J33: 20260729-01-01430 | K33: 46234.559 | L33: 调试 | M33: 呼和浩特服务中心 | N33: 网点买断 | O33: FGDG20260729001313 | P33: 西北大区部 | Q33: 46234 | R33: 侯慧忠 | S33: 已完工 | T33: 1 | X33: 1507020201523 | AA33: 1507020201523-260622017963 | AB33: 气路不锈钢波纹软管-螺纹+插口-1000-套塑-WJ(CCC) | AC33: JS000015636
A34: 90 | C34: 46234.647 | F34: 内蒙古萱圆居民日常生活服务有限公司 | G34: 灶具 | H34: 90 | I34: 90 | J34: 20260730-01-14559 | K34: 46234.627 | L34: 调试 | M34: 呼和浩特服务中心 | N34: 网点买断 | O34: FGDG20260730013403 | P34: 西北大区部 | Q34: 46234.333 | R34: 李永强 | S34: 已完工 | T34: 1 | X34: 1507020201523 | AA34: 1507020201523-260309016216 | AB34: 气路不锈钢波纹软管-螺纹+插口-1000-套塑-WJ(CCC) | AC34: JS000042742
A35: 60 | C35: 46234.645 | F35: 土默特左旗占平安装维修部 | G35: 水槽洗碗机 | H35: 100 | I35: 100 | J35: 20260731-01-16213 | K35: 46234.693 | L35: 安装 | M35: 呼和浩特服务中心 | N35: 铜角阀（水） | O35: FGDG20260731014622 | P35: 西北大区部 | Q35: 46234 | R35: 赵拴钱 | S35: 已完工 | T35: 1 | AC35: JS000039518
A36: 40 | C36: 46234.645 | F36: 土默特左旗占平安装维修部 | G36: 水槽洗碗机 | H36: 100 | I36: 100 | J36: 20260731-01-16213 | K36: 46234.693 | L36: 安装 | M36: 呼和浩特服务中心 | N36: 铜活接三通 | O36: FGDG20260731014622 | P36: 西北大区部 | Q36: 46234 | R36: 赵拴钱 | S36: 已完工 | T36: 1 | AC36: JS000039518
A37: 60 | C37: 46235 | F37: 土默特左旗占平安装维修部 | G37: 嵌入式洗碗机 | H37: 60 | I37: 60 | J37: 20260731-01-19682 | K37: 46235.427 | L37: 安装 | M37: 呼和浩特服务中心 | N37: 铜角阀（水） | O37: FGDG20260731017647 | P37: 西北大区部 | Q37: 46234 | R37: 妥晓勇 | S37: 已完工 | T37: 1 | AC37: JS000034706
A38: 90 | C38: 46235.354 | F38: 土默特左旗金誉良电气安装服务部 | G38: 灶具 | H38: 90 | I38: 90 | J38: 20260729-01-23833 | K38: 46235.438 | L38: 灶具放置 | M38: 呼和浩特服务中心 | N38: 网点买断 | O38: FGDG20260729021218 | P38: 西北大区部 | Q38: 46235.417 | R38: 刘晓丰 | S38: 已完工 | T38: 1 | X38: 1507020201523 | AA38: 1507020201523-260622018077 | AB38: 气路不锈钢波纹软管-螺纹+插口-1000-套塑-WJ(CCC) | AC38: JS000029708
A39: 90 | C39: 46235.458 | F39: 土默特左旗金誉良电气安装服务部 | G39: 灶具 | H39: 90 | I39: 90 | J39: 20260731-01-29265 | K39: 46235.471 | L39: 灶具放置 | M39: 呼和浩特服务中心 | N39: 网点买断 | O39: FGDG20260731025758 | P39: 西北大区部 | Q39: 46235 | R39: 刘晓丰 | S39: 已完工 | T39: 1 | X39: 1507020201523 | AA39: 1507020201523-260622018147 | AB39: 气路不锈钢波纹软管-螺纹+插口-1000-套塑-WJ(CCC) | AC39: JS000029708
A40: 135 | C40: 46235 | F40: 呼和浩特市凯多丰电器服务维修有限公司 | G40: 水槽洗碗机 | H40: 135 | I40: 135 | J40: 20260801-01-11242 | K40: 46235.485 | L40: 安装 | M40: 呼和浩特服务中心 | N40: 铜角阀（水） | O40: FGDG20260801010110 | P40: 西北大区部 | Q40: 46235 | R40: 刘伟 | S40: 已完工 | T40: 3 | AC40: JS000003431
A41: 40 | C41: 46235.125 | F41: 内蒙古洁莱电器安装服务有限公司 | G41: 水槽洗碗机 | H41: 40 | I41: 40 | J41: 20260731-01-28954 | K41: 46235.505 | L41: 安装 | M41: 呼和浩特服务中心 | N41: 铜活接三通 | O41: FGDG20260731025480 | P41: 西北大区部 | Q41: 46235 | R41: 侯小乐 | S41: 已完工 | T41: 1 | AC41: JS000025735
